Workbook

Sheet Bets
A1: Bet ID | B1: Bettor | C1: Date posted (CT) | D1: Day of week (posted) | E1: Game date | F1: Game day of week | G1: Game kickoff time (ET) | H1: Prime time (Y/N) | I1: Prime time slot | J1: Sport category | K1: League/event | L1: Bet type | M1: Selection/legs | N1: # legs | O1: Odds (American) | P1: Odds (decimal) | Q1: Stake $ | R1: Units | S1: To win/payout $ (total return) | T1: Book/platform | U1: Result | V1: Profit/Loss $ | W1: Profit/Loss units | X1: Result source | Y1: Sponsored/promo flag | Z1: Post URL | AA1: Notes | AB1: Single vs parlay | AC1: Settled $ stake (helper) | AD1: Settled units (helper)
A2: T-578065 | B2: Trent | C2: 46235.522 | D2: =IF(C2="","",TEXT(C2,"dddd")) | E2: 46235 | F2: =IF(E2="","",TEXT(E2,"dddd")) | G2: 9:38 PM | H2: N | J2: MLB | K2: MLB | L2: parlay | M2: TB ML -160; PHI ML -138; LAD ML -156; MIL ML -112 | N2: 4 | O2: +770 | P2: 8.7 | Q2: 1000 | S2: 7700 | T2: Pikkit | U2: L | V2: =IF(NOT(ISNUMBER(Q2)),"",IF(U2="W",IF(ISNUMBER(S2),S2-Q2,IF(ISNUMBER(P2),Q2*(P2-1),"")),IF(U2="L",-Q2,IF(U2="Push",0,"")))) | W2: =IF(NOT(ISNUMBER(R2)),"",IF(U2="W",IF(ISNUMBER(P2),R2*(P2-1),""),IF(U2="L",-R2,IF(U2="Push",0,"")))) | X2: graded from final | Y2: N | Z2: https://x.com/BookitWithTrent/status/2083606714033578065 | AA2: "Last Chance U slip" | AB2: Parlay/multi-leg | AC2: =IF(ISNUMBER(V2),Q2,"") | AD2: =IF(ISNUMBER(W2),R2,"")
A3: T-134103 | B3: Trent | C3: 46236.508 | D3: =IF(C3="","",TEXT(C3,"dddd")) | E3: 46236 | F3: =IF(E3="","",TEXT(E3,"dddd")) | G3: not matched | H3: N | J3: Other | K3: PLL Lacrosse | L3: ML | M3: New York Atlas ML | N3: 1 | O3: not shown | R3: not shown | T3: not shown | U3: Unknown | V3: =IF(NOT(ISNUMBER(Q3)),"",IF(U3="W",IF(ISNUMBER(S3),S3-Q3,IF(ISNUMBER(P3),Q3*(P3-1),"")),IF(U3="L",-Q3,IF(U3="Push",0,"")))) | W3: =IF(NOT(ISNUMBER(R3)),"",IF(U3="W",IF(ISNUMBER(P3),R3*(P3-1),""),IF(U3="L",-R3,IF(U3="Push",0,"")))) | X3: unverified | Y3: N | Z3: https://x.com/BookitWithTrent/status/2083963819387134103 | AA3: "Mortal mega" (unit size not stated); Game date assumed = post date (CT) | AB3: Single | AC3: =IF(ISNUMBER(V3),Q3,"") | AD3: =IF(ISNUMBER(W3),R3,"")
A4: T-418015 | B4: Trent | C4: 46237.596 | D4: =IF(C4="","",TEXT(C4,"dddd")) | E4: 46237 | F4: =IF(E4="","",TEXT(E4,"dddd")) | G4: not matched | H4: N | J4: MLB | K4: MLB | L4: PrizePicks/DFS | M4: James Wood o7 HFS; Ben Rice o6.5 HFS; Jeremy Pena o7 HFS; Junior Caminero o9.5 HFS | N4: 4 | O4: not shown | P4: 10 | Q4: 500 | S4: 5000 | T4: PrizePicks | U4: L | V4: =IF(NOT(ISNUMBER(Q4)),"",IF(U4="W",IF(ISNUMBER(S4),S4-Q4,IF(ISNUMBER(P4),Q4*(P4-1),"")),IF(U4="L",-Q4,IF(U4="Push",0,"")))) | W4: =IF(NOT(ISNUMBER(R4)),"",IF(U4="W",IF(ISNUMBER(P4),R4*(P4-1),""),IF(U4="L",-R4,IF(U4="Push",0,"")))) | X4: graded from final | Y4: N | Z4: https://x.com/BookitWithTrent/status/2084358270215418015 | AA4: 4-pick power play; Final: Wood 1 single (3 HFS) < 7; Decimal odds derived from payout/stake | AB4: Parlay/multi-leg | AC4: =IF(ISNUMBER(V4),Q4,"") | AD4: =IF(ISNUMBER(W4),R4,"")
A5: T-128707 | B5: Trent | C5: 46237.952 | D5: =IF(C5="","",TEXT(C5,"dddd")) | E5: 46237 | F5: =IF(E5="","",TEXT(E5,"dddd")) | G5: 8:40 PM | H5: N | J5: MLB | K5: MLB | L5: parlay | M5: Brewers ML; Dodgers ML; Rays ML; Yankees ML | N5: 4 | O5: +800 | P5: 9 | Q5: 1000 | S5: 7000 | T5: Pikkit | U5: L | V5: =IF(NOT(ISNUMBER(Q5)),"",IF(U5="W",IF(ISNUMBER(S5),S5-Q5,IF(ISNUMBER(P5),Q5*(P5-1),"")),IF(U5="L",-Q5,IF(U5="Push",0,"")))) | W5: =IF(NOT(ISNUMBER(R5)),"",IF(U5="W",IF(ISNUMBER(P5),R5*(P5-1),""),IF(U5="L",-R5,IF(U5="Push",0,"")))) | X5: posted | Y5: N | Z5: https://x.com/BookitWithTrent/status/2084487077245128707 | AA5: "Fugazi Four"; slip shows +800 but payout $7,000; result slip shows 3 legs lost | AB5: Parlay/multi-leg | AC5: =IF(ISNUMBER(V5),Q5,"") | AD5: =IF(ISNUMBER(W5),R5,"")
A6: T-653770 | B6: Trent | C6: 46238.444 | D6: =IF(C6="","",TEXT(C6,"dddd")) | E6: 46238 | F6: =IF(E6="","",TEXT(E6,"dddd")) | G6: not matched | H6: N | J6: MLB | K6: MLB | L6: PrizePicks/DFS | M6: Jesus Luzardo o7.5 K; Tarik Skubal o7.5 K; Yordan Alvarez o6.5 HFS; Junior Caminero o2.5 H+R+RBI | N6: 4 | O6: not shown | P6: 10 | Q6: 1000 | S6: 10000 | T6: PrizePicks | U6: L | V6: =IF(NOT(ISNUMBER(Q6)),"",IF(U6="W",IF(ISNUMBER(S6),S6-Q6,IF(ISNUMBER(P6),Q6*(P6-1),"")),IF(U6="L",-Q6,IF(U6="Push",0,"")))) | W6: =IF(NOT(ISNUMBER(R6)),"",IF(U6="W",IF(ISNUMBER(P6),R6*(P6-1),""),IF(U6="L",-R6,IF(U6="Push",0,"")))) | X6: graded from final | Y6: N | Z6: https://x.com/BookitWithTrent/status/2084665349379653770 | AA6: Final: Luzardo 7 K, Skubal 6 K; Decimal odds derived from payout/stake | AB6: Parlay/multi-leg | AC6: =IF(ISNUMBER(V6),Q6,"") | AD6: =IF(ISNUMBER(W6),R6,"")
A7: T-732627 | B7: Trent | C7: 46238.475 | D7: =IF(C7="","",TEXT(C7,"dddd")) | E7: 46238 | F7: =IF(E7="","",TEXT(E7,"dddd")) | G7: not matched | H7: N | J7: MLB | K7: MLB | L7: PrizePicks/DFS | M7: Matt Olson HR; Shohei Ohtani HR; Yordan Alvarez HR; Junior Caminero HR (each o0.5) | N7: 4 | O7: not shown | P7: 82 | Q7: 250 | S7: 20500 | T7: PrizePicks | U7: L | V7: =IF(NOT(ISNUMBER(Q7)),"",IF(U7="W",IF(ISNUMBER(S7),S7-Q7,IF(ISNUMBER(P7),Q7*(P7-1),"")),IF(U7="L",-Q7,IF(U7="Push",0,"")))) | W7: =IF(NOT(ISNUMBER(R7)),"",IF(U7="W",IF(ISNUMBER(P7),R7*(P7-1),""),IF(U7="L",-R7,IF(U7="Push",0,"")))) | X7: graded from final | Y7: N | Z7: https://x.com/BookitWithTrent/status/2084676777360732627 | AA7: Final: Olson/Ohtani/Alvarez no HR; Decimal odds derived from payout/stake | AB7: Parlay/multi-leg | AC7: =IF(ISNUMBER(V7),Q7,"") | AD7: =IF(ISNUMBER(W7),R7,"")
A8: T-020893 | B8: Trent | C8: 46238.536 | D8: =IF(C8="","",TEXT(C8,"dddd")) | E8: 46238 | F8: =IF(E8="","",TEXT(E8,"dddd")) | G8: not matched | H8: N | J8: MLB | K8: MLB | L8: PrizePicks/DFS | M8: Trout o5.5 HFS; Rafaela o5.5 HFS; Baldwin o5.5 HFS; Freeman o5.5 HFS; Seager o5.5 HFS; Pena o5.5 HFS | N8: 6 | O8: not shown | P8: 37.5 | Q8: 500 | S8: 18750 | T8: PrizePicks | U8: L | V8: =IF(NOT(ISNUMBER(Q8)),"",IF(U8="W",IF(ISNUMBER(S8),S8-Q8,IF(ISNUMBER(P8),Q8*(P8-1),"")),IF(U8="L",-Q8,IF(U8="Push",0,"")))) | W8: =IF(NOT(ISNUMBER(R8)),"",IF(U8="W",IF(ISNUMBER(P8),R8*(P8-1),""),IF(U8="L",-R8,IF(U8="Push",0,"")))) | X8: graded from final | Y8: N | Z8: https://x.com/BookitWithTrent/status/2084698796060020893 | AA8: Final: Trout 3 HFS; Decimal odds derived from payout/stake | AB8: Parlay/multi-leg | AC8: =IF(ISNUMBER(V8),Q8,"") | AD8: =IF(ISNUMBER(W8),R8,"")
A9: T-991261 | B9: Trent | C9: 46238.587 | D9: =IF(C9="","",TEXT(C9,"dddd")) | E9: 46238 | F9: =IF(E9="","",TEXT(E9,"dddd")) | G9: 8:40 PM | H9: N | J9: MLB | K9: MLB | L9: parlay | M9: Phillies ML; Rays ML; Braves ML; Twins ML; Rangers ML | N9: 5 | O9: +900 | P9: 10 | Q9: 1000 | S9: 10000 | T9: Pikkit | U9: L | V9: =IF(NOT(ISNUMBER(Q9)),"",IF(U9="W",IF(ISNUMBER(S9),S9-Q9,IF(ISNUMBER(P9),Q9*(P9-1),"")),IF(U9="L",-Q9,IF(U9="Push",0,"")))) | W9: =IF(NOT(ISNUMBER(R9)),"",IF(U9="W",IF(ISNUMBER(P9),R9*(P9-1),""),IF(U9="L",-R9,IF(U9="Push",0,"")))) | X9: posted | Y9: N | Z9: https://x.com/BookitWithTrent/status/2084717205220991261 | AA9: "Fugazi Five"; result slip (105054) shows Twins leg lost | AB9: Parlay/multi-leg | AC9: =IF(ISNUMBER(V9),Q9,"") | AD9: =IF(ISNUMBER(W9),R9,"")
A10: T-959071 | B10: Trent | C10: 46239.425 | D10: =IF(C10="","",TEXT(C10,"dddd")) | E10: 46239 | F10: =IF(E10="","",TEXT(E10,"dddd")) | G10: not matched | H10: N | J10: MLB | K10: MLB | L10: PrizePicks/DFS | M10: Yordan Alvarez o6.5 HFS; Shohei Ohtani o6.5 HFS; Wyatt Langford o5.5 HFS; Junior Caminero o11.5 HFS | N10: 4 | O10: not shown | P10: 10 | Q10: 1000 | S10: 10000 | T10: PrizePicks | U10: W | V10: =IF(NOT(ISNUMBER(Q10)),"",IF(U10="W",IF(ISNUMBER(S10),S10-Q10,IF(ISNUMBER(P10),Q10*(P10-1),"")),IF(U10="L",-Q10,IF(U10="Push",0,"")))) | W10: =IF(NOT(ISNUMBER(R10)),"",IF(U10="W",IF(ISNUMBER(P10),R10*(P10-1),""),IF(U10="L",-R10,IF(U10="Push",0,"")))) | X10: posted | Y10: N | Z10: https://x.com/BookitWithTrent/status/2085021011854959071 | AA10: "Birthday 4 man nuke"; cashed per 416291/771254; Game date assumed = post date (CT); Decimal odds derived from payout/stake | AB10: Parlay/multi-leg | AC10: =IF(ISNUMBER(V10),Q10,"") | AD10: =IF(ISNUMBER(W10),R10,"")
A11: T-509092 | B11: Trent | C11: 46239.474 | D11: =IF(C11="","",TEXT(C11,"dddd")) | E11: 46239 | F11: =IF(E11="","",TEXT(E11,"dddd")) | G11: 2:20 PM | H11: N | J11: MLB | K11: MLB | L11: ML | M11: Dodgers ML | N11: 1 | O11: not shown | R11: 10 | T11: not shown | U11: L | V11: =IF(NOT(ISNUMBER(Q11)),"",IF(U11="W",IF(ISNUMBER(S11),S11-Q11,IF(ISNUMBER(P11),Q11*(P11-1),"")),IF(U11="L",-Q11,IF(U11="Push",0,"")))) | W11: =IF(NOT(ISNUMBER(R11)),"",IF(U11="W",IF(ISNUMBER(P11),R11*(P11-1),""),IF(U11="L",-R11,IF(U11="Push",0,"")))) | X11: graded from final | Y11: N | Z11: https://x.com/BookitWithTrent/status/2085038898317509092 | AA11: "10U Mortal Mega Max" (CHC vs LAD) | AB11: Single | AC11: =IF(ISNUMBER(V11),Q11,"") | AD11: =IF(ISNUMBER(W11),R11,"")
A12: T-070221 | B12: Trent | C12: 46239.495 | D12: =IF(C12="","",TEXT(C12,"dddd")) | E12: 46239 | F12: =IF(E12="","",TEXT(E12,"dddd")) | G12: not matched | H12: N | J12: MLB | K12: MLB | L12: PrizePicks/DFS | M12: Yordan Alvarez HR o0.5; Shohei Ohtani HR o0.5 | N12: 2 | O12: not shown | P12: 8 | Q12: 300 | S12: 2400 | T12: PrizePicks | U12: L | V12: =IF(NOT(ISNUMBER(Q12)),"",IF(U12="W",IF(ISNUMBER(S12),S12-Q12,IF(ISNUMBER(P12),Q12*(P12-1),"")),IF(U12="L",-Q12,IF(U12="Push",0,"")))) | W12: =IF(NOT(ISNUMBER(R12)),"",IF(U12="W",IF(ISNUMBER(P12),R12*(P12-1),""),IF(U12="L",-R12,IF(U12="Push",0,"")))) | X12: graded from final | Y12: N | Z12: https://x.com/BookitWithTrent/status/2085046247665070221 | AA12: Final: Alvarez no HR; Decimal odds derived from payout/stake | AB12: Parlay/multi-leg | AC12: =IF(ISNUMBER(V12),Q12,"") | AD12: =IF(ISNUMBER(W12),R12,"")
A13: T-678835 | B13: Trent | C13: 46239.654 | D13: =IF(C13="","",TEXT(C13,"dddd")) | E13: 46239 | F13: =IF(E13="","",TEXT(E13,"dddd")) | G13: not matched | H13: N | J13: MLB | K13: MLB | L13: PrizePicks/DFS | M13: Elly De La Cruz o7.5 HFS; Paul Skenes o7 K; Bobby Witt Jr. o6.5 HFS; Bryan Woo o35.5 PFS | N13: 4 | O13: not shown | P13: 10 | Q13: 2000 | S13: 20000 | T13: PrizePicks | U13: L | V13: =IF(NOT(ISNUMBER(Q13)),"",IF(U13="W",IF(ISNUMBER(S13),S13-Q13,IF(ISNUMBER(P13),Q13*(P13-1),"")),IF(U13="L",-Q13,IF(U13="Push",0,"")))) | W13: =IF(NOT(ISNUMBER(R13)),"",IF(U13="W",IF(ISNUMBER(P13),R13*(P13-1),""),IF(U13="L",-R13,IF(U13="Push",0,"")))) | X13: graded from final | Y13: N | Z13: https://x.com/BookitWithTrent/status/2085103959832678835 | AA13: late-night 4 man; Final: Skenes 6 K; Decimal odds derived from payout/stake | AB13: Parlay/multi-leg | AC13: =IF(ISNUMBER(V13),Q13,"") | AD13: =IF(ISNUMBER(W13),R13,"")
A14: T-006899 | B14: Trent | C14: 46239.693 | D14: =IF(C14="","",TEXT(C14,"dddd")) | E14: 46239 | F14: =IF(E14="","",TEXT(E14,"dddd")) | G14: 9:40 PM | H14: N | J14: MLB | K14: MLB | L14: parlay | M14: Braves ML; Phillies ML; Pirates ML; Mariners ML | N14: 4 | O14: +900 | P14: 10 | Q14: 1000 | S14: 10000 | T14: Pikkit | U14: L | V14: =IF(NOT(ISNUMBER(Q14)),"",IF(U14="W",IF(ISNUMBER(S14),S14-Q14,IF(ISNUMBER(P14),Q14*(P14-1),"")),IF(U14="L",-Q14,IF(U14="Push",0,"")))) | W14: =IF(NOT(ISNUMBER(R14)),"",IF(U14="W",IF(ISNUMBER(P14),R14*(P14-1),""),IF(U14="L",-R14,IF(U14="Push",0,"")))) | X14: graded from final | Y14: N | Z14: https://x.com/BookitWithTrent/status/2085118211373006899 | AA14: "Wednesday Night Fugazi" | AB14: Parlay/multi-leg | AC14: =IF(ISNUMBER(V14),Q14,"") | AD14: =IF(ISNUMBER(W14),R14,"")
A15: T-890696 | B15: Trent | C15: 46240.479 | D15: =IF(C15="","",TEXT(C15,"dddd")) | E15: 46240 | F15: =IF(E15="","",TEXT(E15,"dddd")) | G15: not matched | H15: N | J15: MLB | K15: MLB | L15: PrizePicks/DFS | M15: No-HR (u0.5 HR): De La Cruz; Cal Raleigh; Schwarber; Abreu; Olson; Caglianone | N15: 6 | O15: not shown | T15: PrizePicks | U15: L | V15: =IF(NOT(ISNUMBER(Q15)),"",IF(U15="W",IF(ISNUMBER(S15),S15-Q15,IF(ISNUMBER(P15),Q15*(P15-1),"")),IF(U15="L",-Q15,IF(U15="Push",0,"")))) | W15: =IF(NOT(ISNUMBER(R15)),"",IF(U15="W",IF(ISNUMBER(P15),R15*(P15-1),""),IF(U15="L",-R15,IF(U15="Push",0,"")))) | X15: graded from final | Y15: Y - tags PrizePicks | Z15: https://x.com/BookitWithTrent/status/2085403129818890696 | AA15: stake not shown (lineup screenshot); Final: De La Cruz homered | AB15: Parlay/multi-leg | AC15: =IF(ISNUMBER(V15),Q15,"") | AD15: =IF(ISNUMBER(W15),R15,"")
A16: T-785238 | B16: Trent | C16: 46240.492 | D16: =IF(C16="","",TEXT(C16,"dddd")) | E16: 46240 | F16: =IF(E16="","",TEXT(E16,"dddd")) | G16: not matched | H16: N | J16: MLB | K16: MLB | L16: PrizePicks/DFS | M16: Dylan Cease o39.5 PFS; Cristopher Sanchez o7 K; Ronald Acuna Jr. o6.5 HFS; Bobby Witt Jr. o6.5 HFS | N16: 4 | O16: not shown | P16: 10 | Q16: 1000 | S16: 10000 | T16: PrizePicks | U16: L | V16: =IF(NOT(ISNUMBER(Q16)),"",IF(U16="W",IF(ISNUMBER(S16),S16-Q16,IF(ISNUMBER(P16),Q16*(P16-1),"")),IF(U16="L",-Q16,IF(U16="Push",0,"")))) | W16: =IF(NOT(ISNUMBER(R16)),"",IF(U16="W",IF(ISNUMBER(P16),R16*(P16-1),""),IF(U16="L",-R16,IF(U16="Push",0,"")))) | X16: posted | Y16: N | Z16: https://x.com/BookitWithTrent/status/2085407541819785238 | AA16: Sanchez finished with 6 K (943495 "One fucking K"); Game date assumed = post date (CT); Decimal odds derived from payout/stake | AB16: Parlay/multi-leg | AC16: =IF(ISNUMBER(V16),Q16,"") | AD16: =IF(ISNUMBER(W16),R16,"")
A17: T-801235 | B17: Trent | C17: 46240.678 | D17: =IF(C17="","",TEXT(C17,"dddd")) | E17: 46240 | F17: =IF(E17="","",TEXT(E17,"dddd")) | G17: 8:00 PM | H17: Y | I17: TNF | J17: NFL | K17: NFL Preseason | L17: ML | M17: Arizona Cardinals ML (vs WAS) | N17: 1 | O17: +100 | P17: 2 | Q17: 1087.32 | R17: 10 | S17: 2132 | T17: PrizePicks | U17: L | V17: =IF(NOT(ISNUMBER(Q17)),"",IF(U17="W",IF(ISNUMBER(S17),S17-Q17,IF(ISNUMBER(P17),Q17*(P17-1),"")),IF(U17="L",-Q17,IF(U17="Push",0,"")))) | W17: =IF(NOT(ISNUMBER(R17)),"",IF(U17="W",IF(ISNUMBER(P17),R17*(P17-1),""),IF(U17="L",-R17,IF(U17="Push",0,"")))) | X17: posted | Y17: N | Z17: https://x.com/BookitWithTrent/status/2085475090179801235 | AA17: "Play of the Year" 10U; PrizePicks 1-pick slip $1,087.32 to win $2,132; loss stated in later post; Game date assumed = post date (CT) | AB17: Single | AC17: =IF(ISNUMBER(V17),Q17,"") | AD17: =IF(ISNUMBER(W17),R17,"")
A18: T-011621 | B18: Trent | C18: 46241.671 | D18: =IF(C18="","",TEXT(C18,"dddd")) | E18: 46241 | F18: =IF(E18="","",TEXT(E18,"dddd")) | G18: not matched | H18: N | J18: Other | K18: PLL Lacrosse | L18: ML | M18: Whipsnakes ML (vs Cannons) | N18: 1 | O18: not shown | R18: not shown | T18: not shown | U18: Unknown | V18: =IF(NOT(ISNUMBER(Q18)),"",IF(U18="W",IF(ISNUMBER(S18),S18-Q18,IF(ISNUMBER(P18),Q18*(P18-1),"")),IF(U18="L",-Q18,IF(U18="Push",0,"")))) | W18: =IF(NOT(ISNUMBER(R18)),"",IF(U18="W",IF(ISNUMBER(P18),R18*(P18-1),""),IF(U18="L",-R18,IF(U18="Push",0,"")))) | X18: unverified | Y18: N | Z18: https://x.com/BookitWithTrent/status/2085834923991011621 | AA18: "Mortal mega"; Game date assumed = post date (CT) | AB18: Single | AC18: =IF(ISNUMBER(V18),Q18,"") | AD18: =IF(ISNUMBER(W18),R18,"")
A19: T-053239 | B19: Trent | C19: 46242.43 | D19: =IF(C19="","",TEXT(C19,"dddd")) | E19: 46242 | F19: =IF(E19="","",TEXT(E19,"dddd")) | G19: 3:05 PM | H19: N | J19: MLB | K19: MLB | L19: parlay | M19: ATL ML -135; Chris Sale o6.5 K -668 | N19: 2 | O19: +100 | P19: 2 | Q19: 1000 | S19: 1000 | T19: Pikkit | U19: L | V19: =IF(NOT(ISNUMBER(Q19)),"",IF(U19="W",IF(ISNUMBER(S19),S19-Q19,IF(ISNUMBER(P19),Q19*(P19-1),"")),IF(U19="L",-Q19,IF(U19="Push",0,"")))) | W19: =IF(NOT(ISNUMBER(R19)),"",IF(U19="W",IF(ISNUMBER(P19),R19*(P19-1),""),IF(U19="L",-R19,IF(U19="Push",0,"")))) | X19: graded from final | Y19: Y - tags Pikkit | Z19: https://x.com/BookitWithTrent/status/2086110001551053239 | AA19: "Braves ML + Sale 7+"; payout field is to-win | AB19: Parlay/multi-leg | AC19: =IF(ISNUMBER(V19),Q19,"") | AD19: =IF(ISNUMBER(W19),R19,"")
A20: T-205609 | B20: Trent | C20: 46242.449 | D20: =IF(C20="","",TEXT(C20,"dddd")) | E20: 46242 | F20: =IF(E20="","",TEXT(E20,"dddd")) | G20: not matched | H20: N | J20: Other | K20: PLL Lacrosse | L20: spread | M20: New York Atlas +1.5 | N20: 1 | O20: not shown | T20: not shown | U20: Unknown | V20: =IF(NOT(ISNUMBER(Q20)),"",IF(U20="W",IF(ISNUMBER(S20),S20-Q20,IF(ISNUMBER(P20),Q20*(P20-1),"")),IF(U20="L",-Q20,IF(U20="Push",0,"")))) | W20: =IF(NOT(ISNUMBER(R20)),"",IF(U20="W",IF(ISNUMBER(P20),R20*(P20-1),""),IF(U20="L",-R20,IF(U20="Push",0,"")))) | X20: unverified | Y20: N | Z20: https://x.com/BookitWithTrent/status/2086116921108205609 | AA20: "Mortal mega" fading @krabs_bookit; Game date assumed = post date (CT) | AB20: Single | AC20: =IF(ISNUMBER(V20),Q20,"") | AD20: =IF(ISNUMBER(W20),R20,"")
A21: T-265862 | B21: Trent | C21: 46242.482 | D21: =IF(C21="","",TEXT(C21,"dddd")) | E21: 46242 | F21: =IF(E21="","",TEXT(E21,"dddd")) | G21: 3:05 PM | H21: N | J21: MLB | K21: MLB | L21: PrizePicks/DFS | M21: Under 0.5 HR: Ben Rice; Paul Goldschmidt; Trent Grisham; Austin Riley; Matt Olson; Mike Yastrzemski | N21: 6 | O21: +130 | P21: 2.3 | Q21: 2000 | S21: 2600 | T21: PrizePicks | U21: L | V21: =IF(NOT(ISNUMBER(Q21)),"",IF(U21="W",IF(ISNUMBER(S21),S21-Q21,IF(ISNUMBER(P21),Q21*(P21-1),"")),IF(U21="L",-Q21,IF(U21="Push",0,"")))) | W21: =IF(NOT(ISNUMBER(R21)),"",IF(U21="W",IF(ISNUMBER(P21),R21*(P21-1),""),IF(U21="L",-R21,IF(U21="Push",0,"")))) | X21: graded from final | Y21: Y - tags Pikkit | Z21: https://x.com/BookitWithTrent/status/2086128660709265862 | AA21: 2.3x power play shown on Pikkit; ATL@NYY no-HR lay; Final: Ben Rice homered | AB21: Parlay/multi-leg | AC21: =IF(ISNUMBER(V21),Q21,"") | AD21: =IF(ISNUMBER(W21),R21,"")
A22: T-455925 | B22: Trent | C22: 46243.438 | D22: =IF(C22="","",TEXT(C22,"dddd")) | E22: 46243 | F22: =IF(E22="","",TEXT(E22,"dddd")) | G22: not matched | H22: N | J22: MLB | K22: MLB | L22: PrizePicks/DFS | M22: CJ Abrams o6.5 HFS; Royce Lewis u5.5 HFS; Kumar Rocker u16.5 PO; Justin Wrobleski o27.5 PFS | N22: 4 | O22: not shown | P22: 10 | Q22: 1000 | S22: 10000 | T22: PrizePicks | U22: L | V22: =IF(NOT(ISNUMBER(Q22)),"",IF(U22="W",IF(ISNUMBER(S22),S22-Q22,IF(ISNUMBER(P22),Q22*(P22-1),"")),IF(U22="L",-Q22,IF(U22="Push",0,"")))) | W22: =IF(NOT(ISNUMBER(R22)),"",IF(U22="W",IF(ISNUMBER(P22),R22*(P22-1),""),IF(U22="L",-R22,IF(U22="Push",0,"")))) | X22: posted | Y22: N | Z22: https://x.com/BookitWithTrent/status/2086475207892455925 | AA22: Collab slip w/ @jovan_deeb; "I sold the 4 man"; Game date assumed = post date (CT); Decimal odds derived from payout/stake | AB22: Parlay/multi-leg | AC22: =IF(ISNUMBER(V22),Q22,"") | AD22: =IF(ISNUMBER(W22),R22,"")
A23: T-648430 | B23: Trent | C23: 46243.683 | D23: =IF(C23="","",TEXT(C23,"dddd")) | E23: 46243 | F23: =IF(E23="","",TEXT(E23,"dddd")) | G23: 8:20 PM | H23: N | J23: MLB | K23: MLB | L23: ML | M23: Houston Astros ML (Sunday night) | N23: 1 | O23: not shown | T23: not shown | U23: L | V23: =IF(NOT(ISNUMBER(Q23)),"",IF(U23="W",IF(ISNUMBER(S23),S23-Q23,IF(ISNUMBER(P23),Q23*(P23-1),"")),IF(U23="L",-Q23,IF(U23="Push",0,"")))) | W23: =IF(NOT(ISNUMBER(R23)),"",IF(U23="W",IF(ISNUMBER(P23),R23*(P23-1),""),IF(U23="L",-R23,IF(U23="Push",0,"")))) | X23: graded from final | Y23: N | Z23: https://x.com/BookitWithTrent/status/2086564147198648430 | AA23: "Sunday Night Mortal Mega... for all the coin back" | AB23: Single | AC23: =IF(ISNUMBER(V23),Q23,"") | AD23: =IF(ISNUMBER(W23),R23,"")
A24: T-372455 | B24: Trent | C24: 46244.561 | D24: =IF(C24="","",TEXT(C24,"dddd")) | E24: 46244 | F24: =IF(E24="","",TEXT(E24,"dddd")) | G24: not matched | H24: N | J24: MLB | K24: MLB | L24: PrizePicks/DFS | M24: Junior Caminero o8 HFS; Tarik Skubal o7.5 K | N24: 2 | O24: not shown | P24: 3 | Q24: 3000 | S24: 9000 | T24: PrizePicks | U24: L | V24: =IF(NOT(ISNUMBER(Q24)),"",IF(U24="W",IF(ISNUMBER(S24),S24-Q24,IF(ISNUMBER(P24),Q24*(P24-1),"")),IF(U24="L",-Q24,IF(U24="Push",0,"")))) | W24: =IF(NOT(ISNUMBER(R24)),"",IF(U24="W",IF(ISNUMBER(P24),R24*(P24-1),""),IF(U24="L",-R24,IF(U24="Push",0,"")))) | X24: posted | Y24: N | Z24: https://x.com/BookitWithTrent/status/2086882285014372455 | AA24: "worst 2 man ever gg"; Game date assumed = post date (CT); Decimal odds derived from payout/stake | AB24: Parlay/multi-leg | AC24: =IF(ISNUMBER(V24),Q24,"") | AD24: =IF(ISNUMBER(W24),R24,"")
A25: T-373509 | B25: Trent | C25: 46245.584 | D25: =IF(C25="","",TEXT(C25,"dddd")) | E25: 46245 | F25: =IF(E25="","",TEXT(E25,"dddd")) | G25: not matched | H25: N | J25: MLB | K25: MLB | L25: prop | M25: Blake Snell o14.5 1st-inning pitches (vs KC) | N25: 1 | O25: not shown | T25: PrizePicks | U25: L | V25: =IF(NOT(ISNUMBER(Q25)),"",IF(U25="W",IF(ISNUMBER(S25),S25-Q25,IF(ISNUMBER(P25),Q25*(P25-1),"")),IF(U25="L",-Q25,IF(U25="Push",0,"")))) | W25: =IF(NOT(ISNUMBER(R25)),"",IF(U25="W",IF(ISNUMBER(P25),R25*(P25-1),""),IF(U25="L",-R25,IF(U25="Push",0,"")))) | X25: posted | Y25: N | Z25: https://x.com/BookitWithTrent/status/2087252861994373509 | AA25: "Rare MLB Play of Year"; stake not shown; "worst fucking play ever"; Game date assumed = post date (CT) | AB25: Single | AC25: =IF(ISNUMBER(V25),Q25,"") | AD25: =IF(ISNUMBER(W25),R25,"")
A26: T-102203 | B26: Trent | C26: 46245.591 | D26: =IF(C26="","",TEXT(C26,"dddd")) | E26: 46245 | F26: =IF(E26="","",TEXT(E26,"dddd")) | G26: 10:10 PM | H26: N | J26: MLB | K26: MLB | L26: parlay | M26: Blue Jays ML; White Sox ML; Rangers ML; Astros ML; Dodgers ML | N26: 5 | O26: +1000 | P26: 11 | Q26: 1000 | S26: 11000 | T26: Pikkit | U26: L | V26: =IF(NOT(ISNUMBER(Q26)),"",IF(U26="W",IF(ISNUMBER(S26),S26-Q26,IF(ISNUMBER(P26),Q26*(P26-1),"")),IF(U26="L",-Q26,IF(U26="Push",0,"")))) | W26: =IF(NOT(ISNUMBER(R26)),"",IF(U26="W",IF(ISNUMBER(P26),R26*(P26-1),""),IF(U26="L",-R26,IF(U26="Push",0,"")))) | X26: graded from final | Y26: N | Z26: https://x.com/BookitWithTrent/status/2087255371677102203 | AA26: "Fugazi Five" | AB26: Parlay/multi-leg | AC26: =IF(ISNUMBER(V26),Q26,"") | AD26: =IF(ISNUMBER(W26),R26,"")
A27: T-155794 | B27: Trent | C27: 46245.605 | D27: =IF(C27="","",TEXT(C27,"dddd")) | E27: 46245 | F27: =IF(E27="","",TEXT(E27,"dddd")) | G27: 6:45 PM | H27: N | J27: MLB | K27: MLB | L27: card | M27: Cubs -1.5 | N27: 1 | O27: not shown | T27: not shown | U27: W | V27: =IF(NOT(ISNUMBER(Q27)),"",IF(U27="W",IF(ISNUMBER(S27),S27-Q27,IF(ISNUMBER(P27),Q27*(P27-1),"")),IF(U27="L",-Q27,IF(U27="Push",0,"")))) | W27: =IF(NOT(ISNUMBER(R27)),"",IF(U27="W",IF(ISNUMBER(P27),R27*(P27-1),""),IF(U27="L",-R27,IF(U27="Push",0,"")))) | X27: graded from final | Y27: N | Z27: https://x.com/BookitWithTrent/status/2087260715086155794 | AA27: Part of 8-pick "MLB Whales" card (each pick tracked as its own row) | AB27: Single | AC27: =IF(ISNUMBER(V27),Q27,"") | AD27: =IF(ISNUMBER(W27),R27,"")
A28: T-155794b | B28: Trent | C28: 46245.605 | D28: =IF(C28="","",TEXT(C28,"dddd")) | E28: 46245 | F28: =IF(E28="","",TEXT(E28,"dddd")) | G28: 9:45 PM | H28: N | J28: MLB | K28: MLB | L28: spread | M28: Astros -1.5 | N28: 1 | O28: not shown | T28: not shown | U28: L | V28: =IF(NOT(ISNUMBER(Q28)),"",IF(U28="W",IF(ISNUMBER(S28),S28-Q28,IF(ISNUMBER(P28),Q28*(P28-1),"")),IF(U28="L",-Q28,IF(U28="Push",0,"")))) | W28: =IF(NOT(ISNUMBER(R28)),"",IF(U28="W",IF(ISNUMBER(P28),R28*(P28-1),""),IF(U28="L",-R28,IF(U28="Push",0,"")))) | X28: graded from final | Y28: N | Z28: https://x.com/BookitWithTrent/status/2087260715086155794 | AA28: MLB Whales card | AB28: Single | AC28: =IF(ISNUMBER(V28),Q28,"") | AD28: =IF(ISNUMBER(W28),R28,"")
A29: T-155794c | B29: Trent | C29: 46245.605 | D29: =IF(C29="","",TEXT(C29,"dddd")) | E29: 46245 | F29: =IF(E29="","",TEXT(E29,"dddd")) | G29: 7:40 PM | H29: N | J29: MLB | K29: MLB | L29: spread | M29: White Sox F5 -0.5 | N29: 1 | O29: not shown | T29: not shown | U29: W | V29: =IF(NOT(ISNUMBER(Q29)),"",IF(U29="W",IF(ISNUMBER(S29),S29-Q29,IF(ISNUMBER(P29),Q29*(P29-1),"")),IF(U29="L",-Q29,IF(U29="Push",0,"")))) | W29: =IF(NOT(ISNUMBER(R29)),"",IF(U29="W",IF(ISNUMBER(P29),R29*(P29-1),""),IF(U29="L",-R29,IF(U29="Push",0,"")))) | X29: graded from final | Y29: N | Z29: https://x.com/BookitWithTrent/status/2087260715086155794 | AA29: MLB Whales card | AB29: Single | AC29: =IF(ISNUMBER(V29),Q29,"") | AD29: =IF(ISNUMBER(W29),R29,"")
A30: T-155794d | B30: Trent | C30: 46245.605 | D30: =IF(C30="","",TEXT(C30,"dddd")) | E30: 46245 | F30: =IF(E30="","",TEXT(E30,"dddd")) | G30: 9:38 PM | H30: N | J30: MLB | K30: MLB | L30: spread | M30: Rangers F5 -0.5 | N30: 1 | O30: not shown | T30: not shown | U30: L | V30: =IF(NOT(ISNUMBER(Q30)),"",IF(U30="W",IF(ISNUMBER(S30),S30-Q30,IF(ISNUMBER(P30),Q30*(P30-1),"")),IF(U30="L",-Q30,IF(U30="Push",0,"")))) | W30: =IF(NOT(ISNUMBER(R30)),"",IF(U30="W",IF(ISNUMBER(P30),R30*(P30-1),""),IF(U30="L",-R30,IF(U30="Push",0,"")))) | X30: graded from final | Y30: N | Z30: https://x.com/BookitWithTrent/status/2087260715086155794 | AA30: MLB Whales card | AB30: Single | AC30: =IF(ISNUMBER(V30),Q30,"") | AD30: =IF(ISNUMBER(W30),R30,"")
A31: T-155794e | B31: Trent | C31: 46245.605 | D31: =IF(C31="","",TEXT(C31,"dddd")) | E31: 46245 | F31: =IF(E31="","",TEXT(E31,"dddd")) | G31: 9:40 PM | H31: N | J31: MLB | K31: MLB | L31: total | M31: Dbacks/Rockies Over 9.5 | N31: 1 | O31: not shown | T31: not shown | U31: L | V31: =IF(NOT(ISNUMBER(Q31)),"",IF(U31="W",IF(ISNUMBER(S31),S31-Q31,IF(ISNUMBER(P31),Q31*(P31-1),"")),IF(U31="L",-Q31,IF(U31="Push",0,"")))) | W31: =IF(NOT(ISNUMBER(R31)),"",IF(U31="W",IF(ISNUMBER(P31),R31*(P31-1),""),IF(U31="L",-R31,IF(U31="Push",0,"")))) | X31: graded from final | Y31: N | Z31: https://x.com/BookitWithTrent/status/2087260715086155794 | AA31: MLB Whales card | AB31: Single | AC31: =IF(ISNUMBER(V31),Q31,"") | AD31: =IF(ISNUMBER(W31),R31,"")
A32: T-155794f | B32: Trent | C32: 46245.605 | D32: =IF(C32="","",TEXT(C32,"dddd")) | E32: 46245 | F32: =IF(E32="","",TEXT(E32,"dddd")) | G32: 7:40 PM | H32: N | J32: MLB | K32: MLB | L32: total | M32: Twins/Orioles Over 9.5 | N32: 1 | O32: not shown | T32: not shown | U32: L | V32: =IF(NOT(ISNUMBER(Q32)),"",IF(U32="W",IF(ISNUMBER(S32),S32-Q32,IF(ISNUMBER(P32),Q32*(P32-1),"")),IF(U32="L",-Q32,IF(U32="Push",0,"")))) | W32: =IF(NOT(ISNUMBER(R32)),"",IF(U32="W",IF(ISNUMBER(P32),R32*(P32-1),""),IF(U32="L",-R32,IF(U32="Push",0,"")))) | X32: graded from final | Y32: N | Z32: https://x.com/BookitWithTrent/status/2087260715086155794 | AA32: MLB Whales card | AB32: Single | AC32: =IF(ISNUMBER(V32),Q32,"") | AD32: =IF(ISNUMBER(W32),R32,"")
A33: T-155794g | B33: Trent | C33: 46245.605 | D33: =IF(C33="","",TEXT(C33,"dddd")) | E33: 46245 | F33: =IF(E33="","",TEXT(E33,"dddd")) | G33: 7:15 PM | H33: N | J33: MLB | K33: MLB | L33: total | M33: Mets/Braves Under 8.5 | N33: 1 | O33: not shown | T33: not shown | U33: W | V33: =IF(NOT(ISNUMBER(Q33)),"",IF(U33="W",IF(ISNUMBER(S33),S33-Q33,IF(ISNUMBER(P33),Q33*(P33-1),"")),IF(U33="L",-Q33,IF(U33="Push",0,"")))) | W33: =IF(NOT(ISNUMBER(R33)),"",IF(U33="W",IF(ISNUMBER(P33),R33*(P33-1),""),IF(U33="L",-R33,IF(U33="Push",0,"")))) | X33: graded from final | Y33: N | Z33: https://x.com/BookitWithTrent/status/2087260715086155794 | AA33: MLB Whales card | AB33: Single | AC33: =IF(ISNUMBER(V33),Q33,"") | AD33: =IF(ISNUMBER(W33),R33,"")
A34: T-155794h | B34: Trent | C34: 46245.605 | D34: =IF(C34="","",TEXT(C34,"dddd")) | E34: 46245 | F34: =IF(E34="","",TEXT(E34,"dddd")) | G34: 6:40 PM | H34: N | J34: MLB | K34: MLB | L34: total | M34: Guardians/Tigers Under 8.5 | N34: 1 | O34: not shown | T34: not shown | U34: L | V34: =IF(NOT(ISNUMBER(Q34)),"",IF(U34="W",IF(ISNUMBER(S34),S34-Q34,IF(ISNUMBER(P34),Q34*(P34-1),"")),IF(U34="L",-Q34,IF(U34="Push",0,"")))) | W34: =IF(NOT(ISNUMBER(R34)),"",IF(U34="W",IF(ISNUMBER(P34),R34*(P34-1),""),IF(U34="L",-R34,IF(U34="Push",0,"")))) | X34: graded from final | Y34: N | Z34: https://x.com/BookitWithTrent/status/2087260715086155794 | AA34: MLB Whales card | AB34: Single | AC34: =IF(ISNUMBER(V34),Q34,"") | AD34: =IF(ISNUMBER(W34),R34,"")
A35: T-412111 | B35: Trent | C35: 46246.492 | D35: =IF(C35="","",TEXT(C35,"dddd")) | E35: 46246 | F35: =IF(E35="","",TEXT(E35,"dddd")) | G35: 1:40 PM | H35: N | J35: MLB | K35: MLB | L35: ML | M35: Twins ML | N35: 1 | O35: -110 | P35: 1.9091 | T35: not shown | U35: W | V35: =IF(NOT(ISNUMBER(Q35)),"",IF(U35="W",IF(ISNUMBER(S35),S35-Q35,IF(ISNUMBER(P35),Q35*(P35-1),"")),IF(U35="L",-Q35,IF(U35="Push",0,"")))) | W35: =IF(NOT(ISNUMBER(R35)),"",IF(U35="W",IF(ISNUMBER(P35),R35*(P35-1),""),IF(U35="L",-R35,IF(U35="Push",0,"")))) | X35: graded from final | Y35: N | Z35: https://x.com/BookitWithTrent/status/2087581889888412111 | AA35: Daytime Baseball Megas card | AB35: Single | AC35: =IF(ISNUMBER(V35),Q35,"") | AD35: =IF(ISNUMBER(W35),R35,"")
A36: T-412111b | B36: Trent | C36: 46246.492 | D36: =IF(C36="","",TEXT(C36,"dddd")) | E36: 46246 | F36: =IF(E36="","",TEXT(E36,"dddd")) | G36: 2:15 PM | H36: N | J36: MLB | K36: MLB | L36: total | M36: Phillies/Cardinals Under 8 | N36: 1 | O36: -110 | P36: 1.9091 | T36: not shown | U36: Push | V36: =IF(NOT(ISNUMBER(Q36)),"",IF(U36="W",IF(ISNUMBER(S36),S36-Q36,IF(ISNUMBER(P36),Q36*(P36-1),"")),IF(U36="L",-Q36,IF(U36="Push",0,"")))) | W36: =IF(NOT(ISNUMBER(R36)),"",IF(U36="W",IF(ISNUMBER(P36),R36*(P36-1),""),IF(U36="L",-R36,IF(U36="Push",0,"")))) | X36: graded from final | Y36: N | Z36: https://x.com/BookitWithTrent/status/2087581889888412111 | AA36: Daytime Baseball Megas card | AB36: Single | AC36: =IF(ISNUMBER(V36),Q36,"") | AD36: =IF(ISNUMBER(W36),R36,"")
A37: T-412111c | B37: Trent | C37: 46246.492 | D37: =IF(C37="","",TEXT(C37,"dddd")) | E37: 46246 | F37: =IF(E37="","",TEXT(E37,"dddd")) | G37: 3:05 PM | H37: N | J37: MLB | K37: MLB | L37: spread | M37: Rays -1.5 | N37: 1 | O37: -130 | P37: 1.7692 | T37: not shown | U37: W | V37: =IF(NOT(ISNUMBER(Q37)),"",IF(U37="W",IF(ISNUMBER(S37),S37-Q37,IF(ISNUMBER(P37),Q37*(P37-1),"")),IF(U37="L",-Q37,IF(U37="Push",0,"")))) | W37: =IF(NOT(ISNUMBER(R37)),"",IF(U37="W",IF(ISNUMBER(P37),R37*(P37-1),""),IF(U37="L",-R37,IF(U37="Push",0,"")))) | X37: graded from final | Y37: N | Z37: https://x.com/BookitWithTrent/status/2087581889888412111 | AA37: Daytime Baseball Megas card | AB37: Single | AC37: =IF(ISNUMBER(V37),Q37,"") | AD37: =IF(ISNUMBER(W37),R37,"")
A38: T-412111d | B38: Trent | C38: 46246.492 | D38: =IF(C38="","",TEXT(C38,"dddd")) | E38: 46246 | F38: =IF(E38="","",TEXT(E38,"dddd")) | G38: 3:40 PM | H38: N | J38: MLB | K38: MLB | L38: total | M38: Rockies/Dbacks Over 9 | N38: 1 | O38: -110 | P38: 1.9091 | T38: not shown | U38: W | V38: =IF(NOT(ISNUMBER(Q38)),"",IF(U38="W",IF(ISNUMBER(S38),S38-Q38,IF(ISNUMBER(P38),Q38*(P38-1),"")),IF(U38="L",-Q38,IF(U38="Push",0,"")))) | W38: =IF(NOT(ISNUMBER(R38)),"",IF(U38="W",IF(ISNUMBER(P38),R38*(P38-1),""),IF(U38="L",-R38,IF(U38="Push",0,"")))) | X38: graded from final | Y38: N | Z38: https://x.com/BookitWithTrent/status/2087581889888412111 | AA38: Daytime Baseball Megas card | AB38: Single | AC38: =IF(ISNUMBER(V38),Q38,"") | AD38: =IF(ISNUMBER(W38),R38,"")
A39: T-283140 | B39: Trent | C39: 46246.844 | D39: =IF(C39="","",TEXT(C39,"dddd")) | E39: 46246 | F39: =IF(E39="","",TEXT(E39,"dddd")) | G39: 10:10 PM | H39: N | J39: MLB | K39: MLB | L39: spread | M39: Dodgers -1.5 | N39: 1 | O39: not shown | T39: not shown | U39: W | V39: =IF(NOT(ISNUMBER(Q39)),"",IF(U39="W",IF(ISNUMBER(S39),S39-Q39,IF(ISNUMBER(P39),Q39*(P39-1),"")),IF(U39="L",-Q39,IF(U39="Push",0,"")))) | W39: =IF(NOT(ISNUMBER(R39)),"",IF(U39="W",IF(ISNUMBER(P39),R39*(P39-1),""),IF(U39="L",-R39,IF(U39="Push",0,"")))) | X39: posted | Y39: N | Z39: https://x.com/BookitWithTrent/status/2087709718890283140 | AA39: "Mega max"; "AFTER 11 GAMES IT FINALLY CASHED" | AB39: Single | AC39: =IF(ISNUMBER(V39),Q39,"") | AD39: =IF(ISNUMBER(W39),R39,"")
A40: T-523783 | B40: Trent | C40: 46247.491 | D40: =IF(C40="","",TEXT(C40,"dddd")) | E40: 46247 | F40: =IF(E40="","",TEXT(E40,"dddd")) | G40: 1:10 PM | H40: N | J40: MLB | K40: MLB | L40: ML | M40: Pirates ML | N40: 1 | O40: not shown | T40: not shown | U40: W | V40: =IF(NOT(ISNUMBER(Q40)),"",IF(U40="W",IF(ISNUMBER(S40),S40-Q40,IF(ISNUMBER(P40),Q40*(P40-1),"")),IF(U40="L",-Q40,IF(U40="Push",0,"")))) | W40: =IF(NOT(ISNUMBER(R40)),"",IF(U40="W",IF(ISNUMBER(P40),R40*(P40-1),""),IF(U40="L",-R40,IF(U40="Push",0,"")))) | X40: posted | Y40: N | Z40: https://x.com/BookitWithTrent/status/2087944039148523783 | AA40: Daytime card; recap 116961 (4-1) | AB40: Single | AC40: =IF(ISNUMBER(V40),Q40,"") | AD40: =IF(ISNUMBER(W40),R40,"")
A41: T-523783b | B41: Trent | C41: 46247.491 | D41: =IF(C41="","",TEXT(C41,"dddd")) | E41: 46247 | F41: =IF(E41="","",TEXT(E41,"dddd")) | G41: 1:10 PM | H41: N | J41: MLB | K41: MLB | L41: ML | M41: Guardians ML | N41: 1 | O41: not shown | T41: not shown | U41: L | V41: =IF(NOT(ISNUMBER(Q41)),"",IF(U41="W",IF(ISNUMBER(S41),S41-Q41,IF(ISNUMBER(P41),Q41*(P41-1),"")),IF(U41="L",-Q41,IF(U41="Push",0,"")))) | W41: =IF(NOT(ISNUMBER(R41)),"",IF(U41="W",IF(ISNUMBER(P41),R41*(P41-1),""),IF(U41="L",-R41,IF(U41="Push",0,"")))) | X41: posted | Y41: N | Z41: https://x.com/BookitWithTrent/status/2087944039148523783 | AA41: Daytime card; recap 116961 | AB41: Single | AC41: =IF(ISNUMBER(V41),Q41,"") | AD41: =IF(ISNUMBER(W41),R41,"")
A42: T-523783c | B42: Trent | C42: 46247.491 | D42: =IF(C42="","",TEXT(C42,"dddd")) | E42: 46247 | F42: =IF(E42="","",TEXT(E42,"dddd")) | G42: 1:35 PM | H42: N | J42: MLB | K42: MLB | L42: total | M42: Yankees/Mariners Under 7.5 | N42: 1 | O42: not shown | T42: not shown | U42: W | V42: =IF(NOT(ISNUMBER(Q42)),"",IF(U42="W",IF(ISNUMBER(S42),S42-Q42,IF(ISNUMBER(P42),Q42*(P42-1),"")),IF(U42="L",-Q42,IF(U42="Push",0,"")))) | W42: =IF(NOT(ISNUMBER(R42)),"",IF(U42="W",IF(ISNUMBER(P42),R42*(P42-1),""),IF(U42="L",-R42,IF(U42="Push",0,"")))) | X42: posted | Y42: N | Z42: https://x.com/BookitWithTrent/status/2087944039148523783 | AA42: Daytime card; recap 116961 | AB42: Single | AC42: =IF(ISNUMBER(V42),Q42,"") | AD42: =IF(ISNUMBER(W42),R42,"")
A43: T-523783d | B43: Trent | C43: 46247.491 | D43: =IF(C43="","",TEXT(C43,"dddd")) | E43: 46247 | F43: =IF(E43="","",TEXT(E43,"dddd")) | G43: 1:10 PM | H43: N | J43: MLB | K43: MLB | L43: total | M43: Reds/White Sox Over 8.5 | N43: 1 | O43: not shown | T43: not shown | U43: W | V43: =IF(NOT(ISNUMBER(Q43)),"",IF(U43="W",IF(ISNUMBER(S43),S43-Q43,IF(ISNUMBER(P43),Q43*(P43-1),"")),IF(U43="L",-Q43,IF(U43="Push",0,"")))) | W43: =IF(NOT(ISNUMBER(R43)),"",IF(U43="W",IF(ISNUMBER(P43),R43*(P43-1),""),IF(U43="L",-R43,IF(U43="Push",0,"")))) | X43: posted | Y43: N | Z43: https://x.com/BookitWithTrent/status/2087944039148523783 | AA43: Daytime card; recap 116961 | AB43: Single | AC43: =IF(ISNUMBER(V43),Q43,"") | AD43: =IF(ISNUMBER(W43),R43,"")
A44: T-523783e | B44: Trent | C44: 46247.491 | D44: =IF(C44="","",TEXT(C44,"dddd")) | E44: 46247 | F44: =IF(E44="","",TEXT(E44,"dddd")) | G44: 3:07 PM | H44: N | J44: MLB | K44: MLB | L44: spread | M44: Red Sox F5 -0.5 | N44: 1 | O44: not shown | T44: not shown | U44: W | V44: =IF(NOT(ISNUMBER(Q44)),"",IF(U44="W",IF(ISNUMBER(S44),S44-Q44,IF(ISNUMBER(P44),Q44*(P44-1),"")),IF(U44="L",-Q44,IF(U44="Push",0,"")))) | W44: =IF(NOT(ISNUMBER(R44)),"",IF(U44="W",IF(ISNUMBER(P44),R44*(P44-1),""),IF(U44="L",-R44,IF(U44="Push",0,"")))) | X44: posted | Y44: N | Z44: https://x.com/BookitWithTrent/status/2087944039148523783 | AA44: Daytime card; recap 116961 | AB44: Single | AC44: =IF(ISNUMBER(V44),Q44,"") | AD44: =IF(ISNUMBER(W44),R44,"")
A45: T-400677 | B45: Trent | C45: 46247.62 | D45: =IF(C45="","",TEXT(C45,"dddd")) | E45: 46247 | F45: =IF(E45="","",TEXT(E45,"dddd")) | G45: 7:30 PM | H45: N | J45: MLB | K45: MLB | L45: prop | M45: NRFI Phillies vs Twins (Field of Dreams) | N45: 1 | O45: +100 | P45: 2 | R45: 10 | T45: not shown | U45: L | V45: =IF(NOT(ISNUMBER(Q45)),"",IF(U45="W",IF(ISNUMBER(S45),S45-Q45,IF(ISNUMBER(P45),Q45*(P45-1),"")),IF(U45="L",-Q45,IF(U45="Push",0,"")))) | W45: =IF(NOT(ISNUMBER(R45)),"",IF(U45="W",IF(ISNUMBER(P45),R45*(P45-1),""),IF(U45="L",-R45,IF(U45="Push",0,"")))) | X45: posted | Y45: N | Z45: https://x.com/BookitWithTrent/status/2087990640336400677 | AA45: 10U MAX; Schwarber 1st-inning HR ("NRFI was the worst wager ever placed") | AB45: Single | AC45: =IF(ISNUMBER(V45),Q45,"") | AD45: =IF(ISNUMBER(W45),R45,"")
A46: T-993518 | B46: Trent | C46: 46248.46 | D46: =IF(C46="","",TEXT(C46,"dddd")) | E46: 46248 | F46: =IF(E46="","",TEXT(E46,"dddd")) | G46: 2:20 PM | H46: N | J46: MLB | K46: MLB | L46: spread | M46: Cubs -1.5 | N46: 1 | O46: +115 | P46: 2.15 | T46: not shown | U46: W | V46: =IF(NOT(ISNUMBER(Q46)),"",IF(U46="W",IF(ISNUMBER(S46),S46-Q46,IF(ISNUMBER(P46),Q46*(P46-1),"")),IF(U46="L",-Q46,IF(U46="Push",0,"")))) | W46: =IF(NOT(ISNUMBER(R46)),"",IF(U46="W",IF(ISNUMBER(P46),R46*(P46-1),""),IF(U46="L",-R46,IF(U46="Push",0,"")))) | X46: graded from final | Y46: N | Z46: https://x.com/BookitWithTrent/status/2088295075381993518 | AA46: "Daytime Baseball Mortal Mega Max" | AB46: Single | AC46: =IF(ISNUMBER(V46),Q46,"") | AD46: =IF(ISNUMBER(W46),R46,"")
A47: T-664446 | B47: Trent | C47: 46248.532 | D47: =IF(C47="","",TEXT(C47,"dddd")) | E47: 46248 | F47: =IF(E47="","",TEXT(E47,"dddd")) | G47: not matched | H47: N | J47: Other | K47: Horse racing (Woodbine) | L47: other | M47: Exacta (horses not shown) | N47: 1 | O47: not shown | S47: 3000 | T47: not shown | U47: W | V47: =IF(NOT(ISNUMBER(Q47)),"",IF(U47="W",IF(ISNUMBER(S47),S47-Q47,IF(ISNUMBER(P47),Q47*(P47-1),"")),IF(U47="L",-Q47,IF(U47="Push",0,"")))) | W47: =IF(NOT(ISNUMBER(R47)),"",IF(U47="W",IF(ISNUMBER(P47),R47*(P47-1),""),IF(U47="L",-R47,IF(U47="Push",0,"")))) | X47: posted | Y47: N | Z47: https://x.com/BookitWithTrent/status/2088321270584664446 | AA47: Exacta tip from @RealGootzHall "cashed and paid out $3,000"; stake not shown; Game date assumed = post date (CT) | AB47: Single | AC47: =IF(ISNUMBER(V47),Q47,"") | AD47: =IF(ISNUMBER(W47),R47,"")
A48: T-938901 | B48: Trent | C48: 46248.691 | D48: =IF(C48="","",TEXT(C48,"dddd")) | E48: 46248 | F48: =IF(E48="","",TEXT(E48,"dddd")) | G48: 7:15 PM | H48: N | J48: MLB | K48: MLB | L48: ML | M48: Blue Jays ML | N48: 1 | O48: +130 | P48: 2.3 | R48: 10 | T48: not shown | U48: W | V48: =IF(NOT(ISNUMBER(Q48)),"",IF(U48="W",IF(ISNUMBER(S48),S48-Q48,IF(ISNUMBER(P48),Q48*(P48-1),"")),IF(U48="L",-Q48,IF(U48="Push",0,"")))) | W48: =IF(NOT(ISNUMBER(R48)),"",IF(U48="W",IF(ISNUMBER(P48),R48*(P48-1),""),IF(U48="L",-R48,IF(U48="Push",0,"")))) | X48: graded from final | Y48: N | Z48: https://x.com/BookitWithTrent/status/2088378739704938901 | AA48: "Friday Night Mortal Mega Max" 10U | AB48: Single | AC48: =IF(ISNUMBER(V48),Q48,"") | AD48: =IF(ISNUMBER(W48),R48,"")
A49: T-230793 | B49: Trent | C49: 46248.734 | D49: =IF(C49="","",TEXT(C49,"dddd")) | E49: 46248 | F49: =IF(E49="","",TEXT(E49,"dddd")) | G49: not matched | H49: N | J49: MLB | K49: MLB | L49: prop | M49: Vladimir Guerrero Jr. to hit a HR | N49: 1 | O49: +470 | P49: 5.7 | T49: not shown | U49: L | V49: =IF(NOT(ISNUMBER(Q49)),"",IF(U49="W",IF(ISNUMBER(S49),S49-Q49,IF(ISNUMBER(P49),Q49*(P49-1),"")),IF(U49="L",-Q49,IF(U49="Push",0,"")))) | W49: =IF(NOT(ISNUMBER(R49)),"",IF(U49="W",IF(ISNUMBER(P49),R49*(P49-1),""),IF(U49="L",-R49,IF(U49="Push",0,"")))) | X49: graded from final | Y49: N | Z49: https://x.com/BookitWithTrent/status/2088394406810230793 | AA49: "i'm nuking" (stake not shown); Final: Vlad Jr no HR | AB49: Single | AC49: =IF(ISNUMBER(V49),Q49,"") | AD49: =IF(ISNUMBER(W49),R49,"")
A50: S-415231 | B50: Steve | C50: 46249.473 | D50: =IF(C50="","",TEXT(C50,"dddd")) | E50: 46249 | F50: =IF(E50="","",TEXT(E50,"dddd")) | G50: not matched | H50: Unknown | I50: kickoff not matched | J50: NFL | K50: NFL Preseason | L50: spread | M50: New York Giants +1.5 vs Minnesota Vikings | N50: 1 | O50: -108 | P50: 1.9259 | Q50: 24633.23 | S50: 47542.13 | T50: Gamdom | U50: L | V50: =IF(NOT(ISNUMBER(Q50)),"",IF(U50="W",IF(ISNUMBER(S50),S50-Q50,IF(ISNUMBER(P50),Q50*(P50-1),"")),IF(U50="L",-Q50,IF(U50="Push",0,"")))) | W50: =IF(NOT(ISNUMBER(R50)),"",IF(U50="W",IF(ISNUMBER(P50),R50*(P50-1),""),IF(U50="L",-R50,IF(U50="Push",0,"")))) | X50: posted | Y50: Y - tags Gamdom | Z50: https://x.com/stevewilldoit/status/2088662105335415231 | AA50: Steve says he bet "20k for fun" and posted by mistake; later refunded followers' Giants bets; payout figure is total return; Game date assumed = post date (CT) | AB50: Single | AC50: =IF(ISNUMBER(V50),Q50,"") | AD50: =IF(ISNUMBER(W50),R50,"")
A51: S-415231b | B51: Steve | C51: 46249.473 | D51: =IF(C51="","",TEXT(C51,"dddd")) | E51: 46249 | F51: =IF(E51="","",TEXT(E51,"dddd")) | G51: 7:10 PM | H51: N | J51: MLB | K51: MLB | L51: ML | M51: Cleveland Guardians F5 ML vs San Diego Padres | N51: 1 | O51: -143 | P51: 1.6993 | Q51: 60000 | S51: 102000 | T51: Gamdom | U51: W | V51: =IF(NOT(ISNUMBER(Q51)),"",IF(U51="W",IF(ISNUMBER(S51),S51-Q51,IF(ISNUMBER(P51),Q51*(P51-1),"")),IF(U51="L",-Q51,IF(U51="Push",0,"")))) | W51: =IF(NOT(ISNUMBER(R51)),"",IF(U51="W",IF(ISNUMBER(P51),R51*(P51-1),""),IF(U51="L",-R51,IF(U51="Push",0,"")))) | X51: posted | Y51: Y - tags Gamdom | Z51: https://x.com/stevewilldoit/status/2088662105335415231 | AA51: "AI guy" pick; "top 2 picks hit... went 2-0"; payout is total return | AB51: Single | AC51: =IF(ISNUMBER(V51),Q51,"") | AD51: =IF(ISNUMBER(W51),R51,"")
A52: S-415231c | B52: Steve | C52: 46249.473 | D52: =IF(C52="","",TEXT(C52,"dddd")) | E52: 46249 | F52: =IF(E52="","",TEXT(E52,"dddd")) | G52: 6:10 PM | H52: N | J52: MLB | K52: MLB | L52: total | M52: Rays vs Orioles F5 Under 4.5 | N52: 1 | O52: -164 | P52: 1.6098 | Q52: 70000 | S52: 112700 | T52: Gamdom | U52: W | V52: =IF(NOT(ISNUMBER(Q52)),"",IF(U52="W",IF(ISNUMBER(S52),S52-Q52,IF(ISNUMBER(P52),Q52*(P52-1),"")),IF(U52="L",-Q52,IF(U52="Push",0,"")))) | W52: =IF(NOT(ISNUMBER(R52)),"",IF(U52="W",IF(ISNUMBER(P52),R52*(P52-1),""),IF(U52="L",-R52,IF(U52="Push",0,"")))) | X52: posted | Y52: Y - tags Gamdom | Z52: https://x.com/stevewilldoit/status/2088662105335415231 | AA52: "AI guy" pick; "went 2-0"; payout is total return | AB52: Single | AC52: =IF(ISNUMBER(V52),Q52,"") | AD52: =IF(ISNUMBER(W52),R52,"")
A53: T-556839 | B53: Trent | C53: 46249.49 | D53: =IF(C53="","",TEXT(C53,"dddd")) | E53: 46249 | F53: =IF(E53="","",TEXT(E53,"dddd")) | G53: not matched | H53: N | J53: Other | K53: PLL Lacrosse | L53: spread | M53: Waterdogs -2.5 | N53: 1 | O53: not shown | T53: not shown | U53: Unknown | V53: =IF(NOT(ISNUMBER(Q53)),"",IF(U53="W",IF(ISNUMBER(S53),S53-Q53,IF(ISNUMBER(P53),Q53*(P53-1),"")),IF(U53="L",-Q53,IF(U53="Push",0,"")))) | W53: =IF(NOT(ISNUMBER(R53)),"",IF(U53="W",IF(ISNUMBER(P53),R53*(P53-1),""),IF(U53="L",-R53,IF(U53="Push",0,"")))) | X53: unverified | Y53: N | Z53: https://x.com/BookitWithTrent/status/2088668527347556839 | AA53: "Mortal mega max" fading @krabs_bookit; Game date assumed = post date (CT) | AB53: Single | AC53: =IF(ISNUMBER(V53),Q53,"") | AD53: =IF(ISNUMBER(W53),R53,"")
A54: T-087760 | B54: Trent | C54: 46249.739 | D54: =IF(C54="","",TEXT(C54,"dddd")) | E54: 46249 | F54: =IF(E54="","",TEXT(E54,"dddd")) | G54: 7:15 PM | H54: N | J54: MLB | K54: MLB | L54: ML | M54: Dodgers ML (vs Brewers) | N54: 1 | O54: +120 | P54: 2.2 | R54: 10 | T54: not shown | U54: L | V54: =IF(NOT(ISNUMBER(Q54)),"",IF(U54="W",IF(ISNUMBER(S54),S54-Q54,IF(ISNUMBER(P54),Q54*(P54-1),"")),IF(U54="L",-Q54,IF(U54="Push",0,"")))) | W54: =IF(NOT(ISNUMBER(R54)),"",IF(U54="W",IF(ISNUMBER(P54),R54*(P54-1),""),IF(U54="L",-R54,IF(U54="Push",0,"")))) | X54: graded from final | Y54: N | Z54: https://x.com/BookitWithTrent/status/2088758496737087760 | AA54: "MLB Mortal Mega" 10U | AB54: Single | AC54: =IF(ISNUMBER(V54),Q54,"") | AD54: =IF(ISNUMBER(W54),R54,"")
A55: T-484115 | B55: Trent | C55: 46250.43 | D55: =IF(C55="","",TEXT(C55,"dddd")) | E55: 46250 | F55: =IF(E55="","",TEXT(E55,"dddd")) | G55: not matched | H55: N | J55: MLB | K55: MLB | L55: PrizePicks/DFS | M55: Dylan Cease o8.5 K; Sean Burke o5.5 K; Tarik Skubal o7 K; Hunter Brown o5.5 K | N55: 4 | O55: not shown | P55: 10 | Q55: 1000 | S55: 10000 | T55: PrizePicks | U55: L | V55: =IF(NOT(ISNUMBER(Q55)),"",IF(U55="W",IF(ISNUMBER(S55),S55-Q55,IF(ISNUMBER(P55),Q55*(P55-1),"")),IF(U55="L",-Q55,IF(U55="Push",0,"")))) | W55: =IF(NOT(ISNUMBER(R55)),"",IF(U55="W",IF(ISNUMBER(P55),R55*(P55-1),""),IF(U55="L",-R55,IF(U55="Push",0,"")))) | X55: posted | Y55: N | Z55: https://x.com/BookitWithTrent/status/2089009183928484115 | AA55: "Sunday K lay"; Burke had 0 K per later post; Game date assumed = post date (CT); Decimal odds derived from payout/stake | AB55: Parlay/multi-leg | AC55: =IF(ISNUMBER(V55),Q55,"") | AD55: =IF(ISNUMBER(W55),R55,"")
A56: T-603249 | B56: Trent | C56: 46250.669 | D56: =IF(C56="","",TEXT(C56,"dddd")) | E56: 46250 | F56: =IF(E56="","",TEXT(E56,"dddd")) | G56: 7:20 PM | H56: N | J56: MLB | K56: MLB | L56: ML | M56: Astros ML (vs Mariners) | N56: 1 | O56: -120 | P56: 1.8333 | R56: 20 | T56: not shown | U56: L | V56: =IF(NOT(ISNUMBER(Q56)),"",IF(U56="W",IF(ISNUMBER(S56),S56-Q56,IF(ISNUMBER(P56),Q56*(P56-1),"")),IF(U56="L",-Q56,IF(U56="Push",0,"")))) | W56: =IF(NOT(ISNUMBER(R56)),"",IF(U56="W",IF(ISNUMBER(P56),R56*(P56-1),""),IF(U56="L",-R56,IF(U56="Push",0,"")))) | X56: graded from final | Y56: N | Z56: https://x.com/BookitWithTrent/status/2089095668891603249 | AA56: "Sunday Night Mortal Mega" 20U MAX; later posts ("first inning Mariners nuke", "in urine") imply loss but not explicit | AB56: Single | AC56: =IF(ISNUMBER(V56),Q56,"") | AD56: =IF(ISNUMBER(W56),R56,"")
A57: T-151255 | B57: Trent | C57: 46251.543 | D57: =IF(C57="","",TEXT(C57,"dddd")) | E57: 46251 | F57: =IF(E57="","",TEXT(E57,"dddd")) | G57: 8:40 PM | H57: N | J57: MLB | K57: MLB | L57: parlay | M57: Rays ML; Phillies ML; Braves ML; Royals ML; Dodgers ML | N57: 5 | O57: +800 | P57: 9 | Q57: 1000 | S57: 9000 | T57: Pikkit | U57: L | V57: =IF(NOT(ISNUMBER(Q57)),"",IF(U57="W",IF(ISNUMBER(S57),S57-Q57,IF(ISNUMBER(P57),Q57*(P57-1),"")),IF(U57="L",-Q57,IF(U57="Push",0,"")))) | W57: =IF(NOT(ISNUMBER(R57)),"",IF(U57="W",IF(ISNUMBER(P57),R57*(P57-1),""),IF(U57="L",-R57,IF(U57="Push",0,"")))) | X57: posted | Y57: N | Z57: https://x.com/BookitWithTrent/status/2089412398109151255 | AA57: "Monday Fugazi 5"; next day "Lost by 1 leg last night"; slip shows +800 but payout $9,000 | AB57: Parlay/multi-leg | AC57: =IF(ISNUMBER(V57),Q57,"") | AD57: =IF(ISNUMBER(W57),R57,"")
A58: T-869741 | B58: Trent | C58: 46251.609 | D58: =IF(C58="","",TEXT(C58,"dddd")) | E58: 46251 | F58: =IF(E58="","",TEXT(E58,"dddd")) | G58: not matched | H58: N | J58: MLB | K58: MLB | L58: PrizePicks/DFS | M58: Junior Caminero o6.5 HFS; Jac Caglianone o6 HFS; Ronald Acuna Jr. o6.5 HFS; Shohei Ohtani o11.5 HFS | N58: 4 | O58: not shown | P58: 10 | Q58: 1000 | S58: 10000 | T58: PrizePicks | U58: L | V58: =IF(NOT(ISNUMBER(Q58)),"",IF(U58="W",IF(ISNUMBER(S58),S58-Q58,IF(ISNUMBER(P58),Q58*(P58-1),"")),IF(U58="L",-Q58,IF(U58="Push",0,"")))) | W58: =IF(NOT(ISNUMBER(R58)),"",IF(U58="W",IF(ISNUMBER(P58),R58*(P58-1),""),IF(U58="L",-R58,IF(U58="Push",0,"")))) | X58: posted | Y58: N | Z58: https://x.com/BookitWithTrent/status/2089436176901869741 | AA58: Caminero finished with 3 ("Literally fuck Junior"); Game date assumed = post date (CT); Decimal odds derived from payout/stake | AB58: Parlay/multi-leg | AC58: =IF(ISNUMBER(V58),Q58,"") | AD58: =IF(ISNUMBER(W58),R58,"")
A59: T-411548 | B59: Trent | C59: 46251.617 | D59: =IF(C59="","",TEXT(C59,"dddd")) | E59: 46251 | F59: =IF(E59="","",TEXT(E59,"dddd")) | G59: not matched | H59: N | J59: MLB | K59: MLB | L59: PrizePicks/DFS | M59: o1.5 H+R+RBI(?) each: Caminero; Harper; Caglianone; Olson; Miguel Vargas; Max Muncy | N59: 6 | O59: not shown | P59: 108 | Q59: 500 | S59: 54000 | T59: PrizePicks | U59: L | V59: =IF(NOT(ISNUMBER(Q59)),"",IF(U59="W",IF(ISNUMBER(S59),S59-Q59,IF(ISNUMBER(P59),Q59*(P59-1),"")),IF(U59="L",-Q59,IF(U59="Push",0,"")))) | W59: =IF(NOT(ISNUMBER(R59)),"",IF(U59="W",IF(ISNUMBER(P59),R59*(P59-1),""),IF(U59="L",-R59,IF(U59="Push",0,"")))) | X59: graded from final | Y59: N | Z59: https://x.com/BookitWithTrent/status/2089439184402411548 | AA59: line shown as 2.5? H+R+RBI with demon icons (small image); Final: Caminero 1 H+R+RBI; Decimal odds derived from payout/stake | AB59: Parlay/multi-leg | AC59: =IF(ISNUMBER(V59),Q59,"") | AD59: =IF(ISNUMBER(W59),R59,"")
A60: T-334174 | B60: Trent | C60: 46252.571 | D60: =IF(C60="","",TEXT(C60,"dddd")) | E60: 46252 | F60: =IF(E60="","",TEXT(E60,"dddd")) | G60: 8:10 PM | H60: N | J60: MLB | K60: MLB | L60: parlay | M60: Phillies ML; Guardians ML; Brewers ML; Cubs ML; Astros ML | N60: 5 | O60: +850 | P60: 9.5 | Q60: 1000 | S60: 9500 | T60: Pikkit | U60: L | V60: =IF(NOT(ISNUMBER(Q60)),"",IF(U60="W",IF(ISNUMBER(S60),S60-Q60,IF(ISNUMBER(P60),Q60*(P60-1),"")),IF(U60="L",-Q60,IF(U60="Push",0,"")))) | W60: =IF(NOT(ISNUMBER(R60)),"",IF(U60="W",IF(ISNUMBER(P60),R60*(P60-1),""),IF(U60="L",-R60,IF(U60="Push",0,"")))) | X60: posted | Y60: N | Z60: https://x.com/BookitWithTrent/status/2089785110908334174 | AA60: "Fugazi Five"; result slip (301365) shows Astros leg lost | AB60: Parlay/multi-leg | AC60: =IF(ISNUMBER(V60),Q60,"") | AD60: =IF(ISNUMBER(W60),R60,"")
A61: T-976207 | B61: Trent | C61: 46252.618 | D61: =IF(C61="","",TEXT(C61,"dddd")) | E61: 46252 | F61: =IF(E61="","",TEXT(E61,"dddd")) | G61: not matched | H61: N | J61: MLB | K61: MLB | L61: PrizePicks/DFS | M61: Foster Griffin o34.5 PFS; Robbie Ray o4.5 K; Ozzie Albies o1.5 H+R+RBI; Yordan Alvarez o7.5 HFS | N61: 4 | O61: not shown | P61: 10 | Q61: 1000 | S61: 10000 | T61: PrizePicks | U61: L | V61: =IF(NOT(ISNUMBER(Q61)),"",IF(U61="W",IF(ISNUMBER(S61),S61-Q61,IF(ISNUMBER(P61),Q61*(P61-1),"")),IF(U61="L",-Q61,IF(U61="Push",0,"")))) | W61: =IF(NOT(ISNUMBER(R61)),"",IF(U61="W",IF(ISNUMBER(P61),R61*(P61-1),""),IF(U61="L",-R61,IF(U61="Push",0,"")))) | X61: graded from final | Y61: N | Z61: https://x.com/BookitWithTrent/status/2089801846348976207 | AA61: "4 man nuke of the night"; Final: Robbie Ray 4 K; Decimal odds derived from payout/stake | AB61: Parlay/multi-leg | AC61: =IF(ISNUMBER(V61),Q61,"") | AD61: =IF(ISNUMBER(W61),R61,"")
A62: S-924096 | B62: Steve | C62: 46252.661 | D62: =IF(C62="","",TEXT(C62,"dddd")) | E62: 46252 | F62: =IF(E62="","",TEXT(E62,"dddd")) | G62: 7:10 PM | H62: N | J62: MLB | K62: MLB | L62: ML | M62: San Diego Padres ML vs New York Mets | N62: 1 | O62: -114 | P62: 1.8772 | Q62: 40000 | S62: 75200 | T62: Gamdom | U62: W | V62: =IF(NOT(ISNUMBER(Q62)),"",IF(U62="W",IF(ISNUMBER(S62),S62-Q62,IF(ISNUMBER(P62),Q62*(P62-1),"")),IF(U62="L",-Q62,IF(U62="Push",0,"")))) | W62: =IF(NOT(ISNUMBER(R62)),"",IF(U62="W",IF(ISNUMBER(P62),R62*(P62-1),""),IF(U62="L",-R62,IF(U62="Push",0,"")))) | X62: graded from final | Y62: Y - tags Gamdom | Z62: https://x.com/stevewilldoit/status/2089817642919924096 | AA62: "AI guy" pick | AB62: Single | AC62: =IF(ISNUMBER(V62),Q62,"") | AD62: =IF(ISNUMBER(W62),R62,"")
A63: S-924096b | B63: Steve | C63: 46252.661 | D63: =IF(C63="","",TEXT(C63,"dddd")) | E63: 46252 | F63: =IF(E63="","",TEXT(E63,"dddd")) | G63: 7:40 PM | H63: N | J63: MLB | K63: MLB | L63: ML | M63: Atlanta Braves ML vs Minnesota Twins | N63: 1 | O63: -139 | P63: 1.7194 | Q63: 40000 | S63: 68800 | T63: Gamdom | U63: L | V63: =IF(NOT(ISNUMBER(Q63)),"",IF(U63="W",IF(ISNUMBER(S63),S63-Q63,IF(ISNUMBER(P63),Q63*(P63-1),"")),IF(U63="L",-Q63,IF(U63="Push",0,"")))) | W63: =IF(NOT(ISNUMBER(R63)),"",IF(U63="W",IF(ISNUMBER(P63),R63*(P63-1),""),IF(U63="L",-R63,IF(U63="Push",0,"")))) | X63: graded from final | Y63: Y - tags Gamdom | Z63: https://x.com/stevewilldoit/status/2089817642919924096 | AA63: "AI guy" pick (ATL FG ML -127 per text) | AB63: Single | AC63: =IF(ISNUMBER(V63),Q63,"") | AD63: =IF(ISNUMBER(W63),R63,"")
A64: T-510431 | B64: Trent | C64: 46252.71 | D64: =IF(C64="","",TEXT(C64,"dddd")) | E64: 46252 | F64: =IF(E64="","",TEXT(E64,"dddd")) | G64: 7:40 PM | H64: N | J64: MLB | K64: MLB | L64: ML | M64: Braves ML (vs Twins) | N64: 1 | O64: -135 | P64: 1.7407 | R64: 10 | T64: not shown | U64: L | V64: =IF(NOT(ISNUMBER(Q64)),"",IF(U64="W",IF(ISNUMBER(S64),S64-Q64,IF(ISNUMBER(P64),Q64*(P64-1),"")),IF(U64="L",-Q64,IF(U64="Push",0,"")))) | W64: =IF(NOT(ISNUMBER(R64)),"",IF(U64="W",IF(ISNUMBER(P64),R64*(P64-1),""),IF(U64="L",-R64,IF(U64="Push",0,"")))) | X64: graded from final | Y64: N | Z64: https://x.com/BookitWithTrent/status/2089835155850510431 | AA64: "MLB Mortal Mega Max" 10u | AB64: Single | AC64: =IF(ISNUMBER(V64),Q64,"") | AD64: =IF(ISNUMBER(W64),R64,"")
A65: S-221262 | B65: Steve | C65: 46252.78 | D65: =IF(C65="","",TEXT(C65,"dddd")) | E65: 46252 | F65: =IF(E65="","",TEXT(E65,"dddd")) | G65: 7:10 PM | H65: N | J65: MLB | K65: MLB | L65: ML | M65: San Diego Padres ML (live) vs NY Mets | N65: 1 | O65: -118 | P65: 1.8475 | Q65: 50000 | S65: 92500 | T65: Gamdom | U65: W | V65: =IF(NOT(ISNUMBER(Q65)),"",IF(U65="W",IF(ISNUMBER(S65),S65-Q65,IF(ISNUMBER(P65),Q65*(P65-1),"")),IF(U65="L",-Q65,IF(U65="Push",0,"")))) | W65: =IF(NOT(ISNUMBER(R65)),"",IF(U65="W",IF(ISNUMBER(P65),R65*(P65-1),""),IF(U65="L",-R65,IF(U65="Push",0,"")))) | X65: posted | Y65: Y - tags Gamdom | Z65: https://x.com/stevewilldoit/status/2089860709618221262 | AA65: Live bet on marker; "BOOOOOM!!!" reply | AB65: Single | AC65: =IF(ISNUMBER(V65),Q65,"") | AD65: =IF(ISNUMBER(W65),R65,"")
A66: T-588040 | B66: Trent | C66: 46253.439 | D66: =IF(C66="","",TEXT(C66,"dddd")) | E66: 46253 | F66: =IF(E66="","",TEXT(E66,"dddd")) | G66: 12:35 PM | H66: N | J66: MLB | K66: MLB | L66: spread | M66: Pirates F5 -0.5 | N66: 1 | O66: -115 | P66: 1.8696 | T66: not shown | U66: L | V66: =IF(NOT(ISNUMBER(Q66)),"",IF(U66="W",IF(ISNUMBER(S66),S66-Q66,IF(ISNUMBER(P66),Q66*(P66-1),"")),IF(U66="L",-Q66,IF(U66="Push",0,"")))) | W66: =IF(NOT(ISNUMBER(R66)),"",IF(U66="W",IF(ISNUMBER(P66),R66*(P66-1),""),IF(U66="L",-R66,IF(U66="Push",0,"")))) | X66: posted | Y66: N | Z66: https://x.com/BookitWithTrent/status/2090099455072588040 | AA66: Daytime card; "lost every bet today" | AB66: Single | AC66: =IF(ISNUMBER(V66),Q66,"") | AD66: =IF(ISNUMBER(W66),R66,"")
A67: T-588040b | B67: Trent | C67: 46253.439 | D67: =IF(C67="","",TEXT(C67,"dddd")) | E67: 46253 | F67: =IF(E67="","",TEXT(E67,"dddd")) | G67: 1:10 PM | H67: N | J67: MLB | K67: MLB | L67: ML | M67: Padres ML | N67: 1 | O67: -130 | P67: 1.7692 | T67: not shown | U67: L | V67: =IF(NOT(ISNUMBER(Q67)),"",IF(U67="W",IF(ISNUMBER(S67),S67-Q67,IF(ISNUMBER(P67),Q67*(P67-1),"")),IF(U67="L",-Q67,IF(U67="Push",0,"")))) | W67: =IF(NOT(ISNUMBER(R67)),"",IF(U67="W",IF(ISNUMBER(P67),R67*(P67-1),""),IF(U67="L",-R67,IF(U67="Push",0,"")))) | X67: posted | Y67: N | Z67: https://x.com/BookitWithTrent/status/2090099455072588040 | AA67: Daytime card; "lost every bet today" | AB67: Single | AC67: =IF(ISNUMBER(V67),Q67,"") | AD67: =IF(ISNUMBER(W67),R67,"")
A68: T-588040c | B68: Trent | C68: 46253.439 | D68: =IF(C68="","",TEXT(C68,"dddd")) | E68: 46253 | F68: =IF(E68="","",TEXT(E68,"dddd")) | G68: 1:40 PM | H68: N | J68: MLB | K68: MLB | L68: total | M68: Braves/Twins Under 8.5 | N68: 1 | O68: -110 | P68: 1.9091 | T68: not shown | U68: L | V68: =IF(NOT(ISNUMBER(Q68)),"",IF(U68="W",IF(ISNUMBER(S68),S68-Q68,IF(ISNUMBER(P68),Q68*(P68-1),"")),IF(U68="L",-Q68,IF(U68="Push",0,"")))) | W68: =IF(NOT(ISNUMBER(R68)),"",IF(U68="W",IF(ISNUMBER(P68),R68*(P68-1),""),IF(U68="L",-R68,IF(U68="Push",0,"")))) | X68: posted | Y68: N | Z68: https://x.com/BookitWithTrent/status/2090099455072588040 | AA68: Daytime card; "lost every bet today" | AB68: Single | AC68: =IF(ISNUMBER(V68),Q68,"") | AD68: =IF(ISNUMBER(W68),R68,"")
A69: T-588040d | B69: Trent | C69: 46253.439 | D69: =IF(C69="","",TEXT(C69,"dddd")) | E69: 46253 | F69: =IF(E69="","",TEXT(E69,"dddd")) | G69: 2:20 PM | H69: N | J69: MLB | K69: MLB | L69: total | M69: White Sox/Cubs Over 8 | N69: 1 | O69: -110 | P69: 1.9091 | T69: not shown | U69: L | V69: =IF(NOT(ISNUMBER(Q69)),"",IF(U69="W",IF(ISNUMBER(S69),S69-Q69,IF(ISNUMBER(P69),Q69*(P69-1),"")),IF(U69="L",-Q69,IF(U69="Push",0,"")))) | W69: =IF(NOT(ISNUMBER(R69)),"",IF(U69="W",IF(ISNUMBER(P69),R69*(P69-1),""),IF(U69="L",-R69,IF(U69="Push",0,"")))) | X69: posted | Y69: N | Z69: https://x.com/BookitWithTrent/status/2090099455072588040 | AA69: Daytime card; "lost every bet today" | AB69: Single | AC69: =IF(ISNUMBER(V69),Q69,"") | AD69: =IF(ISNUMBER(W69),R69,"")
A70: S-810023 | B70: Steve | C70: 46253.502 | D70: =IF(C70="","",TEXT(C70,"dddd")) | E70: 46253 | F70: =IF(E70="","",TEXT(E70,"dddd")) | G70: 1:10 PM | H70: N | J70: MLB | K70: MLB | L70: ML | M70: San Diego Padres F5 1x2 vs NY Mets | N70: 1 | O70: -104 | P70: 1.9615 | Q70: 100000 | S70: 196000 | T70: Gamdom | U70: L | V70: =IF(NOT(ISNUMBER(Q70)),"",IF(U70="W",IF(ISNUMBER(S70),S70-Q70,IF(ISNUMBER(P70),Q70*(P70-1),"")),IF(U70="L",-Q70,IF(U70="Push",0,"")))) | W70: =IF(NOT(ISNUMBER(R70)),"",IF(U70="W",IF(ISNUMBER(P70),R70*(P70-1),""),IF(U70="L",-R70,IF(U70="Push",0,"")))) | X70: graded from final | Y70: Y - tags Gamdom | Z70: https://x.com/stevewilldoit/status/2090122504991810023 | AA70: "Not looking good"; "push if we tie" (actually a 3-way market) | AB70: Single | AC70: =IF(ISNUMBER(V70),Q70,"") | AD70: =IF(ISNUMBER(W70),R70,"")
A71: T-011970 | B71: Trent | C71: 46253.625 | D71: =IF(C71="","",TEXT(C71,"dddd")) | E71: 46253 | F71: =IF(E71="","",TEXT(E71,"dddd")) | G71: not matched | H71: N | J71: MLB | K71: MLB | L71: PrizePicks/DFS | M71: Parker Messick o37.5 PFS; Drew Rasmussen u1.5 ER; Elly De La Cruz o7.5 HFS; Andy Pages o2.5 H+R+RBI | N71: 4 | O71: not shown | P71: 10 | Q71: 1000 | S71: 10000 | T71: PrizePicks | U71: L | V71: =IF(NOT(ISNUMBER(Q71)),"",IF(U71="W",IF(ISNUMBER(S71),S71-Q71,IF(ISNUMBER(P71),Q71*(P71-1),"")),IF(U71="L",-Q71,IF(U71="Push",0,"")))) | W71: =IF(NOT(ISNUMBER(R71)),"",IF(U71="W",IF(ISNUMBER(P71),R71*(P71-1),""),IF(U71="L",-R71,IF(U71="Push",0,"")))) | X71: graded from final | Y71: N | Z71: https://x.com/BookitWithTrent/status/2090166817260011970 | AA71: Final: Rasmussen 5 ER; Decimal odds derived from payout/stake | AB71: Parlay/multi-leg | AC71: =IF(ISNUMBER(V71),Q71,"") | AD71: =IF(ISNUMBER(W71),R71,"")
A72: T-532165 | B72: Trent | C72: 46253.636 | D72: =IF(C72="","",TEXT(C72,"dddd")) | E72: 46253 | F72: =IF(E72="","",TEXT(E72,"dddd")) | G72: 6:40 PM | H72: N | J72: MLB | K72: MLB | L72: spread | M72: Guardians -1.5 | N72: 1 | O72: -105 | P72: 1.9524 | T72: not shown | U72: L | V72: =IF(NOT(ISNUMBER(Q72)),"",IF(U72="W",IF(ISNUMBER(S72),S72-Q72,IF(ISNUMBER(P72),Q72*(P72-1),"")),IF(U72="L",-Q72,IF(U72="Push",0,"")))) | W72: =IF(NOT(ISNUMBER(R72)),"",IF(U72="W",IF(ISNUMBER(P72),R72*(P72-1),""),IF(U72="L",-R72,IF(U72="Push",0,"")))) | X72: posted | Y72: N | Z72: https://x.com/BookitWithTrent/status/2090170737537532165 | AA72: "Nuke of the Night"; "lost every bet today" | AB72: Single | AC72: =IF(ISNUMBER(V72),Q72,"") | AD72: =IF(ISNUMBER(W72),R72,"")
A73: S-963765 | B73: Steve | C73: 46253.692 | D73: =IF(C73="","",TEXT(C73,"dddd")) | E73: 46253 | F73: =IF(E73="","",TEXT(E73,"dddd")) | G73: 6:40 PM | H73: N | J73: MLB | K73: MLB | L73: total | M73: Guardians vs Giants F5 Under 4 | N73: 1 | O73: -122 | P73: 1.8197 | Q73: 75000 | S73: 136500 | T73: Gamdom | U73: W | V73: =IF(NOT(ISNUMBER(Q73)),"",IF(U73="W",IF(ISNUMBER(S73),S73-Q73,IF(ISNUMBER(P73),Q73*(P73-1),"")),IF(U73="L",-Q73,IF(U73="Push",0,"")))) | W73: =IF(NOT(ISNUMBER(R73)),"",IF(U73="W",IF(ISNUMBER(P73),R73*(P73-1),""),IF(U73="L",-R73,IF(U73="Push",0,"")))) | X73: graded from final | Y73: Y - tags Gamdom | Z73: https://x.com/stevewilldoit/status/2090191206797963765 | AA73: AI guy pick | AB73: Single | AC73: =IF(ISNUMBER(V73),Q73,"") | AD73: =IF(ISNUMBER(W73),R73,"")
A74: S-308082 | B74: Steve | C74: 46253.72 | D74: =IF(C74="","",TEXT(C74,"dddd")) | E74: 46253 | F74: =IF(E74="","",TEXT(E74,"dddd")) | G74: 6:40 PM | H74: N | J74: MLB | K74: MLB | L74: total | M74: Guardians vs Giants F5 Under 4.5 | N74: 1 | O74: -167 | P74: 1.5988 | Q74: 53000 | S74: 84800 | T74: Gamdom | U74: W | V74: =IF(NOT(ISNUMBER(Q74)),"",IF(U74="W",IF(ISNUMBER(S74),S74-Q74,IF(ISNUMBER(P74),Q74*(P74-1),"")),IF(U74="L",-Q74,IF(U74="Push",0,"")))) | W74: =IF(NOT(ISNUMBER(R74)),"",IF(U74="W",IF(ISNUMBER(P74),R74*(P74-1),""),IF(U74="L",-R74,IF(U74="Push",0,"")))) | X74: graded from final | Y74: N | Z74: https://x.com/stevewilldoit/status/2090201501503308082 | AA74: Added after the U4 bet ("Fuck it") | AB74: Single | AC74: =IF(ISNUMBER(V74),Q74,"") | AD74: =IF(ISNUMBER(W74),R74,"")
A75: S-738112 | B75: Steve | C75: 46253.793 | D75: =IF(C75="","",TEXT(C75,"dddd")) | E75: 46253 | F75: =IF(E75="","",TEXT(E75,"dddd")) | G75: 8:05 PM | H75: N | J75: MLB | K75: MLB | L75: ML | M75: Washington Nationals ML vs Texas Rangers | N75: 1 | O75: +109 | P75: 2.09 | Q75: 50000 | S75: 104500 | T75: Gamdom | U75: W | V75: =IF(NOT(ISNUMBER(Q75)),"",IF(U75="W",IF(ISNUMBER(S75),S75-Q75,IF(ISNUMBER(P75),Q75*(P75-1),"")),IF(U75="L",-Q75,IF(U75="Push",0,"")))) | W75: =IF(NOT(ISNUMBER(R75)),"",IF(U75="W",IF(ISNUMBER(P75),R75*(P75-1),""),IF(U75="L",-R75,IF(U75="Push",0,"")))) | X75: graded from final | Y75: N | Z75: https://x.com/stevewilldoit/status/2090227712589738112 | AA75: "Not confident play at all" | AB75: Single | AC75: =IF(ISNUMBER(V75),Q75,"") | AD75: =IF(ISNUMBER(W75),R75,"")
A76: S-276650 | B76: Steve | C76: 46253.881 | D76: =IF(C76="","",TEXT(C76,"dddd")) | E76: 46253 | F76: =IF(E76="","",TEXT(E76,"dddd")) | G76: 8:05 PM | H76: N | J76: MLB | K76: MLB | L76: spread | M76: Washington Nationals -1.5 (live, up 2-0) vs Texas Rangers | N76: 1 | O76: -133 | P76: 1.7519 | Q76: 137000 | S76: 239750 | T76: Gamdom | U76: W | V76: =IF(NOT(ISNUMBER(Q76)),"",IF(U76="W",IF(ISNUMBER(S76),S76-Q76,IF(ISNUMBER(P76),Q76*(P76-1),"")),IF(U76="L",-Q76,IF(U76="Push",0,"")))) | W76: =IF(NOT(ISNUMBER(R76)),"",IF(U76="W",IF(ISNUMBER(P76),R76*(P76-1),""),IF(U76="L",-R76,IF(U76="Push",0,"")))) | X76: graded from final | Y76: Y - tags Gamdom | Z76: https://x.com/stevewilldoit/status/2090259861053276650 | AA76: "Bet this on accident live when we were up 2-0... Let's go" | AB76: Single | AC76: =IF(ISNUMBER(V76),Q76,"") | AD76: =IF(ISNUMBER(W76),R76,"")
A77: T-054664 | B77: Trent | C77: 46254.46 | D77: =IF(C77="","",TEXT(C77,"dddd")) | E77: 46254 | F77: =IF(E77="","",TEXT(E77,"dddd")) | G77: 12:40 PM | H77: N | J77: MLB | K77: MLB | L77: total | M77: Cardinals/Reds Over 8.5 | N77: 1 | O77: not shown | T77: not shown | U77: W | V77: =IF(NOT(ISNUMBER(Q77)),"",IF(U77="W",IF(ISNUMBER(S77),S77-Q77,IF(ISNUMBER(P77),Q77*(P77-1),"")),IF(U77="L",-Q77,IF(U77="Push",0,"")))) | W77: =IF(NOT(ISNUMBER(R77)),"",IF(U77="W",IF(ISNUMBER(P77),R77*(P77-1),""),IF(U77="L",-R77,IF(U77="Push",0,"")))) | X77: graded from final | Y77: N | Z77: https://x.com/BookitWithTrent/status/2090469355205054664 | AA77: Daytime card | AB77: Single | AC77: =IF(ISNUMBER(V77),Q77,"") | AD77: =IF(ISNUMBER(W77),R77,"")
A78: T-054664b | B78: Trent | C78: 46254.46 | D78: =IF(C78="","",TEXT(C78,"dddd")) | E78: 46254 | F78: =IF(E78="","",TEXT(E78,"dddd")) | G78: 1:10 PM | H78: N | J78: MLB | K78: MLB | L78: total | M78: Giants/Guardians Under 7 | N78: 1 | O78: not shown | T78: not shown | U78: Push | V78: =IF(NOT(ISNUMBER(Q78)),"",IF(U78="W",IF(ISNUMBER(S78),S78-Q78,IF(ISNUMBER(P78),Q78*(P78-1),"")),IF(U78="L",-Q78,IF(U78="Push",0,"")))) | W78: =IF(NOT(ISNUMBER(R78)),"",IF(U78="W",IF(ISNUMBER(P78),R78*(P78-1),""),IF(U78="L",-R78,IF(U78="Push",0,"")))) | X78: graded from final | Y78: N | Z78: https://x.com/BookitWithTrent/status/2090469355205054664 | AA78: Daytime card | AB78: Single | AC78: =IF(ISNUMBER(V78),Q78,"") | AD78: =IF(ISNUMBER(W78),R78,"")
A79: T-054664c | B79: Trent | C79: 46254.46 | D79: =IF(C79="","",TEXT(C79,"dddd")) | E79: 46254 | F79: =IF(E79="","",TEXT(E79,"dddd")) | G79: 1:10 PM | H79: N | J79: MLB | K79: MLB | L79: spread | M79: Blue Jays +1.5 | N79: 1 | O79: not shown | T79: not shown | U79: W | V79: =IF(NOT(ISNUMBER(Q79)),"",IF(U79="W",IF(ISNUMBER(S79),S79-Q79,IF(ISNUMBER(P79),Q79*(P79-1),"")),IF(U79="L",-Q79,IF(U79="Push",0,"")))) | W79: =IF(NOT(ISNUMBER(R79)),"",IF(U79="W",IF(ISNUMBER(P79),R79*(P79-1),""),IF(U79="L",-R79,IF(U79="Push",0,"")))) | X79: graded from final | Y79: N | Z79: https://x.com/BookitWithTrent/status/2090469355205054664 | AA79: Daytime card | AB79: Single | AC79: =IF(ISNUMBER(V79),Q79,"") | AD79: =IF(ISNUMBER(W79),R79,"")
A80: T-054664d | B80: Trent | C80: 46254.46 | D80: =IF(C80="","",TEXT(C80,"dddd")) | E80: 46254 | F80: =IF(E80="","",TEXT(E80,"dddd")) | G80: 2:10 PM | H80: N | J80: MLB | K80: MLB | L80: ML | M80: Brewers ML | N80: 1 | O80: not shown | T80: not shown | U80: W | V80: =IF(NOT(ISNUMBER(Q80)),"",IF(U80="W",IF(ISNUMBER(S80),S80-Q80,IF(ISNUMBER(P80),Q80*(P80-1),"")),IF(U80="L",-Q80,IF(U80="Push",0,"")))) | W80: =IF(NOT(ISNUMBER(R80)),"",IF(U80="W",IF(ISNUMBER(P80),R80*(P80-1),""),IF(U80="L",-R80,IF(U80="Push",0,"")))) | X80: graded from final | Y80: N | Z80: https://x.com/BookitWithTrent/status/2090469355205054664 | AA80: Daytime card | AB80: Single | AC80: =IF(ISNUMBER(V80),Q80,"") | AD80: =IF(ISNUMBER(W80),R80,"")
A81: T-054664e | B81: Trent | C81: 46254.46 | D81: =IF(C81="","",TEXT(C81,"dddd")) | E81: 46254 | F81: =IF(E81="","",TEXT(E81,"dddd")) | G81: 2:10 PM | H81: N | J81: MLB | K81: MLB | L81: ML | M81: Braves ML | N81: 1 | O81: not shown | T81: not shown | U81: W | V81: =IF(NOT(ISNUMBER(Q81)),"",IF(U81="W",IF(ISNUMBER(S81),S81-Q81,IF(ISNUMBER(P81),Q81*(P81-1),"")),IF(U81="L",-Q81,IF(U81="Push",0,"")))) | W81: =IF(NOT(ISNUMBER(R81)),"",IF(U81="W",IF(ISNUMBER(P81),R81*(P81-1),""),IF(U81="L",-R81,IF(U81="Push",0,"")))) | X81: graded from final | Y81: N | Z81: https://x.com/BookitWithTrent/status/2090469355205054664 | AA81: Daytime card | AB81: Single | AC81: =IF(ISNUMBER(V81),Q81,"") | AD81: =IF(ISNUMBER(W81),R81,"")
A82: T-054664f | B82: Trent | C82: 46254.46 | D82: =IF(C82="","",TEXT(C82,"dddd")) | E82: 46254 | F82: =IF(E82="","",TEXT(E82,"dddd")) | G82: 2:10 PM | H82: N | J82: MLB | K82: MLB | L82: total | M82: Royals/Athletics Under 8 | N82: 1 | O82: not shown | T82: not shown | U82: Push | V82: =IF(NOT(ISNUMBER(Q82)),"",IF(U82="W",IF(ISNUMBER(S82),S82-Q82,IF(ISNUMBER(P82),Q82*(P82-1),"")),IF(U82="L",-Q82,IF(U82="Push",0,"")))) | W82: =IF(NOT(ISNUMBER(R82)),"",IF(U82="W",IF(ISNUMBER(P82),R82*(P82-1),""),IF(U82="L",-R82,IF(U82="Push",0,"")))) | X82: graded from final | Y82: N | Z82: https://x.com/BookitWithTrent/status/2090469355205054664 | AA82: Daytime card | AB82: Single | AC82: =IF(ISNUMBER(V82),Q82,"") | AD82: =IF(ISNUMBER(W82),R82,"")
A83: S-208025 | B83: Steve | C83: 46254.483 | D83: =IF(C83="","",TEXT(C83,"dddd")) | E83: 46254 | F83: =IF(E83="","",TEXT(E83,"dddd")) | G83: 12:40 PM | H83: N | J83: MLB | K83: MLB | L83: ML | M83: St. Louis Cardinals F5 ML | N83: 1 | O83: +114 | P83: 2.14 | Q83: 35000 | S83: 74900 | T83: Gamdom | U83: W | V83: =IF(NOT(ISNUMBER(Q83)),"",IF(U83="W",IF(ISNUMBER(S83),S83-Q83,IF(ISNUMBER(P83),Q83*(P83-1),"")),IF(U83="L",-Q83,IF(U83="Push",0,"")))) | W83: =IF(NOT(ISNUMBER(R83)),"",IF(U83="W",IF(ISNUMBER(P83),R83*(P83-1),""),IF(U83="L",-R83,IF(U83="Push",0,"")))) | X83: graded from final | Y83: Y - tags Gamdom | Z83: https://x.com/stevewilldoit/status/2090477913246208025 | AA83: AI guy text says "STL F5 ML -110"; slip odds 2.14 (discrepancy) | AB83: Single | AC83: =IF(ISNUMBER(V83),Q83,"") | AD83: =IF(ISNUMBER(W83),R83,"")
A84: T-548389 | B84: Trent | C84: 46254.684 | D84: =IF(C84="","",TEXT(C84,"dddd")) | E84: 46254 | F84: =IF(E84="","",TEXT(E84,"dddd")) | G84: not matched | H84: N | J84: MLB | K84: MLB | L84: PrizePicks/DFS | M84: Alec Burleson o7 HFS; Jose Ramirez o6.5 HFS; Alejandro Kirk o5 HFS; Jackson Chourio o5.5 HFS; Bobby Witt Jr. o7 HFS; Munetaka Murakami o5 HFS | N84: 6 | O84: not shown | P84: 37.5 | Q84: 500 | S84: 18750 | T84: PrizePicks | U84: L | V84: =IF(NOT(ISNUMBER(Q84)),"",IF(U84="W",IF(ISNUMBER(S84),S84-Q84,IF(ISNUMBER(P84),Q84*(P84-1),"")),IF(U84="L",-Q84,IF(U84="Push",0,"")))) | W84: =IF(NOT(ISNUMBER(R84)),"",IF(U84="W",IF(ISNUMBER(P84),R84*(P84-1),""),IF(U84="L",-R84,IF(U84="Push",0,"")))) | X84: posted | Y84: N | Z84: https://x.com/BookitWithTrent/status/2090550544712548389 | AA84: Murakami leg missed ("Fuck Murakami man"); Game date assumed = post date (CT); Decimal odds derived from payout/stake | AB84: Parlay/multi-leg | AC84: =IF(ISNUMBER(V84),Q84,"") | AD84: =IF(ISNUMBER(W84),R84,"")
A85: T-720304 | B85: Trent | C85: 46254.708 | D85: =IF(C85="","",TEXT(C85,"dddd")) | E85: 46254 | F85: =IF(E85="","",TEXT(E85,"dddd")) | G85: 8:00 PM | H85: Y | I85: TNF | J85: NFL | K85: NFL Preseason | L85: ML | M85: Raiders ML | N85: 1 | O85: not shown | T85: not shown | U85: W | V85: =IF(NOT(ISNUMBER(Q85)),"",IF(U85="W",IF(ISNUMBER(S85),S85-Q85,IF(ISNUMBER(P85),Q85*(P85-1),"")),IF(U85="L",-Q85,IF(U85="Push",0,"")))) | W85: =IF(NOT(ISNUMBER(R85)),"",IF(U85="W",IF(ISNUMBER(P85),R85*(P85-1),""),IF(U85="L",-R85,IF(U85="Push",0,"")))) | X85: graded from final | Y85: N | Z85: https://x.com/BookitWithTrent/status/2090559247276720304 | AA85: "MORTAL mega max" | AB85: Single | AC85: =IF(ISNUMBER(V85),Q85,"") | AD85: =IF(ISNUMBER(W85),R85,"")
A86: T-027525 | B86: Trent | C86: 46255.479 | D86: =IF(C86="","",TEXT(C86,"dddd")) | E86: 46255 | F86: =IF(E86="","",TEXT(E86,"dddd")) | G86: 4:10 PM | H86: N | J86: MLB | K86: MLB | L86: total | M86: Braves/Brewers Under 5.5 ("Under of Eon") | N86: 1 | O86: +100 | P86: 2 | Q86: 2500 | R86: 10 | S86: 5000 | T86: PrizePicks | U86: W | V86: =IF(NOT(ISNUMBER(Q86)),"",IF(U86="W",IF(ISNUMBER(S86),S86-Q86,IF(ISNUMBER(P86),Q86*(P86-1),"")),IF(U86="L",-Q86,IF(U86="Push",0,"")))) | W86: =IF(NOT(ISNUMBER(R86)),"",IF(U86="W",IF(ISNUMBER(P86),R86*(P86-1),""),IF(U86="L",-R86,IF(U86="Push",0,"")))) | X86: posted | Y86: N | Z86: https://x.com/BookitWithTrent/status/2090838851942027525 | AA86: 10U Mortal Mega Max; "CASH THE UNDER OF EON" | AB86: Single | AC86: =IF(ISNUMBER(V86),Q86,"") | AD86: =IF(ISNUMBER(W86),R86,"")
A87: T-999585 | B87: Trent | C87: 46255.483 | D87: =IF(C87="","",TEXT(C87,"dddd")) | E87: 46255 | F87: =IF(E87="","",TEXT(E87,"dddd")) | G87: not matched | H87: N | J87: MLB | K87: MLB | L87: PrizePicks/DFS | M87: Chris Sale o9.5 K; Jacob Misiorowski o9.5 K | N87: 2 | O87: not shown | P87: 5.75 | Q87: 1000 | S87: 5750 | T87: PrizePicks | U87: L | V87: =IF(NOT(ISNUMBER(Q87)),"",IF(U87="W",IF(ISNUMBER(S87),S87-Q87,IF(ISNUMBER(P87),Q87*(P87-1),"")),IF(U87="L",-Q87,IF(U87="Push",0,"")))) | W87: =IF(NOT(ISNUMBER(R87)),"",IF(U87="W",IF(ISNUMBER(P87),R87*(P87-1),""),IF(U87="L",-R87,IF(U87="Push",0,"")))) | X87: graded from final | Y87: N | Z87: https://x.com/BookitWithTrent/status/2090840165639999585 | AA87: "10 + 10 = $5.75k"; Final: Sale 6 K, Misiorowski 6 K; Decimal odds derived from payout/stake | AB87: Parlay/multi-leg | AC87: =IF(ISNUMBER(V87),Q87,"") | AD87: =IF(ISNUMBER(W87),R87,"")
A88: S-992483 | B88: Steve | C88: 46255.573 | D88: =IF(C88="","",TEXT(C88,"dddd")) | E88: 46255 | F88: =IF(E88="","",TEXT(E88,"dddd")) | G88: 4:10 PM | H88: N | J88: MLB | K88: MLB | L88: total | M88: Braves vs Brewers F5 Under 3 | N88: 1 | O88: -182 | P88: 1.5495 | Q88: 75000 | S88: 116250 | T88: Gamdom | U88: W | V88: =IF(NOT(ISNUMBER(Q88)),"",IF(U88="W",IF(ISNUMBER(S88),S88-Q88,IF(ISNUMBER(P88),Q88*(P88-1),"")),IF(U88="L",-Q88,IF(U88="Push",0,"")))) | W88: =IF(NOT(ISNUMBER(R88)),"",IF(U88="W",IF(ISNUMBER(P88),R88*(P88-1),""),IF(U88="L",-R88,IF(U88="Push",0,"")))) | X88: posted | Y88: Y - tags Gamdom | Z88: https://x.com/stevewilldoit/status/2090872777527992483 | AA88: AI guy text "ATL-MIL F5 U3 -125"; slip 1.55; "💰" follow-up reply | AB88: Single | AC88: =IF(ISNUMBER(V88),Q88,"") | AD88: =IF(ISNUMBER(W88),R88,"")
A89: T-408413 | B89: Trent | C89: 46255.629 | D89: =IF(C89="","",TEXT(C89,"dddd")) | E89: 46255 | F89: =IF(E89="","",TEXT(E89,"dddd")) | G89: 10:10 PM | H89: N | J89: MLB | K89: MLB | L89: parlay | M89: Astros ML; Guardians ML; Dodgers ML; White Sox ML; Mariners ML | N89: 5 | O89: +1100 | P89: 12 | Q89: 1000 | S89: 12000 | T89: Pikkit | U89: W | V89: =IF(NOT(ISNUMBER(Q89)),"",IF(U89="W",IF(ISNUMBER(S89),S89-Q89,IF(ISNUMBER(P89),Q89*(P89-1),"")),IF(U89="L",-Q89,IF(U89="Push",0,"")))) | W89: =IF(NOT(ISNUMBER(R89)),"",IF(U89="W",IF(ISNUMBER(P89),R89*(P89-1),""),IF(U89="L",-R89,IF(U89="Push",0,"")))) | X89: posted | Y89: N | Z89: https://x.com/BookitWithTrent/status/2090893042278408413 | AA89: "Friday Night Fugazi Five"; result slip (308378) all legs checked | AB89: Parlay/multi-leg | AC89: =IF(ISNUMBER(V89),Q89,"") | AD89: =IF(ISNUMBER(W89),R89,"")
A90: S-974013 | B90: Steve | C90: 46255.719 | D90: =IF(C90="","",TEXT(C90,"dddd")) | E90: 46255 | F90: =IF(E90="","",TEXT(E90,"dddd")) | G90: 8:15 PM | H90: N | J90: MLB | K90: MLB | L90: total | M90: Rangers vs Angels F5 Under 4 | N90: 1 | O90: -141 | P90: 1.7092 | Q90: 65000 | S90: 111150 | T90: Gamdom | U90: W | V90: =IF(NOT(ISNUMBER(Q90)),"",IF(U90="W",IF(ISNUMBER(S90),S90-Q90,IF(ISNUMBER(P90),Q90*(P90-1),"")),IF(U90="L",-Q90,IF(U90="Push",0,"")))) | W90: =IF(NOT(ISNUMBER(R90)),"",IF(U90="W",IF(ISNUMBER(P90),R90*(P90-1),""),IF(U90="L",-R90,IF(U90="Push",0,"")))) | X90: graded from final | Y90: Y - tags Gamdom | Z90: https://x.com/stevewilldoit/status/2090925724894974013 | AA90: "Confidence level is not high" | AB90: Single | AC90: =IF(ISNUMBER(V90),Q90,"") | AD90: =IF(ISNUMBER(W90),R90,"")
A91: S-439939 | B91: Steve | C91: 46255.776 | D91: =IF(C91="","",TEXT(C91,"dddd")) | E91: 46255 | F91: =IF(E91="","",TEXT(E91,"dddd")) | G91: 8:15 PM | H91: N | J91: MLB | K91: MLB | L91: total | M91: Rangers vs Angels F5 Under 4 (added) | N91: 1 | O91: -143 | P91: 1.6993 | Q91: 70000 | S91: 119000 | T91: Gamdom | U91: W | V91: =IF(NOT(ISNUMBER(Q91)),"",IF(U91="W",IF(ISNUMBER(S91),S91-Q91,IF(ISNUMBER(P91),Q91*(P91-1),"")),IF(U91="L",-Q91,IF(U91="Push",0,"")))) | W91: =IF(NOT(ISNUMBER(R91)),"",IF(U91="W",IF(ISNUMBER(P91),R91*(P91-1),""),IF(U91="L",-R91,IF(U91="Push",0,"")))) | X91: graded from final | Y91: N | Z91: https://x.com/stevewilldoit/status/2090946509487439939 | AA91: "Added more on under 4" | AB91: Single | AC91: =IF(ISNUMBER(V91),Q91,"") | AD91: =IF(ISNUMBER(W91),R91,"")
A92: S-439939b | B92: Steve | C92: 46255.776 | D92: =IF(C92="","",TEXT(C92,"dddd")) | E92: 46255 | F92: =IF(E92="","",TEXT(E92,"dddd")) | G92: 8:10 PM | H92: N | J92: MLB | K92: MLB | L92: parlay | M92: Orioles ML; White Sox ML; Mets ML; Royals ML (per text) | N92: 4 | O92: +1830 | P92: 19.3 | Q92: 20000 | S92: 386000 | T92: Gamdom | U92: L | V92: =IF(NOT(ISNUMBER(Q92)),"",IF(U92="W",IF(ISNUMBER(S92),S92-Q92,IF(ISNUMBER(P92),Q92*(P92-1),"")),IF(U92="L",-Q92,IF(U92="Push",0,"")))) | W92: =IF(NOT(ISNUMBER(R92)),"",IF(U92="W",IF(ISNUMBER(P92),R92*(P92-1),""),IF(U92="L",-R92,IF(U92="Push",0,"")))) | X92: graded from final | Y92: N | Z92: https://x.com/stevewilldoit/status/2090946509487439939 | AA92: "Have 20k to win 380k"; slip 19.30; only Orioles leg visible | AB92: Parlay/multi-leg | AC92: =IF(ISNUMBER(V92),Q92,"") | AD92: =IF(ISNUMBER(W92),R92,"")
A93: S-521914 | B93: Steve | C93: 46256.414 | D93: =IF(C93="","",TEXT(C93,"dddd")) | E93: 46256 | F93: =IF(E93="","",TEXT(E93,"dddd")) | G93: not matched | H93: N | J93: Soccer | K93: La Liga | L93: total | M93: Athletic Bilbao vs Sevilla Over 2 | N93: 1 | O93: -154 | P93: 1.6494 | Q93: 100000 | S93: 165000 | T93: Gamdom | U93: W | V93: =IF(NOT(ISNUMBER(Q93)),"",IF(U93="W",IF(ISNUMBER(S93),S93-Q93,IF(ISNUMBER(P93),Q93*(P93-1),"")),IF(U93="L",-Q93,IF(U93="Push",0,"")))) | W93: =IF(NOT(ISNUMBER(R93)),"",IF(U93="W",IF(ISNUMBER(P93),R93*(P93-1),""),IF(U93="L",-R93,IF(U93="Push",0,"")))) | X93: graded from final | Y93: Y - tags Gamdom | Z93: https://x.com/stevewilldoit/status/2091177630611521914 | AA93: "Lock from boss man" (Felix/Romer); chat says over 2.5, slip says Over 2; Final: Sevilla 3-1 at Athletic (4 goals, over 2) | AB93: Single | AC93: =IF(ISNUMBER(V93),Q93,"") | AD93: =IF(ISNUMBER(W93),R93,"")
A94: S-521914b | B94: Steve | C94: 46256.414 | D94: =IF(C94="","",TEXT(C94,"dddd")) | E94: 46256 | F94: =IF(E94="","",TEXT(E94,"dddd")) | G94: not matched | H94: N | J94: Soccer | K94: La Liga | L94: other | M94: Second slip (selection cut off) | N94: 1 | O94: -154 | P94: 1.6494 | Q94: 50000 | S94: 82500 | T94: Gamdom | U94: Unknown | V94: =IF(NOT(ISNUMBER(Q94)),"",IF(U94="W",IF(ISNUMBER(S94),S94-Q94,IF(ISNUMBER(P94),Q94*(P94-1),"")),IF(U94="L",-Q94,IF(U94="Push",0,"")))) | W94: =IF(NOT(ISNUMBER(R94)),"",IF(U94="W",IF(ISNUMBER(P94),R94*(P94-1),""),IF(U94="L",-R94,IF(U94="Push",0,"")))) | X94: unverified | Y94: Y - tags Gamdom | Z94: https://x.com/stevewilldoit/status/2091177630611521914 | AA94: selection not shown; Game date assumed = post date (CT) | AB94: Single | AC94: =IF(ISNUMBER(V94),Q94,"") | AD94: =IF(ISNUMBER(W94),R94,"")
A95: S-011750 | B95: Steve | C95: 46256.487 | D95: =IF(C95="","",TEXT(C95,"dddd")) | E95: 46256 | F95: =IF(E95="","",TEXT(E95,"dddd")) | G95: 2:10 PM | H95: N | J95: MLB | K95: MLB | L95: total | M95: Brewers vs Braves F5 Under 4 | N95: 1 | O95: -112 | P95: 1.8929 | Q95: 100000 | S95: 189000 | T95: Gamdom | U95: L | V95: =IF(NOT(ISNUMBER(Q95)),"",IF(U95="W",IF(ISNUMBER(S95),S95-Q95,IF(ISNUMBER(P95),Q95*(P95-1),"")),IF(U95="L",-Q95,IF(U95="Push",0,"")))) | W95: =IF(NOT(ISNUMBER(R95)),"",IF(U95="W",IF(ISNUMBER(P95),R95*(P95-1),""),IF(U95="L",-R95,IF(U95="Push",0,"")))) | X95: graded from final | Y95: Y - tags Gamdom | Z95: https://x.com/stevewilldoit/status/2091204105893011750 | AA95: AI guy text "ATL-MIL F5 Under 4 -105"; later "Hoping for a push on the first bet" | AB95: Single | AC95: =IF(ISNUMBER(V95),Q95,"") | AD95: =IF(ISNUMBER(W95),R95,"")
A96: S-011750b | B96: Steve | C96: 46256.487 | D96: =IF(C96="","",TEXT(C96,"dddd")) | E96: 46256 | F96: =IF(E96="","",TEXT(E96,"dddd")) | G96: 8:10 PM | H96: N | J96: MLB | K96: MLB | L96: spread | M96: Arizona Diamondbacks F5 -0.5 vs Cincinnati Reds | N96: 1 | O96: -135 | P96: 1.7407 | Q96: 100000 | S96: 174000 | T96: Gamdom | U96: L | V96: =IF(NOT(ISNUMBER(Q96)),"",IF(U96="W",IF(ISNUMBER(S96),S96-Q96,IF(ISNUMBER(P96),Q96*(P96-1),"")),IF(U96="L",-Q96,IF(U96="Push",0,"")))) | W96: =IF(NOT(ISNUMBER(R96)),"",IF(U96="W",IF(ISNUMBER(P96),R96*(P96-1),""),IF(U96="L",-R96,IF(U96="Push",0,"")))) | X96: graded from final | Y96: Y - tags Gamdom | Z96: https://x.com/stevewilldoit/status/2091204105893011750 | AA96: AI guy text "Arizona F5 -1/2 -115" | AB96: Single | AC96: =IF(ISNUMBER(V96),Q96,"") | AD96: =IF(ISNUMBER(W96),R96,"")
A97: T-067106 | B97: Trent | C97: 46256.645 | D97: =IF(C97="","",TEXT(C97,"dddd")) | E97: 46256 | F97: =IF(E97="","",TEXT(E97,"dddd")) | G97: 8:10 PM | H97: N | J97: MLB | K97: MLB | L97: parlay | M97: Astros ML; Guardians ML; Dodgers ML; White Sox ML; Mariners ML | N97: 5 | O97: +1100 | P97: 12 | Q97: 1000 | S97: 12000 | T97: Pikkit | U97: L | V97: =IF(NOT(ISNUMBER(Q97)),"",IF(U97="W",IF(ISNUMBER(S97),S97-Q97,IF(ISNUMBER(P97),Q97*(P97-1),"")),IF(U97="L",-Q97,IF(U97="Push",0,"")))) | W97: =IF(NOT(ISNUMBER(R97)),"",IF(U97="W",IF(ISNUMBER(P97),R97*(P97-1),""),IF(U97="L",-R97,IF(U97="Push",0,"")))) | X97: graded from final | Y97: N | Z97: https://x.com/BookitWithTrent/status/2091261360894067106 | AA97: "Saturday Night Fugazi 5" (same lay as previous night) | AB97: Parlay/multi-leg | AC97: =IF(ISNUMBER(V97),Q97,"") | AD97: =IF(ISNUMBER(W97),R97,"")
A98: T-417202 | B98: Trent | C98: 46256.65 | D98: =IF(C98="","",TEXT(C98,"dddd")) | E98: 46256 | F98: =IF(E98="","",TEXT(E98,"dddd")) | G98: not matched | H98: N | J98: MLB | K98: MLB | L98: PrizePicks/DFS | M98: HR o0.5: Mike Trout; Munetaka Murakami; Yordan Alvarez; Shohei Ohtani | N98: 4 | O98: not shown | T98: PrizePicks | U98: L | V98: =IF(NOT(ISNUMBER(Q98)),"",IF(U98="W",IF(ISNUMBER(S98),S98-Q98,IF(ISNUMBER(P98),Q98*(P98-1),"")),IF(U98="L",-Q98,IF(U98="Push",0,"")))) | W98: =IF(NOT(ISNUMBER(R98)),"",IF(U98="W",IF(ISNUMBER(P98),R98*(P98-1),""),IF(U98="L",-R98,IF(U98="Push",0,"")))) | X98: graded from final | Y98: N | Z98: https://x.com/BookitWithTrent/status/2091262999625417202 | AA98: stake not shown; Final: Murakami/Alvarez/Ohtani no HR | AB98: Parlay/multi-leg | AC98: =IF(ISNUMBER(V98),Q98,"") | AD98: =IF(ISNUMBER(W98),R98,"")
A99: T-227453 | B99: Trent | C99: 46256.68 | D99: =IF(C99="","",TEXT(C99,"dddd")) | E99: 46256 | F99: =IF(E99="","",TEXT(E99,"dddd")) | G99: not matched | H99: N | J99: MLB | K99: MLB | L99: prop | M99: Tarik Skubal o8.5 K | N99: 1 | O99: not shown | T99: Bookit app (Beat the Streak) | U99: W | V99: =IF(NOT(ISNUMBER(Q99)),"",IF(U99="W",IF(ISNUMBER(S99),S99-Q99,IF(ISNUMBER(P99),Q99*(P99-1),"")),IF(U99="L",-Q99,IF(U99="Push",0,"")))) | W99: =IF(NOT(ISNUMBER(R99)),"",IF(U99="W",IF(ISNUMBER(P99),R99*(P99-1),""),IF(U99="L",-R99,IF(U99="Push",0,"")))) | X99: graded from final | Y99: N | Z99: https://x.com/BookitWithTrent/status/2091273929348227453 | AA99: "Life on line"; free-to-play streak pick, stake not shown; Final: Skubal 11 K | AB99: Single | AC99: =IF(ISNUMBER(V99),Q99,"") | AD99: =IF(ISNUMBER(W99),R99,"")
A100: T-557787 | B100: Trent | C100: 46257.531 | D100: =IF(C100="","",TEXT(C100,"dddd")) | E100: 46257 | F100: =IF(E100="","",TEXT(E100,"dddd")) | G100: not matched | H100: N | J100: MLB | K100: MLB | L100: prop | M100: Blake Snell o8.5 K | N100: 1 | O100: not shown | T100: Bookit app (Beat the Streak) | U100: W | V100: =IF(NOT(ISNUMBER(Q100)),"",IF(U100="W",IF(ISNUMBER(S100),S100-Q100,IF(ISNUMBER(P100),Q100*(P100-1),"")),IF(U100="L",-Q100,IF(U100="Push",0,"")))) | W100: =IF(NOT(ISNUMBER(R100)),"",IF(U100="W",IF(ISNUMBER(P100),R100*(P100-1),""),IF(U100="L",-R100,IF(U100="Push",0,"")))) | X100: posted | Y100: N | Z100: https://x.com/BookitWithTrent/status/2091582265528557787 | AA100: "holy fuckin chalk"; free-to-play streak pick, stake not shown; Game date assumed = post date (CT) | AB100: Single | AC100: =IF(ISNUMBER(V100),Q100,"") | AD100: =IF(ISNUMBER(W100),R100,"")
...

Sheet Summary
A1: Trent & Steve Bet Tracker — Summary (all formulas reference the Bets tab)
A2: CFB season start (Week 0): | C2: 46261 | D2: Thu Aug 27, 2026 (first FBS game Sat Aug 29, UNC vs TCU in Dublin)
A3: NFL season start (Week 1): | C3: 46274 | D3: Wed Sep 9, 2026 (Patriots at Seahawks)
A5: All bets (Aug 1, 2026 – present)
A6: Bettor | B6: Bets | C6: W | D6: L | E6: Push | F6: Pending | G6: Unknown | H6: Win % (W/(W+L)) | I6: Total staked $ (all $ bets) | J6: Settled staked $ | K6: Net P/L $ | L6: ROI (net / settled $) | M6: Units staked (settled) | N6: Net units | O6: ROI (units)
A7: Trent (@BookitWithTrent) | B7: =COUNTIFS(Bets!$A$2:$A$506,"<>",Bets!$B$2:$B$506,"Trent") | C7: =COUNTIFS(Bets!$A$2:$A$506,"<>",Bets!$B$2:$B$506,"Trent",Bets!$U$2:$U$506,"W") | D7: =COUNTIFS(Bets!$A$2:$A$506,"<>",Bets!$B$2:$B$506,"Trent",Bets!$U$2:$U$506,"L") | E7: =COUNTIFS(Bets!$A$2:$A$506,"<>",Bets!$B$2:$B$506,"Trent",Bets!$U$2:$U$506,"Push") | F7: =COUNTIFS(Bets!$A$2:$A$506,"<>",Bets!$B$2:$B$506,"Trent",Bets!$U$2:$U$506,"Pending") | G7: =COUNTIFS(Bets!$A$2:$A$506,"<>",Bets!$B$2:$B$506,"Trent",Bets!$U$2:$U$506,"Unknown") | H7: =IF(C7+D7=0,"",C7/(C7+D7)) | I7: =SUMIFS(Bets!$Q$2:$Q$506,Bets!$A$2:$A$506,"<>",Bets!$B$2:$B$506,"Trent") | J7: =SUMIFS(Bets!$AC$2:$AC$506,Bets!$A$2:$A$506,"<>",Bets!$B$2:$B$506,"Trent") | K7: =SUMIFS(Bets!$V$2:$V$506,Bets!$A$2:$A$506,"<>",Bets!$B$2:$B$506,"Trent") | L7: =IF(J7=0,"",K7/J7) | M7: =SUMIFS(Bets!$AD$2:$AD$506,Bets!$A$2:$A$506,"<>",Bets!$B$2:$B$506,"Trent") | N7: =SUMIFS(Bets!$W$2:$W$506,Bets!$A$2:$A$506,"<>",Bets!$B$2:$B$506,"Trent") | O7: =IF(M7=0,"",N7/M7)
A8: Steve (@stevewilldoit) | B8: =COUNTIFS(Bets!$A$2:$A$506,"<>",Bets!$B$2:$B$506,"Steve") | C8: =COUNTIFS(Bets!$A$2:$A$506,"<>",Bets!$B$2:$B$506,"Steve",Bets!$U$2:$U$506,"W") | D8: =COUNTIFS(Bets!$A$2:$A$506,"<>",Bets!$B$2:$B$506,"Steve",Bets!$U$2:$U$506,"L") | E8: =COUNTIFS(Bets!$A$2:$A$506,"<>",Bets!$B$2:$B$506,"Steve",Bets!$U$2:$U$506,"Push") | F8: =COUNTIFS(Bets!$A$2:$A$506,"<>",Bets!$B$2:$B$506,"Steve",Bets!$U$2:$U$506,"Pending") | G8: =COUNTIFS(Bets!$A$2:$A$506,"<>",Bets!$B$2:$B$506,"Steve",Bets!$U$2:$U$506,"Unknown") | H8: =IF(C8+D8=0,"",C8/(C8+D8)) | I8: =SUMIFS(Bets!$Q$2:$Q$506,Bets!$A$2:$A$506,"<>",Bets!$B$2:$B$506,"Steve") | J8: =SUMIFS(Bets!$AC$2:$AC$506,Bets!$A$2:$A$506,"<>",Bets!$B$2:$B$506,"Steve") | K8: =SUMIFS(Bets!$V$2:$V$506,Bets!$A$2:$A$506,"<>",Bets!$B$2:$B$506,"Steve") | L8: =IF(J8=0,"",K8/J8) | M8: =SUMIFS(Bets!$AD$2:$AD$506,Bets!$A$2:$A$506,"<>",Bets!$B$2:$B$506,"Steve") | N8: =SUMIFS(Bets!$W$2:$W$506,Bets!$A$2:$A$506,"<>",Bets!$B$2:$B$506,"Steve") | O8: =IF(M8=0,"",N8/M8)
A9: Combined | B9: =COUNTIFS(Bets!$A$2:$A$506,"<>",Bets!$B$2:$B$506,"*") | C9: =COUNTIFS(Bets!$A$2:$A$506,"<>",Bets!$B$2:$B$506,"*",Bets!$U$2:$U$506,"W") | D9: =COUNTIFS(Bets!$A$2:$A$506,"<>",Bets!$B$2:$B$506,"*",Bets!$U$2:$U$506,"L") | E9: =COUNTIFS(Bets!$A$2:$A$506,"<>",Bets!$B$2:$B$506,"*",Bets!$U$2:$U$506,"Push") | F9: =COUNTIFS(Bets!$A$2:$A$506,"<>",Bets!$B$2:$B$506,"*",Bets!$U$2:$U$506,"Pending") | G9: =COUNTIFS(Bets!$A$2:$A$506,"<>",Bets!$B$2:$B$506,"*",Bets!$U$2:$U$506,"Unknown") | H9: =IF(C9+D9=0,"",C9/(C9+D9)) | I9: =SUMIFS(Bets!$Q$2:$Q$506,Bets!$A$2:$A$506,"<>",Bets!$B$2:$B$506,"*") | J9: =SUMIFS(Bets!$AC$2:$AC$506,Bets!$A$2:$A$506,"<>",Bets!$B$2:$B$506,"*") | K9: =SUMIFS(Bets!$V$2:$V$506,Bets!$A$2:$A$506,"<>",Bets!$B$2:$B$506,"*") | L9: =IF(J9=0,"",K9/J9) | M9: =SUMIFS(Bets!$AD$2:$AD$506,Bets!$A$2:$A$506,"<>",Bets!$B$2:$B$506,"*") | N9: =SUMIFS(Bets!$W$2:$W$506,Bets!$A$2:$A$506,"<>",Bets!$B$2:$B$506,"*") | O9: =IF(M9=0,"",N9/M9)
A11: Since CFB start (game date ≥ C2)
A12: Bettor | B12: Bets | C12: W | D12: L | E12: Push | F12: Pending | G12: Unknown | H12: Win % (W/(W+L)) | I12: Total staked $ (all $ bets) | J12: Settled staked $ | K12: Net P/L $ | L12: ROI (net / settled $) | M12: Units staked (settled) | N12: Net units | O12: ROI (units)
A13: Trent (@BookitWithTrent) | B13: =COUNTIFS(Bets!$A$2:$A$506,"<>",Bets!$B$2:$B$506,"Trent",Bets!$E$2:$E$506,">="&$C$2) | C13: =COUNTIFS(Bets!$A$2:$A$506,"<>",Bets!$B$2:$B$506,"Trent",Bets!$E$2:$E$506,">="&$C$2,Bets!$U$2:$U$506,"W") | D13: =COUNTIFS(Bets!$A$2:$A$506,"<>",Bets!$B$2:$B$506,"Trent",Bets!$E$2:$E$506,">="&$C$2,Bets!$U$2:$U$506,"L") | E13: =COUNTIFS(Bets!$A$2:$A$506,"<>",Bets!$B$2:$B$506,"Trent",Bets!$E$2:$E$506,">="&$C$2,Bets!$U$2:$U$506,"Push") | F13: =COUNTIFS(Bets!$A$2:$A$506,"<>",Bets!$B$2:$B$506,"Trent",Bets!$E$2:$E$506,">="&$C$2,Bets!$U$2:$U$506,"Pending") | G13: =COUNTIFS(Bets!$A$2:$A$506,"<>",Bets!$B$2:$B$506,"Trent",Bets!$E$2:$E$506,">="&$C$2,Bets!$U$2:$U$506,"Unknown") | H13: =IF(C13+D13=0,"",C13/(C13+D13)) | I13: =SUMIFS(Bets!$Q$2:$Q$506,Bets!$A$2:$A$506,"<>",Bets!$B$2:$B$506,"Trent",Bets!$E$2:$E$506,">="&$C$2) | J13: =SUMIFS(Bets!$AC$2:$AC$506,Bets!$A$2:$A$506,"<>",Bets!$B$2:$B$506,"Trent",Bets!$E$2:$E$506,">="&$C$2) | K13: =SUMIFS(Bets!$V$2:$V$506,Bets!$A$2:$A$506,"<>",Bets!$B$2:$B$506,"Trent",Bets!$E$2:$E$506,">="&$C$2) | L13: =IF(J13=0,"",K13/J13) | M13: =SUMIFS(Bets!$AD$2:$AD$506,Bets!$A$2:$A$506,"<>",Bets!$B$2:$B$506,"Trent",Bets!$E$2:$E$506,">="&$C$2) | N13: =SUMIFS(Bets!$W$2:$W$506,Bets!$A$2:$A$506,"<>",Bets!$B$2:$B$506,"Trent",Bets!$E$2:$E$506,">="&$C$2) | O13: =IF(M13=0,"",N13/M13)
A14: Steve (@stevewilldoit) | B14: =COUNTIFS(Bets!$A$2:$A$506,"<>",Bets!$B$2:$B$506,"Steve",Bets!$E$2:$E$506,">="&$C$2) | C14: =COUNTIFS(Bets!$A$2:$A$506,"<>",Bets!$B$2:$B$506,"Steve",Bets!$E$2:$E$506,">="&$C$2,Bets!$U$2:$U$506,"W") | D14: =COUNTIFS(Bets!$A$2:$A$506,"<>",Bets!$B$2:$B$506,"Steve",Bets!$E$2:$E$506,">="&$C$2,Bets!$U$2:$U$506,"L") | E14: =COUNTIFS(Bets!$A$2:$A$506,"<>",Bets!$B$2:$B$506,"Steve",Bets!$E$2:$E$506,">="&$C$2,Bets!$U$2:$U$506,"Push") | F14: =COUNTIFS(Bets!$A$2:$A$506,"<>",Bets!$B$2:$B$506,"Steve",Bets!$E$2:$E$506,">="&$C$2,Bets!$U$2:$U$506,"Pending") | G14: =COUNTIFS(Bets!$A$2:$A$506,"<>",Bets!$B$2:$B$506,"Steve",Bets!$E$2:$E$506,">="&$C$2,Bets!$U$2:$U$506,"Unknown") | H14: =IF(C14+D14=0,"",C14/(C14+D14)) | I14: =SUMIFS(Bets!$Q$2:$Q$506,Bets!$A$2:$A$506,"<>",Bets!$B$2:$B$506,"Steve",Bets!$E$2:$E$506,">="&$C$2) | J14: =SUMIFS(Bets!$AC$2:$AC$506,Bets!$A$2:$A$506,"<>",Bets!$B$2:$B$506,"Steve",Bets!$E$2:$E$506,">="&$C$2) | K14: =SUMIFS(Bets!$V$2:$V$506,Bets!$A$2:$A$506,"<>",Bets!$B$2:$B$506,"Steve",Bets!$E$2:$E$506,">="&$C$2) | L14: =IF(J14=0,"",K14/J14) | M14: =SUMIFS(Bets!$AD$2:$AD$506,Bets!$A$2:$A$506,"<>",Bets!$B$2:$B$506,"Steve",Bets!$E$2:$E$506,">="&$C$2) | N14: =SUMIFS(Bets!$W$2:$W$506,Bets!$A$2:$A$506,"<>",Bets!$B$2:$B$506,"Steve",Bets!$E$2:$E$506,">="&$C$2) | O14: =IF(M14=0,"",N14/M14)
A15: Combined | B15: =COUNTIFS(Bets!$A$2:$A$506,"<>",Bets!$B$2:$B$506,"*",Bets!$E$2:$E$506,">="&$C$2) | C15: =COUNTIFS(Bets!$A$2:$A$506,"<>",Bets!$B$2:$B$506,"*",Bets!$E$2:$E$506,">="&$C$2,Bets!$U$2:$U$506,"W") | D15: =COUNTIFS(Bets!$A$2:$A$506,"<>",Bets!$B$2:$B$506,"*",Bets!$E$2:$E$506,">="&$C$2,Bets!$U$2:$U$506,"L") | E15: =COUNTIFS(Bets!$A$2:$A$506,"<>",Bets!$B$2:$B$506,"*",Bets!$E$2:$E$506,">="&$C$2,Bets!$U$2:$U$506,"Push") | F15: =COUNTIFS(Bets!$A$2:$A$506,"<>",Bets!$B$2:$B$506,"*",Bets!$E$2:$E$506,">="&$C$2,Bets!$U$2:$U$506,"Pending") | G15: =COUNTIFS(Bets!$A$2:$A$506,"<>",Bets!$B$2:$B$506,"*",Bets!$E$2:$E$506,">="&$C$2,Bets!$U$2:$U$506,"Unknown") | H15: =IF(C15+D15=0,"",C15/(C15+D15)) | I15: =SUMIFS(Bets!$Q$2:$Q$506,Bets!$A$2:$A$506,"<>",Bets!$B$2:$B$506,"*",Bets!$E$2:$E$506,">="&$C$2) | J15: =SUMIFS(Bets!$AC$2:$AC$506,Bets!$A$2:$A$506,"<>",Bets!$B$2:$B$506,"*",Bets!$E$2:$E$506,">="&$C$2) | K15: =SUMIFS(Bets!$V$2:$V$506,Bets!$A$2:$A$506,"<>",Bets!$B$2:$B$506,"*",Bets!$E$2:$E$506,">="&$C$2) | L15: =IF(J15=0,"",K15/J15) | M15: =SUMIFS(Bets!$AD$2:$AD$506,Bets!$A$2:$A$506,"<>",Bets!$B$2:$B$506,"*",Bets!$E$2:$E$506,">="&$C$2) | N15: =SUMIFS(Bets!$W$2:$W$506,Bets!$A$2:$A$506,"<>",Bets!$B$2:$B$506,"*",Bets!$E$2:$E$506,">="&$C$2) | O15: =IF(M15=0,"",N15/M15)
A17: Since NFL start (game date ≥ C3)
A18: Bettor | B18: Bets | C18: W | D18: L | E18: Push | F18: Pending | G18: Unknown | H18: Win % (W/(W+L)) | I18: Total staked $ (all $ bets) | J18: Settled staked $ | K18: Net P/L $ | L18: ROI (net / settled $) | M18: Units staked (settled) | N18: Net units | O18: ROI (units)
A19: Trent (@BookitWithTrent) | B19: =COUNTIFS(Bets!$A$2:$A$506,"<>",Bets!$B$2:$B$506,"Trent",Bets!$E$2:$E$506,">="&$C$3) | C19: =COUNTIFS(Bets!$A$2:$A$506,"<>",Bets!$B$2:$B$506,"Trent",Bets!$E$2:$E$506,">="&$C$3,Bets!$U$2:$U$506,"W") | D19: =COUNTIFS(Bets!$A$2:$A$506,"<>",Bets!$B$2:$B$506,"Trent",Bets!$E$2:$E$506,">="&$C$3,Bets!$U$2:$U$506,"L") | E19: =COUNTIFS(Bets!$A$2:$A$506,"<>",Bets!$B$2:$B$506,"Trent",Bets!$E$2:$E$506,">="&$C$3,Bets!$U$2:$U$506,"Push") | F19: =COUNTIFS(Bets!$A$2:$A$506,"<>",Bets!$B$2:$B$506,"Trent",Bets!$E$2:$E$506,">="&$C$3,Bets!$U$2:$U$506,"Pending") | G19: =COUNTIFS(Bets!$A$2:$A$506,"<>",Bets!$B$2:$B$506,"Trent",Bets!$E$2:$E$506,">="&$C$3,Bets!$U$2:$U$506,"Unknown") | H19: =IF(C19+D19=0,"",C19/(C19+D19)) | I19: =SUMIFS(Bets!$Q$2:$Q$506,Bets!$A$2:$A$506,"<>",Bets!$B$2:$B$506,"Trent",Bets!$E$2:$E$506,">="&$C$3) | J19: =SUMIFS(Bets!$AC$2:$AC$506,Bets!$A$2:$A$506,"<>",Bets!$B$2:$B$506,"Trent",Bets!$E$2:$E$506,">="&$C$3) | K19: =SUMIFS(Bets!$V$2:$V$506,Bets!$A$2:$A$506,"<>",Bets!$B$2:$B$506,"Trent",Bets!$E$2:$E$506,">="&$C$3) | L19: =IF(J19=0,"",K19/J19) | M19: =SUMIFS(Bets!$AD$2:$AD$506,Bets!$A$2:$A$506,"<>",Bets!$B$2:$B$506,"Trent",Bets!$E$2:$E$506,">="&$C$3) | N19: =SUMIFS(Bets!$W$2:$W$506,Bets!$A$2:$A$506,"<>",Bets!$B$2:$B$506,"Trent",Bets!$E$2:$E$506,">="&$C$3) | O19: =IF(M19=0,"",N19/M19)
A20: Steve (@stevewilldoit) | B20: =COUNTIFS(Bets!$A$2:$A$506,"<>",Bets!$B$2:$B$506,"Steve",Bets!$E$2:$E$506,">="&$C$3) | C20: =COUNTIFS(Bets!$A$2:$A$506,"<>",Bets!$B$2:$B$506,"Steve",Bets!$E$2:$E$506,">="&$C$3,Bets!$U$2:$U$506,"W") | D20: =COUNTIFS(Bets!$A$2:$A$506,"<>",Bets!$B$2:$B$506,"Steve",Bets!$E$2:$E$506,">="&$C$3,Bets!$U$2:$U$506,"L") | E20: =COUNTIFS(Bets!$A$2:$A$506,"<>",Bets!$B$2:$B$506,"Steve",Bets!$E$2:$E$506,">="&$C$3,Bets!$U$2:$U$506,"Push") | F20: =COUNTIFS(Bets!$A$2:$A$506,"<>",Bets!$B$2:$B$506,"Steve",Bets!$E$2:$E$506,">="&$C$3,Bets!$U$2:$U$506,"Pending") | G20: =COUNTIFS(Bets!$A$2:$A$506,"<>",Bets!$B$2:$B$506,"Steve",Bets!$E$2:$E$506,">="&$C$3,Bets!$U$2:$U$506,"Unknown") | H20: =IF(C20+D20=0,"",C20/(C20+D20)) | I20: =SUMIFS(Bets!$Q$2:$Q$506,Bets!$A$2:$A$506,"<>",Bets!$B$2:$B$506,"Steve",Bets!$E$2:$E$506,">="&$C$3) | J20: =SUMIFS(Bets!$AC$2:$AC$506,Bets!$A$2:$A$506,"<>",Bets!$B$2:$B$506,"Steve",Bets!$E$2:$E$506,">="&$C$3) | K20: =SUMIFS(Bets!$V$2:$V$506,Bets!$A$2:$A$506,"<>",Bets!$B$2:$B$506,"Steve",Bets!$E$2:$E$506,">="&$C$3) | L20: =IF(J20=0,"",K20/J20) | M20: =SUMIFS(Bets!$AD$2:$AD$506,Bets!$A$2:$A$506,"<>",Bets!$B$2:$B$506,"Steve",Bets!$E$2:$E$506,">="&$C$3) | N20: =SUMIFS(Bets!$W$2:$W$506,Bets!$A$2:$A$506,"<>",Bets!$B$2:$B$506,"Steve",Bets!$E$2:$E$506,">="&$C$3) | O20: =IF(M20=0,"",N20/M20)
A21: Combined | B21: =COUNTIFS(Bets!$A$2:$A$506,"<>",Bets!$B$2:$B$506,"*",Bets!$E$2:$E$506,">="&$C$3) | C21: =COUNTIFS(Bets!$A$2:$A$506,"<>",Bets!$B$2:$B$506,"*",Bets!$E$2:$E$506,">="&$C$3,Bets!$U$2:$U$506,"W") | D21: =COUNTIFS(Bets!$A$2:$A$506,"<>",Bets!$B$2:$B$506,"*",Bets!$E$2:$E$506,">="&$C$3,Bets!$U$2:$U$506,"L") | E21: =COUNTIFS(Bets!$A$2:$A$506,"<>",Bets!$B$2:$B$506,"*",Bets!$E$2:$E$506,">="&$C$3,Bets!$U$2:$U$506,"Push") | F21: =COUNTIFS(Bets!$A$2:$A$506,"<>",Bets!$B$2:$B$506,"*",Bets!$E$2:$E$506,">="&$C$3,Bets!$U$2:$U$506,"Pending") | G21: =COUNTIFS(Bets!$A$2:$A$506,"<>",Bets!$B$2:$B$506,"*",Bets!$E$2:$E$506,">="&$C$3,Bets!$U$2:$U$506,"Unknown") | H21: =IF(C21+D21=0,"",C21/(C21+D21)) | I21: =SUMIFS(Bets!$Q$2:$Q$506,Bets!$A$2:$A$506,"<>",Bets!$B$2:$B$506,"*",Bets!$E$2:$E$506,">="&$C$3) | J21: =SUMIFS(Bets!$AC$2:$AC$506,Bets!$A$2:$A$506,"<>",Bets!$B$2:$B$506,"*",Bets!$E$2:$E$506,">="&$C$3) | K21: =SUMIFS(Bets!$V$2:$V$506,Bets!$A$2:$A$506,"<>",Bets!$B$2:$B$506,"*",Bets!$E$2:$E$506,">="&$C$3) | L21: =IF(J21=0,"",K21/J21) | M21: =SUMIFS(Bets!$AD$2:$AD$506,Bets!$A$2:$A$506,"<>",Bets!$B$2:$B$506,"*",Bets!$E$2:$E$506,">="&$C$3) | N21: =SUMIFS(Bets!$W$2:$W$506,Bets!$A$2:$A$506,"<>",Bets!$B$2:$B$506,"*",Bets!$E$2:$E$506,">="&$C$3) | O21: =IF(M21=0,"",N21/M21)
A23: Football only (NFL + CFB), all dates
A24: Bettor | B24: Bets | C24: W | D24: L | E24: Push | F24: Pending | G24: Unknown | H24: Win % (W/(W+L)) | I24: Total staked $ (all $ bets) | J24: Settled staked $ | K24: Net P/L $ | L24: ROI (net / settled $) | M24: Units staked (settled) | N24: Net units | O24: ROI (units)
A25: Trent (@BookitWithTrent) | B25: =COUNTIFS(Bets!$A$2:$A$506,"<>",Bets!$B$2:$B$506,"Trent",Bets!$J$2:$J$506,"NFL") | C25: =COUNTIFS(Bets!$A$2:$A$506,"<>",Bets!$B$2:$B$506,"Trent",Bets!$J$2:$J$506,"NFL",Bets!$U$2:$U$506,"W") | D25: =COUNTIFS(Bets!$A$2:$A$506,"<>",Bets!$B$2:$B$506,"Trent",Bets!$J$2:$J$506,"NFL",Bets!$U$2:$U$506,"L") | E25: =COUNTIFS(Bets!$A$2:$A$506,"<>",Bets!$B$2:$B$506,"Trent",Bets!$J$2:$J$506,"NFL",Bets!$U$2:$U$506,"Push") | F25: =COUNTIFS(Bets!$A$2:$A$506,"<>",Bets!$B$2:$B$506,"Trent",Bets!$J$2:$J$506,"NFL",Bets!$U$2:$U$506,"Pending") | G25: =COUNTIFS(Bets!$A$2:$A$506,"<>",Bets!$B$2:$B$506,"Trent",Bets!$J$2:$J$506,"NFL",Bets!$U$2:$U$506,"Unknown") | H25: =IF(C25+D25=0,"",C25/(C25+D25)) | I25: =SUMIFS(Bets!$Q$2:$Q$506,Bets!$A$2:$A$506,"<>",Bets!$B$2:$B$506,"Trent",Bets!$J$2:$J$506,"NFL") | J25: =SUMIFS(Bets!$AC$2:$AC$506,Bets!$A$2:$A$506,"<>",Bets!$B$2:$B$506,"Trent",Bets!$J$2:$J$506,"NFL") | K25: =SUMIFS(Bets!$V$2:$V$506,Bets!$A$2:$A$506,"<>",Bets!$B$2:$B$506,"Trent",Bets!$J$2:$J$506,"NFL") | L25: =IF(J25=0,"",K25/J25) | M25: =SUMIFS(Bets!$AD$2:$AD$506,Bets!$A$2:$A$506,"<>",Bets!$B$2:$B$506,"Trent",Bets!$J$2:$J$506,"NFL") | N25: =SUMIFS(Bets!$W$2:$W$506,Bets!$A$2:$A$506,"<>",Bets!$B$2:$B$506,"Trent",Bets!$J$2:$J$506,"NFL") | O25: =IF(M25=0,"",N25/M25)
A26: Steve (@stevewilldoit) | B26: =COUNTIFS(Bets!$A$2:$A$506,"<>",Bets!$B$2:$B$506,"Steve",Bets!$J$2:$J$506,"NFL") | C26: =COUNTIFS(Bets!$A$2:$A$506,"<>",Bets!$B$2:$B$506,"Steve",Bets!$J$2:$J$506,"NFL",Bets!$U$2:$U$506,"W") | D26: =COUNTIFS(Bets!$A$2:$A$506,"<>",Bets!$B$2:$B$506,"Steve",Bets!$J$2:$J$506,"NFL",Bets!$U$2:$U$506,"L") | E26: =COUNTIFS(Bets!$A$2:$A$506,"<>",Bets!$B$2:$B$506,"Steve",Bets!$J$2:$J$506,"NFL",Bets!$U$2:$U$506,"Push") | F26: =COUNTIFS(Bets!$A$2:$A$506,"<>",Bets!$B$2:$B$506,"Steve",Bets!$J$2:$J$506,"NFL",Bets!$U$2:$U$506,"Pending") | G26: =COUNTIFS(Bets!$A$2:$A$506,"<>",Bets!$B$2:$B$506,"Steve",Bets!$J$2:$J$506,"NFL",Bets!$U$2:$U$506,"Unknown") | H26: =IF(C26+D26=0,"",C26/(C26+D26)) | I26: =SUMIFS(Bets!$Q$2:$Q$506,Bets!$A$2:$A$506,"<>",Bets!$B$2:$B$506,"Steve",Bets!$J$2:$J$506,"NFL") | J26: =SUMIFS(Bets!$AC$2:$AC$506,Bets!$A$2:$A$506,"<>",Bets!$B$2:$B$506,"Steve",Bets!$J$2:$J$506,"NFL") | K26: =SUMIFS(Bets!$V$2:$V$506,Bets!$A$2:$A$506,"<>",Bets!$B$2:$B$506,"Steve",Bets!$J$2:$J$506,"NFL") | L26: =IF(J26=0,"",K26/J26) | M26: =SUMIFS(Bets!$AD$2:$AD$506,Bets!$A$2:$A$506,"<>",Bets!$B$2:$B$506,"Steve",Bets!$J$2:$J$506,"NFL") | N26: =SUMIFS(Bets!$W$2:$W$506,Bets!$A$2:$A$506,"<>",Bets!$B$2:$B$506,"Steve",Bets!$J$2:$J$506,"NFL") | O26: =IF(M26=0,"",N26/M26)
A27: Combined | B27: =COUNTIFS(Bets!$A$2:$A$506,"<>",Bets!$B$2:$B$506,"*",Bets!$J$2:$J$506,"NFL") | C27: =COUNTIFS(Bets!$A$2:$A$506,"<>",Bets!$B$2:$B$506,"*",Bets!$J$2:$J$506,"NFL",Bets!$U$2:$U$506,"W") | D27: =COUNTIFS(Bets!$A$2:$A$506,"<>",Bets!$B$2:$B$506,"*",Bets!$J$2:$J$506,"NFL",Bets!$U$2:$U$506,"L") | E27: =COUNTIFS(Bets!$A$2:$A$506,"<>",Bets!$B$2:$B$506,"*",Bets!$J$2:$J$506,"NFL",Bets!$U$2:$U$506,"Push") | F27: =COUNTIFS(Bets!$A$2:$A$506,"<>",Bets!$B$2:$B$506,"*",Bets!$J$2:$J$506,"NFL",Bets!$U$2:$U$506,"Pending") | G27: =COUNTIFS(Bets!$A$2:$A$506,"<>",Bets!$B$2:$B$506,"*",Bets!$J$2:$J$506,"NFL",Bets!$U$2:$U$506,"Unknown") | H27: =IF(C27+D27=0,"",C27/(C27+D27)) | I27: =SUMIFS(Bets!$Q$2:$Q$506,Bets!$A$2:$A$506,"<>",Bets!$B$2:$B$506,"*",Bets!$J$2:$J$506,"NFL") | J27: =SUMIFS(Bets!$AC$2:$AC$506,Bets!$A$2:$A$506,"<>",Bets!$B$2:$B$506,"*",Bets!$J$2:$J$506,"NFL") | K27: =SUMIFS(Bets!$V$2:$V$506,Bets!$A$2:$A$506,"<>",Bets!$B$2:$B$506,"*",Bets!$J$2:$J$506,"NFL") | L27: =IF(J27=0,"",K27/J27) | M27: =SUMIFS(Bets!$AD$2:$AD$506,Bets!$A$2:$A$506,"<>",Bets!$B$2:$B$506,"*",Bets!$J$2:$J$506,"NFL") | N27: =SUMIFS(Bets!$W$2:$W$506,Bets!$A$2:$A$506,"<>",Bets!$B$2:$B$506,"*",Bets!$J$2:$J$506,"NFL") | O27: =IF(M27=0,"",N27/M27)
A28: Trent (@BookitWithTrent) – CFB | B28: =COUNTIFS(Bets!$A$2:$A$506,"<>",Bets!$B$2:$B$506,"Trent",Bets!$J$2:$J$506,"CFB") | C28: =COUNTIFS(Bets!$A$2:$A$506,"<>",Bets!$B$2:$B$506,"Trent",Bets!$J$2:$J$506,"CFB",Bets!$U$2:$U$506,"W") | D28: =COUNTIFS(Bets!$A$2:$A$506,"<>",Bets!$B$2:$B$506,"Trent",Bets!$J$2:$J$506,"CFB",Bets!$U$2:$U$506,"L") | E28: =COUNTIFS(Bets!$A$2:$A$506,"<>",Bets!$B$2:$B$506,"Trent",Bets!$J$2:$J$506,"CFB",Bets!$U$2:$U$506,"Push") | F28: =COUNTIFS(Bets!$A$2:$A$506,"<>",Bets!$B$2:$B$506,"Trent",Bets!$J$2:$J$506,"CFB",Bets!$U$2:$U$506,"Pending") | G28: =COUNTIFS(Bets!$A$2:$A$506,"<>",Bets!$B$2:$B$506,"Trent",Bets!$J$2:$J$506,"CFB",Bets!$U$2:$U$506,"Unknown") | H28: =IF(C28+D28=0,"",C28/(C28+D28)) | I28: =SUMIFS(Bets!$Q$2:$Q$506,Bets!$A$2:$A$506,"<>",Bets!$B$2:$B$506,"Trent",Bets!$J$2:$J$506,"CFB") | J28: =SUMIFS(Bets!$AC$2:$AC$506,Bets!$A$2:$A$506,"<>",Bets!$B$2:$B$506,"Trent",Bets!$J$2:$J$506,"CFB") | K28: =SUMIFS(Bets!$V$2:$V$506,Bets!$A$2:$A$506,"<>",Bets!$B$2:$B$506,"Trent",Bets!$J$2:$J$506,"CFB") | L28: =IF(J28=0,"",K28/J28) | M28: =SUMIFS(Bets!$AD$2:$AD$506,Bets!$A$2:$A$506,"<>",Bets!$B$2:$B$506,"Trent",Bets!$J$2:$J$506,"CFB") | N28: =SUMIFS(Bets!$W$2:$W$506,Bets!$A$2:$A$506,"<>",Bets!$B$2:$B$506,"Trent",Bets!$J$2:$J$506,"CFB") | O28: =IF(M28=0,"",N28/M28)
A29: Steve (@stevewilldoit) – CFB | B29: =COUNTIFS(Bets!$A$2:$A$506,"<>",Bets!$B$2:$B$506,"Steve",Bets!$J$2:$J$506,"CFB") | C29: =COUNTIFS(Bets!$A$2:$A$506,"<>",Bets!$B$2:$B$506,"Steve",Bets!$J$2:$J$506,"CFB",Bets!$U$2:$U$506,"W") | D29: =COUNTIFS(Bets!$A$2:$A$506,"<>",Bets!$B$2:$B$506,"Steve",Bets!$J$2:$J$506,"CFB",Bets!$U$2:$U$506,"L") | E29: =COUNTIFS(Bets!$A$2:$A$506,"<>",Bets!$B$2:$B$506,"Steve",Bets!$J$2:$J$506,"CFB",Bets!$U$2:$U$506,"Push") | F29: =COUNTIFS(Bets!$A$2:$A$506,"<>",Bets!$B$2:$B$506,"Steve",Bets!$J$2:$J$506,"CFB",Bets!$U$2:$U$506,"Pending") | G29: =COUNTIFS(Bets!$A$2:$A$506,"<>",Bets!$B$2:$B$506,"Steve",Bets!$J$2:$J$506,"CFB",Bets!$U$2:$U$506,"Unknown") | H29: =IF(C29+D29=0,"",C29/(C29+D29)) | I29: =SUMIFS(Bets!$Q$2:$Q$506,Bets!$A$2:$A$506,"<>",Bets!$B$2:$B$506,"Steve",Bets!$J$2:$J$506,"CFB") | J29: =SUMIFS(Bets!$AC$2:$AC$506,Bets!$A$2:$A$506,"<>",Bets!$B$2:$B$506,"Steve",Bets!$J$2:$J$506,"CFB") | K29: =SUMIFS(Bets!$V$2:$V$506,Bets!$A$2:$A$506,"<>",Bets!$B$2:$B$506,"Steve",Bets!$J$2:$J$506,"CFB") | L29: =IF(J29=0,"",K29/J29) | M29: =SUMIFS(Bets!$AD$2:$AD$506,Bets!$A$2:$A$506,"<>",Bets!$B$2:$B$506,"Steve",Bets!$J$2:$J$506,"CFB") | N29: =SUMIFS(Bets!$W$2:$W$506,Bets!$A$2:$A$506,"<>",Bets!$B$2:$B$506,"Steve",Bets!$J$2:$J$506,"CFB") | O29: =IF(M29=0,"",N29/M29)
A30: Combined – CFB | B30: =COUNTIFS(Bets!$A$2:$A$506,"<>",Bets!$B$2:$B$506,"*",Bets!$J$2:$J$506,"CFB") | C30: =COUNTIFS(Bets!$A$2:$A$506,"<>",Bets!$B$2:$B$506,"*",Bets!$J$2:$J$506,"CFB",Bets!$U$2:$U$506,"W") | D30: =COUNTIFS(Bets!$A$2:$A$506,"<>",Bets!$B$2:$B$506,"*",Bets!$J$2:$J$506,"CFB",Bets!$U$2:$U$506,"L") | E30: =COUNTIFS(Bets!$A$2:$A$506,"<>",Bets!$B$2:$B$506,"*",Bets!$J$2:$J$506,"CFB",Bets!$U$2:$U$506,"Push") | F30: =COUNTIFS(Bets!$A$2:$A$506,"<>",Bets!$B$2:$B$506,"*",Bets!$J$2:$J$506,"CFB",Bets!$U$2:$U$506,"Pending") | G30: =COUNTIFS(Bets!$A$2:$A$506,"<>",Bets!$B$2:$B$506,"*",Bets!$J$2:$J$506,"CFB",Bets!$U$2:$U$506,"Unknown") | H30: =IF(C30+D30=0,"",C30/(C30+D30)) | I30: =SUMIFS(Bets!$Q$2:$Q$506,Bets!$A$2:$A$506,"<>",Bets!$B$2:$B$506,"*",Bets!$J$2:$J$506,"CFB") | J30: =SUMIFS(Bets!$AC$2:$AC$506,Bets!$A$2:$A$506,"<>",Bets!$B$2:$B$506,"*",Bets!$J$2:$J$506,"CFB") | K30: =SUMIFS(Bets!$V$2:$V$506,Bets!$A$2:$A$506,"<>",Bets!$B$2:$B$506,"*",Bets!$J$2:$J$506,"CFB") | L30: =IF(J30=0,"",K30/J30) | M30: =SUMIFS(Bets!$AD$2:$AD$506,Bets!$A$2:$A$506,"<>",Bets!$B$2:$B$506,"*",Bets!$J$2:$J$506,"CFB") | N30: =SUMIFS(Bets!$W$2:$W$506,Bets!$A$2:$A$506,"<>",Bets!$B$2:$B$506,"*",Bets!$J$2:$J$506,"CFB") | O30: =IF(M30=0,"",N30/M30)

Sheet By Sport
A1: Record / staked / P&L / ROI by sport category
A3: Trent (@BookitWithTrent)
A4: Bettor | B4: Sport | C4: Bets | D4: W | E4: L | F4: Push | G4: Pending | H4: Unknown | I4: Win % (W/(W+L)) | J4: Total staked $ (all $ bets) | K4: Settled staked $ | L4: Net P/L $ | M4: ROI (net / settled $) | N4: Units staked (settled) | O4: Net units | P4: ROI (units)
A5: Trent (@BookitWithTrent) | B5: CFB | C5: =COUNTIFS(Bets!$A$2:$A$506,"<>",Bets!$B$2:$B$506,"Trent",Bets!$J$2:$J$506,"CFB") | D5: =COUNTIFS(Bets!$A$2:$A$506,"<>",Bets!$B$2:$B$506,"Trent",Bets!$J$2:$J$506,"CFB",Bets!$U$2:$U$506,"W") | E5: =COUNTIFS(Bets!$A$2:$A$506,"<>",Bets!$B$2:$B$506,"Trent",Bets!$J$2:$J$506,"CFB",Bets!$U$2:$U$506,"L") | F5: =COUNTIFS(Bets!$A$2:$A$506,"<>",Bets!$B$2:$B$506,"Trent",Bets!$J$2:$J$506,"CFB",Bets!$U$2:$U$506,"Push") | G5: =COUNTIFS(Bets!$A$2:$A$506,"<>",Bets!$B$2:$B$506,"Trent",Bets!$J$2:$J$506,"CFB",Bets!$U$2:$U$506,"Pending") | H5: =COUNTIFS(Bets!$A$2:$A$506,"<>",Bets!$B$2:$B$506,"Trent",Bets!$J$2:$J$506,"CFB",Bets!$U$2:$U$506,"Unknown") | I5: =IF(D5+E5=0,"",D5/(D5+E5)) | J5: =SUMIFS(Bets!$Q$2:$Q$506,Bets!$A$2:$A$506,"<>",Bets!$B$2:$B$506,"Trent",Bets!$J$2:$J$506,"CFB") | K5: =SUMIFS(Bets!$AC$2:$AC$506,Bets!$A$2:$A$506,"<>",Bets!$B$2:$B$506,"Trent",Bets!$J$2:$J$506,"CFB") | L5: =SUMIFS(Bets!$V$2:$V$506,Bets!$A$2:$A$506,"<>",Bets!$B$2:$B$506,"Trent",Bets!$J$2:$J$506,"CFB") | M5: =IF(K5=0,"",L5/K5) | N5: =SUMIFS(Bets!$AD$2:$AD$506,Bets!$A$2:$A$506,"<>",Bets!$B$2:$B$506,"Trent",Bets!$J$2:$J$506,"CFB") | O5: =SUMIFS(Bets!$W$2:$W$506,Bets!$A$2:$A$506,"<>",Bets!$B$2:$B$506,"Trent",Bets!$J$2:$J$506,"CFB") | P5: =IF(N5=0,"",O5/N5)
A6: Trent (@BookitWithTrent) | B6: MLB | C6: =COUNTIFS(Bets!$A$2:$A$506,"<>",Bets!$B$2:$B$506,"Trent",Bets!$J$2:$J$506,"MLB") | D6: =COUNTIFS(Bets!$A$2:$A$506,"<>",Bets!$B$2:$B$506,"Trent",Bets!$J$2:$J$506,"MLB",Bets!$U$2:$U$506,"W") | E6: =COUNTIFS(Bets!$A$2:$A$506,"<>",Bets!$B$2:$B$506,"Trent",Bets!$J$2:$J$506,"MLB",Bets!$U$2:$U$506,"L") | F6: =COUNTIFS(Bets!$A$2:$A$506,"<>",Bets!$B$2:$B$506,"Trent",Bets!$J$2:$J$506,"MLB",Bets!$U$2:$U$506,"Push") | G6: =COUNTIFS(Bets!$A$2:$A$506,"<>",Bets!$B$2:$B$506,"Trent",Bets!$J$2:$J$506,"MLB",Bets!$U$2:$U$506,"Pending") | H6: =COUNTIFS(Bets!$A$2:$A$506,"<>",Bets!$B$2:$B$506,"Trent",Bets!$J$2:$J$506,"MLB",Bets!$U$2:$U$506,"Unknown") | I6: =IF(D6+E6=0,"",D6/(D6+E6)) | J6: =SUMIFS(Bets!$Q$2:$Q$506,Bets!$A$2:$A$506,"<>",Bets!$B$2:$B$506,"Trent",Bets!$J$2:$J$506,"MLB") | K6: =SUMIFS(Bets!$AC$2:$AC$506,Bets!$A$2:$A$506,"<>",Bets!$B$2:$B$506,"Trent",Bets!$J$2:$J$506,"MLB") | L6: =SUMIFS(Bets!$V$2:$V$506,Bets!$A$2:$A$506,"<>",Bets!$B$2:$B$506,"Trent",Bets!$J$2:$J$506,"MLB") | M6: =IF(K6=0,"",L6/K6) | N6: =SUMIFS(Bets!$AD$2:$AD$506,Bets!$A$2:$A$506,"<>",Bets!$B$2:$B$506,"Trent",Bets!$J$2:$J$506,"MLB") | O6: =SUMIFS(Bets!$W$2:$W$506,Bets!$A$2:$A$506,"<>",Bets!$B$2:$B$506,"Trent",Bets!$J$2:$J$506,"MLB") | P6: =IF(N6=0,"",O6/N6)
A7: Trent (@BookitWithTrent) | B7: NFL | C7: =COUNTIFS(Bets!$A$2:$A$506,"<>",Bets!$B$2:$B$506,"Trent",Bets!$J$2:$J$506,"NFL") | D7: =COUNTIFS(Bets!$A$2:$A$506,"<>",Bets!$B$2:$B$506,"Trent",Bets!$J$2:$J$506,"NFL",Bets!$U$2:$U$506,"W") | E7: =COUNTIFS(Bets!$A$2:$A$506,"<>",Bets!$B$2:$B$506,"Trent",Bets!$J$2:$J$506,"NFL",Bets!$U$2:$U$506,"L") | F7: =COUNTIFS(Bets!$A$2:$A$506,"<>",Bets!$B$2:$B$506,"Trent",Bets!$J$2:$J$506,"NFL",Bets!$U$2:$U$506,"Push") | G7: =COUNTIFS(Bets!$A$2:$A$506,"<>",Bets!$B$2:$B$506,"Trent",Bets!$J$2:$J$506,"NFL",Bets!$U$2:$U$506,"Pending") | H7: =COUNTIFS(Bets!$A$2:$A$506,"<>",Bets!$B$2:$B$506,"Trent",Bets!$J$2:$J$506,"NFL",Bets!$U$2:$U$506,"Unknown") | I7: =IF(D7+E7=0,"",D7/(D7+E7)) | J7: =SUMIFS(Bets!$Q$2:$Q$506,Bets!$A$2:$A$506,"<>",Bets!$B$2:$B$506,"Trent",Bets!$J$2:$J$506,"NFL") | K7: =SUMIFS(Bets!$AC$2:$AC$506,Bets!$A$2:$A$506,"<>",Bets!$B$2:$B$506,"Trent",Bets!$J$2:$J$506,"NFL") | L7: =SUMIFS(Bets!$V$2:$V$506,Bets!$A$2:$A$506,"<>",Bets!$B$2:$B$506,"Trent",Bets!$J$2:$J$506,"NFL") | M7: =IF(K7=0,"",L7/K7) | N7: =SUMIFS(Bets!$AD$2:$AD$506,Bets!$A$2:$A$506,"<>",Bets!$B$2:$B$506,"Trent",Bets!$J$2:$J$506,"NFL") | O7: =SUMIFS(Bets!$W$2:$W$506,Bets!$A$2:$A$506,"<>",Bets!$B$2:$B$506,"Trent",Bets!$J$2:$J$506,"NFL") | P7: =IF(N7=0,"",O7/N7)
A8: Trent (@BookitWithTrent) | B8: Other | C8: =COUNTIFS(Bets!$A$2:$A$506,"<>",Bets!$B$2:$B$506,"Trent",Bets!$J$2:$J$506,"Other") | D8: =COUNTIFS(Bets!$A$2:$A$506,"<>",Bets!$B$2:$B$506,"Trent",Bets!$J$2:$J$506,"Other",Bets!$U$2:$U$506,"W") | E8: =COUNTIFS(Bets!$A$2:$A$506,"<>",Bets!$B$2:$B$506,"Trent",Bets!$J$2:$J$506,"Other",Bets!$U$2:$U$506,"L") | F8: =COUNTIFS(Bets!$A$2:$A$506,"<>",Bets!$B$2:$B$506,"Trent",Bets!$J$2:$J$506,"Other",Bets!$U$2:$U$506,"Push") | G8: =COUNTIFS(Bets!$A$2:$A$506,"<>",Bets!$B$2:$B$506,"Trent",Bets!$J$2:$J$506,"Other",Bets!$U$2:$U$506,"Pending") | H8: =COUNTIFS(Bets!$A$2:$A$506,"<>",Bets!$B$2:$B$506,"Trent",Bets!$J$2:$J$506,"Other",Bets!$U$2:$U$506,"Unknown") | I8: =IF(D8+E8=0,"",D8/(D8+E8)) | J8: =SUMIFS(Bets!$Q$2:$Q$506,Bets!$A$2:$A$506,"<>",Bets!$B$2:$B$506,"Trent",Bets!$J$2:$J$506,"Other") | K8: =SUMIFS(Bets!$AC$2:$AC$506,Bets!$A$2:$A$506,"<>",Bets!$B$2:$B$506,"Trent",Bets!$J$2:$J$506,"Other") | L8: =SUMIFS(Bets!$V$2:$V$506,Bets!$A$2:$A$506,"<>",Bets!$B$2:$B$506,"Trent",Bets!$J$2:$J$506,"Other") | M8: =IF(K8=0,"",L8/K8) | N8: =SUMIFS(Bets!$AD$2:$AD$506,Bets!$A$2:$A$506,"<>",Bets!$B$2:$B$506,"Trent",Bets!$J$2:$J$506,"Other") | O8: =SUMIFS(Bets!$W$2:$W$506,Bets!$A$2:$A$506,"<>",Bets!$B$2:$B$506,"Trent",Bets!$J$2:$J$506,"Other") | P8: =IF(N8=0,"",O8/N8)
A9: Trent (@BookitWithTrent) | B9: Soccer | C9: =COUNTIFS(Bets!$A$2:$A$506,"<>",Bets!$B$2:$B$506,"Trent",Bets!$J$2:$J$506,"Soccer") | D9: =COUNTIFS(Bets!$A$2:$A$506,"<>",Bets!$B$2:$B$506,"Trent",Bets!$J$2:$J$506,"Soccer",Bets!$U$2:$U$506,"W") | E9: =COUNTIFS(Bets!$A$2:$A$506,"<>",Bets!$B$2:$B$506,"Trent",Bets!$J$2:$J$506,"Soccer",Bets!$U$2:$U$506,"L") | F9: =COUNTIFS(Bets!$A$2:$A$506,"<>",Bets!$B$2:$B$506,"Trent",Bets!$J$2:$J$506,"Soccer",Bets!$U$2:$U$506,"Push") | G9: =COUNTIFS(Bets!$A$2:$A$506,"<>",Bets!$B$2:$B$506,"Trent",Bets!$J$2:$J$506,"Soccer",Bets!$U$2:$U$506,"Pending") | H9: =COUNTIFS(Bets!$A$2:$A$506,"<>",Bets!$B$2:$B$506,"Trent",Bets!$J$2:$J$506,"Soccer",Bets!$U$2:$U$506,"Unknown") | I9: =IF(D9+E9=0,"",D9/(D9+E9)) | J9: =SUMIFS(Bets!$Q$2:$Q$506,Bets!$A$2:$A$506,"<>",Bets!$B$2:$B$506,"Trent",Bets!$J$2:$J$506,"Soccer") | K9: =SUMIFS(Bets!$AC$2:$AC$506,Bets!$A$2:$A$506,"<>",Bets!$B$2:$B$506,"Trent",Bets!$J$2:$J$506,"Soccer") | L9: =SUMIFS(Bets!$V$2:$V$506,Bets!$A$2:$A$506,"<>",Bets!$B$2:$B$506,"Trent",Bets!$J$2:$J$506,"Soccer") | M9: =IF(K9=0,"",L9/K9) | N9: =SUMIFS(Bets!$AD$2:$AD$506,Bets!$A$2:$A$506,"<>",Bets!$B$2:$B$506,"Trent",Bets!$J$2:$J$506,"Soccer") | O9: =SUMIFS(Bets!$W$2:$W$506,Bets!$A$2:$A$506,"<>",Bets!$B$2:$B$506,"Trent",Bets!$J$2:$J$506,"Soccer") | P9: =IF(N9=0,"",O9/N9)
A10: Trent (@BookitWithTrent) | B10: Tennis | C10: =COUNTIFS(Bets!$A$2:$A$506,"<>",Bets!$B$2:$B$506,"Trent",Bets!$J$2:$J$506,"Tennis") | D10: =COUNTIFS(Bets!$A$2:$A$506,"<>",Bets!$B$2:$B$506,"Trent",Bets!$J$2:$J$506,"Tennis",Bets!$U$2:$U$506,"W") | E10: =COUNTIFS(Bets!$A$2:$A$506,"<>",Bets!$B$2:$B$506,"Trent",Bets!$J$2:$J$506,"Tennis",Bets!$U$2:$U$506,"L") | F10: =COUNTIFS(Bets!$A$2:$A$506,"<>",Bets!$B$2:$B$506,"Trent",Bets!$J$2:$J$506,"Tennis",Bets!$U$2:$U$506,"Push") | G10: =COUNTIFS(Bets!$A$2:$A$506,"<>",Bets!$B$2:$B$506,"Trent",Bets!$J$2:$J$506,"Tennis",Bets!$U$2:$U$506,"Pending") | H10: =COUNTIFS(Bets!$A$2:$A$506,"<>",Bets!$B$2:$B$506,"Trent",Bets!$J$2:$J$506,"Tennis",Bets!$U$2:$U$506,"Unknown") | I10: =IF(D10+E10=0,"",D10/(D10+E10)) | J10: =SUMIFS(Bets!$Q$2:$Q$506,Bets!$A$2:$A$506,"<>",Bets!$B$2:$B$506,"Trent",Bets!$J$2:$J$506,"Tennis") | K10: =SUMIFS(Bets!$AC$2:$AC$506,Bets!$A$2:$A$506,"<>",Bets!$B$2:$B$506,"Trent",Bets!$J$2:$J$506,"Tennis") | L10: =SUMIFS(Bets!$V$2:$V$506,Bets!$A$2:$A$506,"<>",Bets!$B$2:$B$506,"Trent",Bets!$J$2:$J$506,"Tennis") | M10: =IF(K10=0,"",L10/K10) | N10: =SUMIFS(Bets!$AD$2:$AD$506,Bets!$A$2:$A$506,"<>",Bets!$B$2:$B$506,"Trent",Bets!$J$2:$J$506,"Tennis") | O10: =SUMIFS(Bets!$W$2:$W$506,Bets!$A$2:$A$506,"<>",Bets!$B$2:$B$506,"Trent",Bets!$J$2:$J$506,"Tennis") | P10: =IF(N10=0,"",O10/N10)
A11: Trent (@BookitWithTrent) | B11: UFC/MMA | C11: =COUNTIFS(Bets!$A$2:$A$506,"<>",Bets!$B$2:$B$506,"Trent",Bets!$J$2:$J$506,"UFC/MMA") | D11: =COUNTIFS(Bets!$A$2:$A$506,"<>",Bets!$B$2:$B$506,"Trent",Bets!$J$2:$J$506,"UFC/MMA",Bets!$U$2:$U$506,"W") | E11: =COUNTIFS(Bets!$A$2:$A$506,"<>",Bets!$B$2:$B$506,"Trent",Bets!$J$2:$J$506,"UFC/MMA",Bets!$U$2:$U$506,"L") | F11: =COUNTIFS(Bets!$A$2:$A$506,"<>",Bets!$B$2:$B$506,"Trent",Bets!$J$2:$J$506,"UFC/MMA",Bets!$U$2:$U$506,"Push") | G11: =COUNTIFS(Bets!$A$2:$A$506,"<>",Bets!$B$2:$B$506,"Trent",Bets!$J$2:$J$506,"UFC/MMA",Bets!$U$2:$U$506,"Pending") | H11: =COUNTIFS(Bets!$A$2:$A$506,"<>",Bets!$B$2:$B$506,"Trent",Bets!$J$2:$J$506,"UFC/MMA",Bets!$U$2:$U$506,"Unknown") | I11: =IF(D11+E11=0,"",D11/(D11+E11)) | J11: =SUMIFS(Bets!$Q$2:$Q$506,Bets!$A$2:$A$506,"<>",Bets!$B$2:$B$506,"Trent",Bets!$J$2:$J$506,"UFC/MMA") | K11: =SUMIFS(Bets!$AC$2:$AC$506,Bets!$A$2:$A$506,"<>",Bets!$B$2:$B$506,"Trent",Bets!$J$2:$J$506,"UFC/MMA") | L11: =SUMIFS(Bets!$V$2:$V$506,Bets!$A$2:$A$506,"<>",Bets!$B$2:$B$506,"Trent",Bets!$J$2:$J$506,"UFC/MMA") | M11: =IF(K11=0,"",L11/K11) | N11: =SUMIFS(Bets!$AD$2:$AD$506,Bets!$A$2:$A$506,"<>",Bets!$B$2:$B$506,"Trent",Bets!$J$2:$J$506,"UFC/MMA") | O11: =SUMIFS(Bets!$W$2:$W$506,Bets!$A$2:$A$506,"<>",Bets!$B$2:$B$506,"Trent",Bets!$J$2:$J$506,"UFC/MMA") | P11: =IF(N11=0,"",O11/N11)
A13: Steve (@stevewilldoit)
A14: Bettor | B14: Sport | C14: Bets | D14: W | E14: L | F14: Push | G14: Pending | H14: Unknown | I14: Win % (W/(W+L)) | J14: Total staked $ (all $ bets) | K14: Settled staked $ | L14: Net P/L $ | M14: ROI (net / settled $) | N14: Units staked (settled) | O14: Net units | P14: ROI (units)
A15: Steve (@stevewilldoit) | B15: CFB | C15: =COUNTIFS(Bets!$A$2:$A$506,"<>",Bets!$B$2:$B$506,"Steve",Bets!$J$2:$J$506,"CFB") | D15: =COUNTIFS(Bets!$A$2:$A$506,"<>",Bets!$B$2:$B$506,"Steve",Bets!$J$2:$J$506,"CFB",Bets!$U$2:$U$506,"W") | E15: =COUNTIFS(Bets!$A$2:$A$506,"<>",Bets!$B$2:$B$506,"Steve",Bets!$J$2:$J$506,"CFB",Bets!$U$2:$U$506,"L") | F15: =COUNTIFS(Bets!$A$2:$A$506,"<>",Bets!$B$2:$B$506,"Steve",Bets!$J$2:$J$506,"CFB",Bets!$U$2:$U$506,"Push") | G15: =COUNTIFS(Bets!$A$2:$A$506,"<>",Bets!$B$2:$B$506,"Steve",Bets!$J$2:$J$506,"CFB",Bets!$U$2:$U$506,"Pending") | H15: =COUNTIFS(Bets!$A$2:$A$506,"<>",Bets!$B$2:$B$506,"Steve",Bets!$J$2:$J$506,"CFB",Bets!$U$2:$U$506,"Unknown") | I15: =IF(D15+E15=0,"",D15/(D15+E15)) | J15: =SUMIFS(Bets!$Q$2:$Q$506,Bets!$A$2:$A$506,"<>",Bets!$B$2:$B$506,"Steve",Bets!$J$2:$J$506,"CFB") | K15: =SUMIFS(Bets!$AC$2:$AC$506,Bets!$A$2:$A$506,"<>",Bets!$B$2:$B$506,"Steve",Bets!$J$2:$J$506,"CFB") | L15: =SUMIFS(Bets!$V$2:$V$506,Bets!$A$2:$A$506,"<>",Bets!$B$2:$B$506,"Steve",Bets!$J$2:$J$506,"CFB") | M15: =IF(K15=0,"",L15/K15) | N15: =SUMIFS(Bets!$AD$2:$AD$506,Bets!$A$2:$A$506,"<>",Bets!$B$2:$B$506,"Steve",Bets!$J$2:$J$506,"CFB") | O15: =SUMIFS(Bets!$W$2:$W$506,Bets!$A$2:$A$506,"<>",Bets!$B$2:$B$506,"Steve",Bets!$J$2:$J$506,"CFB") | P15: =IF(N15=0,"",O15/N15)
A16: Steve (@stevewilldoit) | B16: MLB | C16: =COUNTIFS(Bets!$A$2:$A$506,"<>",Bets!$B$2:$B$506,"Steve",Bets!$J$2:$J$506,"MLB") | D16: =COUNTIFS(Bets!$A$2:$A$506,"<>",Bets!$B$2:$B$506,"Steve",Bets!$J$2:$J$506,"MLB",Bets!$U$2:$U$506,"W") | E16: =COUNTIFS(Bets!$A$2:$A$506,"<>",Bets!$B$2:$B$506,"Steve",Bets!$J$2:$J$506,"MLB",Bets!$U$2:$U$506,"L") | F16: =COUNTIFS(Bets!$A$2:$A$506,"<>",Bets!$B$2:$B$506,"Steve",Bets!$J$2:$J$506,"MLB",Bets!$U$2:$U$506,"Push") | G16: =COUNTIFS(Bets!$A$2:$A$506,"<>",Bets!$B$2:$B$506,"Steve",Bets!$J$2:$J$506,"MLB",Bets!$U$2:$U$506,"Pending") | H16: =COUNTIFS(Bets!$A$2:$A$506,"<>",Bets!$B$2:$B$506,"Steve",Bets!$J$2:$J$506,"MLB",Bets!$U$2:$U$506,"Unknown") | I16: =IF(D16+E16=0,"",D16/(D16+E16)) | J16: =SUMIFS(Bets!$Q$2:$Q$506,Bets!$A$2:$A$506,"<>",Bets!$B$2:$B$506,"Steve",Bets!$J$2:$J$506,"MLB") | K16: =SUMIFS(Bets!$AC$2:$AC$506,Bets!$A$2:$A$506,"<>",Bets!$B$2:$B$506,"Steve",Bets!$J$2:$J$506,"MLB") | L16: =SUMIFS(Bets!$V$2:$V$506,Bets!$A$2:$A$506,"<>",Bets!$B$2:$B$506,"Steve",Bets!$J$2:$J$506,"MLB") | M16: =IF(K16=0,"",L16/K16) | N16: =SUMIFS(Bets!$AD$2:$AD$506,Bets!$A$2:$A$506,"<>",Bets!$B$2:$B$506,"Steve",Bets!$J$2:$J$506,"MLB") | O16: =SUMIFS(Bets!$W$2:$W$506,Bets!$A$2:$A$506,"<>",Bets!$B$2:$B$506,"Steve",Bets!$J$2:$J$506,"MLB") | P16: =IF(N16=0,"",O16/N16)
A17: Steve (@stevewilldoit) | B17: NFL | C17: =COUNTIFS(Bets!$A$2:$A$506,"<>",Bets!$B$2:$B$506,"Steve",Bets!$J$2:$J$506,"NFL") | D17: =COUNTIFS(Bets!$A$2:$A$506,"<>",Bets!$B$2:$B$506,"Steve",Bets!$J$2:$J$506,"NFL",Bets!$U$2:$U$506,"W") | E17: =COUNTIFS(Bets!$A$2:$A$506,"<>",Bets!$B$2:$B$506,"Steve",Bets!$J$2:$J$506,"NFL",Bets!$U$2:$U$506,"L") | F17: =COUNTIFS(Bets!$A$2:$A$506,"<>",Bets!$B$2:$B$506,"Steve",Bets!$J$2:$J$506,"NFL",Bets!$U$2:$U$506,"Push") | G17: =COUNTIFS(Bets!$A$2:$A$506,"<>",Bets!$B$2:$B$506,"Steve",Bets!$J$2:$J$506,"NFL",Bets!$U$2:$U$506,"Pending") | H17: =COUNTIFS(Bets!$A$2:$A$506,"<>",Bets!$B$2:$B$506,"Steve",Bets!$J$2:$J$506,"NFL",Bets!$U$2:$U$506,"Unknown") | I17: =IF(D17+E17=0,"",D17/(D17+E17)) | J17: =SUMIFS(Bets!$Q$2:$Q$506,Bets!$A$2:$A$506,"<>",Bets!$B$2:$B$506,"Steve",Bets!$J$2:$J$506,"NFL") | K17: =SUMIFS(Bets!$AC$2:$AC$506,Bets!$A$2:$A$506,"<>",Bets!$B$2:$B$506,"Steve",Bets!$J$2:$J$506,"NFL") | L17: =SUMIFS(Bets!$V$2:$V$506,Bets!$A$2:$A$506,"<>",Bets!$B$2:$B$506,"Steve",Bets!$J$2:$J$506,"NFL") | M17: =IF(K17=0,"",L17/K17) | N17: =SUMIFS(Bets!$AD$2:$AD$506,Bets!$A$2:$A$506,"<>",Bets!$B$2:$B$506,"Steve",Bets!$J$2:$J$506,"NFL") | O17: =SUMIFS(Bets!$W$2:$W$506,Bets!$A$2:$A$506,"<>",Bets!$B$2:$B$506,"Steve",Bets!$J$2:$J$506,"NFL") | P17: =IF(N17=0,"",O17/N17)
A18: Steve (@stevewilldoit) | B18: Other | C18: =COUNTIFS(Bets!$A$2:$A$506,"<>",Bets!$B$2:$B$506,"Steve",Bets!$J$2:$J$506,"Other") | D18: =COUNTIFS(Bets!$A$2:$A$506,"<>",Bets!$B$2:$B$506,"Steve",Bets!$J$2:$J$506,"Other",Bets!$U$2:$U$506,"W") | E18: =COUNTIFS(Bets!$A$2:$A$506,"<>",Bets!$B$2:$B$506,"Steve",Bets!$J$2:$J$506,"Other",Bets!$U$2:$U$506,"L") | F18: =COUNTIFS(Bets!$A$2:$A$506,"<>",Bets!$B$2:$B$506,"Steve",Bets!$J$2:$J$506,"Other",Bets!$U$2:$U$506,"Push") | G18: =COUNTIFS(Bets!$A$2:$A$506,"<>",Bets!$B$2:$B$506,"Steve",Bets!$J$2:$J$506,"Other",Bets!$U$2:$U$506,"Pending") | H18: =COUNTIFS(Bets!$A$2:$A$506,"<>",Bets!$B$2:$B$506,"Steve",Bets!$J$2:$J$506,"Other",Bets!$U$2:$U$506,"Unknown") | I18: =IF(D18+E18=0,"",D18/(D18+E18)) | J18: =SUMIFS(Bets!$Q$2:$Q$506,Bets!$A$2:$A$506,"<>",Bets!$B$2:$B$506,"Steve",Bets!$J$2:$J$506,"Other") | K18: =SUMIFS(Bets!$AC$2:$AC$506,Bets!$A$2:$A$506,"<>",Bets!$B$2:$B$506,"Steve",Bets!$J$2:$J$506,"Other") | L18: =SUMIFS(Bets!$V$2:$V$506,Bets!$A$2:$A$506,"<>",Bets!$B$2:$B$506,"Steve",Bets!$J$2:$J$506,"Other") | M18: =IF(K18=0,"",L18/K18) | N18: =SUMIFS(Bets!$AD$2:$AD$506,Bets!$A$2:$A$506,"<>",Bets!$B$2:$B$506,"Steve",Bets!$J$2:$J$506,"Other") | O18: =SUMIFS(Bets!$W$2:$W$506,Bets!$A$2:$A$506,"<>",Bets!$B$2:$B$506,"Steve",Bets!$J$2:$J$506,"Other") | P18: =IF(N18=0,"",O18/N18)
A19: Steve (@stevewilldoit) | B19: Soccer | C19: =COUNTIFS(Bets!$A$2:$A$506,"<>",Bets!$B$2:$B$506,"Steve",Bets!$J$2:$J$506,"Soccer") | D19: =COUNTIFS(Bets!$A$2:$A$506,"<>",Bets!$B$2:$B$506,"Steve",Bets!$J$2:$J$506,"Soccer",Bets!$U$2:$U$506,"W") | E19: =COUNTIFS(Bets!$A$2:$A$506,"<>",Bets!$B$2:$B$506,"Steve",Bets!$J$2:$J$506,"Soccer",Bets!$U$2:$U$506,"L") | F19: =COUNTIFS(Bets!$A$2:$A$506,"<>",Bets!$B$2:$B$506,"Steve",Bets!$J$2:$J$506,"Soccer",Bets!$U$2:$U$506,"Push") | G19: =COUNTIFS(Bets!$A$2:$A$506,"<>",Bets!$B$2:$B$506,"Steve",Bets!$J$2:$J$506,"Soccer",Bets!$U$2:$U$506,"Pending") | H19: =COUNTIFS(Bets!$A$2:$A$506,"<>",Bets!$B$2:$B$506,"Steve",Bets!$J$2:$J$506,"Soccer",Bets!$U$2:$U$506,"Unknown") | I19: =IF(D19+E19=0,"",D19/(D19+E19)) | J19: =SUMIFS(Bets!$Q$2:$Q$506,Bets!$A$2:$A$506,"<>",Bets!$B$2:$B$506,"Steve",Bets!$J$2:$J$506,"Soccer") | K19: =SUMIFS(Bets!$AC$2:$AC$506,Bets!$A$2:$A$506,"<>",Bets!$B$2:$B$506,"Steve",Bets!$J$2:$J$506,"Soccer") | L19: =SUMIFS(Bets!$V$2:$V$506,Bets!$A$2:$A$506,"<>",Bets!$B$2:$B$506,"Steve",Bets!$J$2:$J$506,"Soccer") | M19: =IF(K19=0,"",L19/K19) | N19: =SUMIFS(Bets!$AD$2:$AD$506,Bets!$A$2:$A$506,"<>",Bets!$B$2:$B$506,"Steve",Bets!$J$2:$J$506,"Soccer") | O19: =SUMIFS(Bets!$W$2:$W$506,Bets!$A$2:$A$506,"<>",Bets!$B$2:$B$506,"Steve",Bets!$J$2:$J$506,"Soccer") | P19: =IF(N19=0,"",O19/N19)
A20: Steve (@stevewilldoit) | B20: Tennis | C20: =COUNTIFS(Bets!$A$2:$A$506,"<>",Bets!$B$2:$B$506,"Steve",Bets!$J$2:$J$506,"Tennis") | D20: =COUNTIFS(Bets!$A$2:$A$506,"<>",Bets!$B$2:$B$506,"Steve",Bets!$J$2:$J$506,"Tennis",Bets!$U$2:$U$506,"W") | E20: =COUNTIFS(Bets!$A$2:$A$506,"<>",Bets!$B$2:$B$506,"Steve",Bets!$J$2:$J$506,"Tennis",Bets!$U$2:$U$506,"L") | F20: =COUNTIFS(Bets!$A$2:$A$506,"<>",Bets!$B$2:$B$506,"Steve",Bets!$J$2:$J$506,"Tennis",Bets!$U$2:$U$506,"Push") | G20: =COUNTIFS(Bets!$A$2:$A$506,"<>",Bets!$B$2:$B$506,"Steve",Bets!$J$2:$J$506,"Tennis",Bets!$U$2:$U$506,"Pending") | H20: =COUNTIFS(Bets!$A$2:$A$506,"<>",Bets!$B$2:$B$506,"Steve",Bets!$J$2:$J$506,"Tennis",Bets!$U$2:$U$506,"Unknown") | I20: =IF(D20+E20=0,"",D20/(D20+E20)) | J20: =SUMIFS(Bets!$Q$2:$Q$506,Bets!$A$2:$A$506,"<>",Bets!$B$2:$B$506,"Steve",Bets!$J$2:$J$506,"Tennis") | K20: =SUMIFS(Bets!$AC$2:$AC$506,Bets!$A$2:$A$506,"<>",Bets!$B$2:$B$506,"Steve",Bets!$J$2:$J$506,"Tennis") | L20: =SUMIFS(Bets!$V$2:$V$506,Bets!$A$2:$A$506,"<>",Bets!$B$2:$B$506,"Steve",Bets!$J$2:$J$506,"Tennis") | M20: =IF(K20=0,"",L20/K20) | N20: =SUMIFS(Bets!$AD$2:$AD$506,Bets!$A$2:$A$506,"<>",Bets!$B$2:$B$506,"Steve",Bets!$J$2:$J$506,"Tennis") | O20: =SUMIFS(Bets!$W$2:$W$506,Bets!$A$2:$A$506,"<>",Bets!$B$2:$B$506,"Steve",Bets!$J$2:$J$506,"Tennis") | P20: =IF(N20=0,"",O20/N20)
A21: Steve (@stevewilldoit) | B21: UFC/MMA | C21: =COUNTIFS(Bets!$A$2:$A$506,"<>",Bets!$B$2:$B$506,"Steve",Bets!$J$2:$J$506,"UFC/MMA") | D21: =COUNTIFS(Bets!$A$2:$A$506,"<>",Bets!$B$2:$B$506,"Steve",Bets!$J$2:$J$506,"UFC/MMA",Bets!$U$2:$U$506,"W") | E21: =COUNTIFS(Bets!$A$2:$A$506,"<>",Bets!$B$2:$B$506,"Steve",Bets!$J$2:$J$506,"UFC/MMA",Bets!$U$2:$U$506,"L") | F21: =COUNTIFS(Bets!$A$2:$A$506,"<>",Bets!$B$2:$B$506,"Steve",Bets!$J$2:$J$506,"UFC/MMA",Bets!$U$2:$U$506,"Push") | G21: =COUNTIFS(Bets!$A$2:$A$506,"<>",Bets!$B$2:$B$506,"Steve",Bets!$J$2:$J$506,"UFC/MMA",Bets!$U$2:$U$506,"Pending") | H21: =COUNTIFS(Bets!$A$2:$A$506,"<>",Bets!$B$2:$B$506,"Steve",Bets!$J$2:$J$506,"UFC/MMA",Bets!$U$2:$U$506,"Unknown") | I21: =IF(D21+E21=0,"",D21/(D21+E21)) | J21: =SUMIFS(Bets!$Q$2:$Q$506,Bets!$A$2:$A$506,"<>",Bets!$B$2:$B$506,"Steve",Bets!$J$2:$J$506,"UFC/MMA") | K21: =SUMIFS(Bets!$AC$2:$AC$506,Bets!$A$2:$A$506,"<>",Bets!$B$2:$B$506,"Steve",Bets!$J$2:$J$506,"UFC/MMA") | L21: =SUMIFS(Bets!$V$2:$V$506,Bets!$A$2:$A$506,"<>",Bets!$B$2:$B$506,"Steve",Bets!$J$2:$J$506,"UFC/MMA") | M21: =IF(K21=0,"",L21/K21) | N21: =SUMIFS(Bets!$AD$2:$AD$506,Bets!$A$2:$A$506,"<>",Bets!$B$2:$B$506,"Steve",Bets!$J$2:$J$506,"UFC/MMA") | O21: =SUMIFS(Bets!$W$2:$W$506,Bets!$A$2:$A$506,"<>",Bets!$B$2:$B$506,"Steve",Bets!$J$2:$J$506,"UFC/MMA") | P21: =IF(N21=0,"",O21/N21)
A23: Combined
A24: Bettor | B24: Sport | C24: Bets | D24: W | E24: L | F24: Push | G24: Pending | H24: Unknown | I24: Win % (W/(W+L)) | J24: Total staked $ (all $ bets) | K24: Settled staked $ | L24: Net P/L $ | M24: ROI (net / settled $) | N24: Units staked (settled) | O24: Net units | P24: ROI (units)
A25: Combined | B25: CFB | C25: =COUNTIFS(Bets!$A$2:$A$506,"<>",Bets!$B$2:$B$506,"*",Bets!$J$2:$J$506,"CFB") | D25: =COUNTIFS(Bets!$A$2:$A$506,"<>",Bets!$B$2:$B$506,"*",Bets!$J$2:$J$506,"CFB",Bets!$U$2:$U$506,"W") | E25: =COUNTIFS(Bets!$A$2:$A$506,"<>",Bets!$B$2:$B$506,"*",Bets!$J$2:$J$506,"CFB",Bets!$U$2:$U$506,"L") | F25: =COUNTIFS(Bets!$A$2:$A$506,"<>",Bets!$B$2:$B$506,"*",Bets!$J$2:$J$506,"CFB",Bets!$U$2:$U$506,"Push") | G25: =COUNTIFS(Bets!$A$2:$A$506,"<>",Bets!$B$2:$B$506,"*",Bets!$J$2:$J$506,"CFB",Bets!$U$2:$U$506,"Pending") | H25: =COUNTIFS(Bets!$A$2:$A$506,"<>",Bets!$B$2:$B$506,"*",Bets!$J$2:$J$506,"CFB",Bets!$U$2:$U$506,"Unknown") | I25: =IF(D25+E25=0,"",D25/(D25+E25)) | J25: =SUMIFS(Bets!$Q$2:$Q$506,Bets!$A$2:$A$506,"<>",Bets!$B$2:$B$506,"*",Bets!$J$2:$J$506,"CFB") | K25: =SUMIFS(Bets!$AC$2:$AC$506,Bets!$A$2:$A$506,"<>",Bets!$B$2:$B$506,"*",Bets!$J$2:$J$506,"CFB") | L25: =SUMIFS(Bets!$V$2:$V$506,Bets!$A$2:$A$506,"<>",Bets!$B$2:$B$506,"*",Bets!$J$2:$J$506,"CFB") | M25: =IF(K25=0,"",L25/K25) | N25: =SUMIFS(Bets!$AD$2:$AD$506,Bets!$A$2:$A$506,"<>",Bets!$B$2:$B$506,"*",Bets!$J$2:$J$506,"CFB") | O25: =SUMIFS(Bets!$W$2:$W$506,Bets!$A$2:$A$506,"<>",Bets!$B$2:$B$506,"*",Bets!$J$2:$J$506,"CFB") | P25: =IF(N25=0,"",O25/N25)
A26: Combined | B26: MLB | C26: =COUNTIFS(Bets!$A$2:$A$506,"<>",Bets!$B$2:$B$506,"*",Bets!$J$2:$J$506,"MLB") | D26: =COUNTIFS(Bets!$A$2:$A$506,"<>",Bets!$B$2:$B$506,"*",Bets!$J$2:$J$506,"MLB",Bets!$U$2:$U$506,"W") | E26: =COUNTIFS(Bets!$A$2:$A$506,"<>",Bets!$B$2:$B$506,"*",Bets!$J$2:$J$506,"MLB",Bets!$U$2:$U$506,"L") | F26: =COUNTIFS(Bets!$A$2:$A$506,"<>",Bets!$B$2:$B$506,"*",Bets!$J$2:$J$506,"MLB",Bets!$U$2:$U$506,"Push") | G26: =COUNTIFS(Bets!$A$2:$A$506,"<>",Bets!$B$2:$B$506,"*",Bets!$J$2:$J$506,"MLB",Bets!$U$2:$U$506,"Pending") | H26: =COUNTIFS(Bets!$A$2:$A$506,"<>",Bets!$B$2:$B$506,"*",Bets!$J$2:$J$506,"MLB",Bets!$U$2:$U$506,"Unknown") | I26: =IF(D26+E26=0,"",D26/(D26+E26)) | J26: =SUMIFS(Bets!$Q$2:$Q$506,Bets!$A$2:$A$506,"<>",Bets!$B$2:$B$506,"*",Bets!$J$2:$J$506,"MLB") | K26: =SUMIFS(Bets!$AC$2:$AC$506,Bets!$A$2:$A$506,"<>",Bets!$B$2:$B$506,"*",Bets!$J$2:$J$506,"MLB") | L26: =SUMIFS(Bets!$V$2:$V$506,Bets!$A$2:$A$506,"<>",Bets!$B$2:$B$506,"*",Bets!$J$2:$J$506,"MLB") | M26: =IF(K26=0,"",L26/K26) | N26: =SUMIFS(Bets!$AD$2:$AD$506,Bets!$A$2:$A$506,"<>",Bets!$B$2:$B$506,"*",Bets!$J$2:$J$506,"MLB") | O26: =SUMIFS(Bets!$W$2:$W$506,Bets!$A$2:$A$506,"<>",Bets!$B$2:$B$506,"*",Bets!$J$2:$J$506,"MLB") | P26: =IF(N26=0,"",O26/N26)
A27: Combined | B27: NFL | C27: =COUNTIFS(Bets!$A$2:$A$506,"<>",Bets!$B$2:$B$506,"*",Bets!$J$2:$J$506,"NFL") | D27: =COUNTIFS(Bets!$A$2:$A$506,"<>",Bets!$B$2:$B$506,"*",Bets!$J$2:$J$506,"NFL",Bets!$U$2:$U$506,"W") | E27: =COUNTIFS(Bets!$A$2:$A$506,"<>",Bets!$B$2:$B$506,"*",Bets!$J$2:$J$506,"NFL",Bets!$U$2:$U$506,"L") | F27: =COUNTIFS(Bets!$A$2:$A$506,"<>",Bets!$B$2:$B$506,"*",Bets!$J$2:$J$506,"NFL",Bets!$U$2:$U$506,"Push") | G27: =COUNTIFS(Bets!$A$2:$A$506,"<>",Bets!$B$2:$B$506,"*",Bets!$J$2:$J$506,"NFL",Bets!$U$2:$U$506,"Pending") | H27: =COUNTIFS(Bets!$A$2:$A$506,"<>",Bets!$B$2:$B$506,"*",Bets!$J$2:$J$506,"NFL",Bets!$U$2:$U$506,"Unknown") | I27: =IF(D27+E27=0,"",D27/(D27+E27)) | J27: =SUMIFS(Bets!$Q$2:$Q$506,Bets!$A$2:$A$506,"<>",Bets!$B$2:$B$506,"*",Bets!$J$2:$J$506,"NFL") | K27: =SUMIFS(Bets!$AC$2:$AC$506,Bets!$A$2:$A$506,"<>",Bets!$B$2:$B$506,"*",Bets!$J$2:$J$506,"NFL") | L27: =SUMIFS(Bets!$V$2:$V$506,Bets!$A$2:$A$506,"<>",Bets!$B$2:$B$506,"*",Bets!$J$2:$J$506,"NFL") | M27: =IF(K27=0,"",L27/K27) | N27: =SUMIFS(Bets!$AD$2:$AD$506,Bets!$A$2:$A$506,"<>",Bets!$B$2:$B$506,"*",Bets!$J$2:$J$506,"NFL") | O27: =SUMIFS(Bets!$W$2:$W$506,Bets!$A$2:$A$506,"<>",Bets!$B$2:$B$506,"*",Bets!$J$2:$J$506,"NFL") | P27: =IF(N27=0,"",O27/N27)
A28: Combined | B28: Other | C28: =COUNTIFS(Bets!$A$2:$A$506,"<>",Bets!$B$2:$B$506,"*",Bets!$J$2:$J$506,"Other") | D28: =COUNTIFS(Bets!$A$2:$A$506,"<>",Bets!$B$2:$B$506,"*",Bets!$J$2:$J$506,"Other",Bets!$U$2:$U$506,"W") | E28: =COUNTIFS(Bets!$A$2:$A$506,"<>",Bets!$B$2:$B$506,"*",Bets!$J$2:$J$506,"Other",Bets!$U$2:$U$506,"L") | F28: =COUNTIFS(Bets!$A$2:$A$506,"<>",Bets!$B$2:$B$506,"*",Bets!$J$2:$J$506,"Other",Bets!$U$2:$U$506,"Push") | G28: =COUNTIFS(Bets!$A$2:$A$506,"<>",Bets!$B$2:$B$506,"*",Bets!$J$2:$J$506,"Other",Bets!$U$2:$U$506,"Pending") | H28: =COUNTIFS(Bets!$A$2:$A$506,"<>",Bets!$B$2:$B$506,"*",Bets!$J$2:$J$506,"Other",Bets!$U$2:$U$506,"Unknown") | I28: =IF(D28+E28=0,"",D28/(D28+E28)) | J28: =SUMIFS(Bets!$Q$2:$Q$506,Bets!$A$2:$A$506,"<>",Bets!$B$2:$B$506,"*",Bets!$J$2:$J$506,"Other") | K28: =SUMIFS(Bets!$AC$2:$AC$506,Bets!$A$2:$A$506,"<>",Bets!$B$2:$B$506,"*",Bets!$J$2:$J$506,"Other") | L28: =SUMIFS(Bets!$V$2:$V$506,Bets!$A$2:$A$506,"<>",Bets!$B$2:$B$506,"*",Bets!$J$2:$J$506,"Other") | M28: =IF(K28=0,"",L28/K28) | N28: =SUMIFS(Bets!$AD$2:$AD$506,Bets!$A$2:$A$506,"<>",Bets!$B$2:$B$506,"*",Bets!$J$2:$J$506,"Other") | O28: =SUMIFS(Bets!$W$2:$W$506,Bets!$A$2:$A$506,"<>",Bets!$B$2:$B$506,"*",Bets!$J$2:$J$506,"Other") | P28: =IF(N28=0,"",O28/N28)
A29: Combined | B29: Soccer | C29: =COUNTIFS(Bets!$A$2:$A$506,"<>",Bets!$B$2:$B$506,"*",Bets!$J$2:$J$506,"Soccer") | D29: =COUNTIFS(Bets!$A$2:$A$506,"<>",Bets!$B$2:$B$506,"*",Bets!$J$2:$J$506,"Soccer",Bets!$U$2:$U$506,"W") | E29: =COUNTIFS(Bets!$A$2:$A$506,"<>",Bets!$B$2:$B$506,"*",Bets!$J$2:$J$506,"Soccer",Bets!$U$2:$U$506,"L") | F29: =COUNTIFS(Bets!$A$2:$A$506,"<>",Bets!$B$2:$B$506,"*",Bets!$J$2:$J$506,"Soccer",Bets!$U$2:$U$506,"Push") | G29: =COUNTIFS(Bets!$A$2:$A$506,"<>",Bets!$B$2:$B$506,"*",Bets!$J$2:$J$506,"Soccer",Bets!$U$2:$U$506,"Pending") | H29: =COUNTIFS(Bets!$A$2:$A$506,"<>",Bets!$B$2:$B$506,"*",Bets!$J$2:$J$506,"Soccer",Bets!$U$2:$U$506,"Unknown") | I29: =IF(D29+E29=0,"",D29/(D29+E29)) | J29: =SUMIFS(Bets!$Q$2:$Q$506,Bets!$A$2:$A$506,"<>",Bets!$B$2:$B$506,"*",Bets!$J$2:$J$506,"Soccer") | K29: =SUMIFS(Bets!$AC$2:$AC$506,Bets!$A$2:$A$506,"<>",Bets!$B$2:$B$506,"*",Bets!$J$2:$J$506,"Soccer") | L29: =SUMIFS(Bets!$V$2:$V$506,Bets!$A$2:$A$506,"<>",Bets!$B$2:$B$506,"*",Bets!$J$2:$J$506,"Soccer") | M29: =IF(K29=0,"",L29/K29) | N29: =SUMIFS(Bets!$AD$2:$AD$506,Bets!$A$2:$A$506,"<>",Bets!$B$2:$B$506,"*",Bets!$J$2:$J$506,"Soccer") | O29: =SUMIFS(Bets!$W$2:$W$506,Bets!$A$2:$A$506,"<>",Bets!$B$2:$B$506,"*",Bets!$J$2:$J$506,"Soccer") | P29: =IF(N29=0,"",O29/N29)
A30: Combined | B30: Tennis | C30: =COUNTIFS(Bets!$A$2:$A$506,"<>",Bets!$B$2:$B$506,"*",Bets!$J$2:$J$506,"Tennis") | D30: =COUNTIFS(Bets!$A$2:$A$506,"<>",Bets!$B$2:$B$506,"*",Bets!$J$2:$J$506,"Tennis",Bets!$U$2:$U$506,"W") | E30: =COUNTIFS(Bets!$A$2:$A$506,"<>",Bets!$B$2:$B$506,"*",Bets!$J$2:$J$506,"Tennis",Bets!$U$2:$U$506,"L") | F30: =COUNTIFS(Bets!$A$2:$A$506,"<>",Bets!$B$2:$B$506,"*",Bets!$J$2:$J$506,"Tennis",Bets!$U$2:$U$506,"Push") | G30: =COUNTIFS(Bets!$A$2:$A$506,"<>",Bets!$B$2:$B$506,"*",Bets!$J$2:$J$506,"Tennis",Bets!$U$2:$U$506,"Pending") | H30: =COUNTIFS(Bets!$A$2:$A$506,"<>",Bets!$B$2:$B$506,"*",Bets!$J$2:$J$506,"Tennis",Bets!$U$2:$U$506,"Unknown") | I30: =IF(D30+E30=0,"",D30/(D30+E30)) | J30: =SUMIFS(Bets!$Q$2:$Q$506,Bets!$A$2:$A$506,"<>",Bets!$B$2:$B$506,"*",Bets!$J$2:$J$506,"Tennis") | K30: =SUMIFS(Bets!$AC$2:$AC$506,Bets!$A$2:$A$506,"<>",Bets!$B$2:$B$506,"*",Bets!$J$2:$J$506,"Tennis") | L30: =SUMIFS(Bets!$V$2:$V$506,Bets!$A$2:$A$506,"<>",Bets!$B$2:$B$506,"*",Bets!$J$2:$J$506,"Tennis") | M30: =IF(K30=0,"",L30/K30) | N30: =SUMIFS(Bets!$AD$2:$AD$506,Bets!$A$2:$A$506,"<>",Bets!$B$2:$B$506,"*",Bets!$J$2:$J$506,"Tennis") | O30: =SUMIFS(Bets!$W$2:$W$506,Bets!$A$2:$A$506,"<>",Bets!$B$2:$B$506,"*",Bets!$J$2:$J$506,"Tennis") | P30: =IF(N30=0,"",O30/N30)
A31: Combined | B31: UFC/MMA | C31: =COUNTIFS(Bets!$A$2:$A$506,"<>",Bets!$B$2:$B$506,"*",Bets!$J$2:$J$506,"UFC/MMA") | D31: =COUNTIFS(Bets!$A$2:$A$506,"<>",Bets!$B$2:$B$506,"*",Bets!$J$2:$J$506,"UFC/MMA",Bets!$U$2:$U$506,"W") | E31: =COUNTIFS(Bets!$A$2:$A$506,"<>",Bets!$B$2:$B$506,"*",Bets!$J$2:$J$506,"UFC/MMA",Bets!$U$2:$U$506,"L") | F31: =COUNTIFS(Bets!$A$2:$A$506,"<>",Bets!$B$2:$B$506,"*",Bets!$J$2:$J$506,"UFC/MMA",Bets!$U$2:$U$506,"Push") | G31: =COUNTIFS(Bets!$A$2:$A$506,"<>",Bets!$B$2:$B$506,"*",Bets!$J$2:$J$506,"UFC/MMA",Bets!$U$2:$U$506,"Pending") | H31: =COUNTIFS(Bets!$A$2:$A$506,"<>",Bets!$B$2:$B$506,"*",Bets!$J$2:$J$506,"UFC/MMA",Bets!$U$2:$U$506,"Unknown") | I31: =IF(D31+E31=0,"",D31/(D31+E31)) | J31: =SUMIFS(Bets!$Q$2:$Q$506,Bets!$A$2:$A$506,"<>",Bets!$B$2:$B$506,"*",Bets!$J$2:$J$506,"UFC/MMA") | K31: =SUMIFS(Bets!$AC$2:$AC$506,Bets!$A$2:$A$506,"<>",Bets!$B$2:$B$506,"*",Bets!$J$2:$J$506,"UFC/MMA") | L31: =SUMIFS(Bets!$V$2:$V$506,Bets!$A$2:$A$506,"<>",Bets!$B$2:$B$506,"*",Bets!$J$2:$J$506,"UFC/MMA") | M31: =IF(K31=0,"",L31/K31) | N31: =SUMIFS(Bets!$AD$2:$AD$506,Bets!$A$2:$A$506,"<>",Bets!$B$2:$B$506,"*",Bets!$J$2:$J$506,"UFC/MMA") | O31: =SUMIFS(Bets!$W$2:$W$506,Bets!$A$2:$A$506,"<>",Bets!$B$2:$B$506,"*",Bets!$J$2:$J$506,"UFC/MMA") | P31: =IF(N31=0,"",O31/N31)

Sheet By Prime Time
A1: Prime time vs non-prime, and by prime-time slot (rule in Legend/Notes)
A3: Prime vs non-prime
A4: Bettor | B4: Prime time | C4: Bets | D4: W | E4: L | F4: Push | G4: Pending | H4: Unknown | I4: Win % (W/(W+L)) | J4: Total staked $ (all $ bets) | K4: Settled staked $ | L4: Net P/L $ | M4: ROI (net / settled $) | N4: Units staked (settled) | O4: Net units | P4: ROI (units)
A5: Trent (@BookitWithTrent) | B5: Y | C5: =COUNTIFS(Bets!$A$2:$A$506,"<>",Bets!$B$2:$B$506,"Trent",Bets!$H$2:$H$506,"Y") | D5: =COUNTIFS(Bets!$A$2:$A$506,"<>",Bets!$B$2:$B$506,"Trent",Bets!$H$2:$H$506,"Y",Bets!$U$2:$U$506,"W") | E5: =COUNTIFS(Bets!$A$2:$A$506,"<>",Bets!$B$2:$B$506,"Trent",Bets!$H$2:$H$506,"Y",Bets!$U$2:$U$506,"L") | F5: =COUNTIFS(Bets!$A$2:$A$506,"<>",Bets!$B$2:$B$506,"Trent",Bets!$H$2:$H$506,"Y",Bets!$U$2:$U$506,"Push") | G5: =COUNTIFS(Bets!$A$2:$A$506,"<>",Bets!$B$2:$B$506,"Trent",Bets!$H$2:$H$506,"Y",Bets!$U$2:$U$506,"Pending") | H5: =COUNTIFS(Bets!$A$2:$A$506,"<>",Bets!$B$2:$B$506,"Trent",Bets!$H$2:$H$506,"Y",Bets!$U$2:$U$506,"Unknown") | I5: =IF(D5+E5=0,"",D5/(D5+E5)) | J5: =SUMIFS(Bets!$Q$2:$Q$506,Bets!$A$2:$A$506,"<>",Bets!$B$2:$B$506,"Trent",Bets!$H$2:$H$506,"Y") | K5: =SUMIFS(Bets!$AC$2:$AC$506,Bets!$A$2:$A$506,"<>",Bets!$B$2:$B$506,"Trent",Bets!$H$2:$H$506,"Y") | L5: =SUMIFS(Bets!$V$2:$V$506,Bets!$A$2:$A$506,"<>",Bets!$B$2:$B$506,"Trent",Bets!$H$2:$H$506,"Y") | M5: =IF(K5=0,"",L5/K5) | N5: =SUMIFS(Bets!$AD$2:$AD$506,Bets!$A$2:$A$506,"<>",Bets!$B$2:$B$506,"Trent",Bets!$H$2:$H$506,"Y") | O5: =SUMIFS(Bets!$W$2:$W$506,Bets!$A$2:$A$506,"<>",Bets!$B$2:$B$506,"Trent",Bets!$H$2:$H$506,"Y") | P5: =IF(N5=0,"",O5/N5)
A6: Trent (@BookitWithTrent) | B6: N | C6: =COUNTIFS(Bets!$A$2:$A$506,"<>",Bets!$B$2:$B$506,"Trent",Bets!$H$2:$H$506,"N") | D6: =COUNTIFS(Bets!$A$2:$A$506,"<>",Bets!$B$2:$B$506,"Trent",Bets!$H$2:$H$506,"N",Bets!$U$2:$U$506,"W") | E6: =COUNTIFS(Bets!$A$2:$A$506,"<>",Bets!$B$2:$B$506,"Trent",Bets!$H$2:$H$506,"N",Bets!$U$2:$U$506,"L") | F6: =COUNTIFS(Bets!$A$2:$A$506,"<>",Bets!$B$2:$B$506,"Trent",Bets!$H$2:$H$506,"N",Bets!$U$2:$U$506,"Push") | G6: =COUNTIFS(Bets!$A$2:$A$506,"<>",Bets!$B$2:$B$506,"Trent",Bets!$H$2:$H$506,"N",Bets!$U$2:$U$506,"Pending") | H6: =COUNTIFS(Bets!$A$2:$A$506,"<>",Bets!$B$2:$B$506,"Trent",Bets!$H$2:$H$506,"N",Bets!$U$2:$U$506,"Unknown") | I6: =IF(D6+E6=0,"",D6/(D6+E6)) | J6: =SUMIFS(Bets!$Q$2:$Q$506,Bets!$A$2:$A$506,"<>",Bets!$B$2:$B$506,"Trent",Bets!$H$2:$H$506,"N") | K6: =SUMIFS(Bets!$AC$2:$AC$506,Bets!$A$2:$A$506,"<>",Bets!$B$2:$B$506,"Trent",Bets!$H$2:$H$506,"N") | L6: =SUMIFS(Bets!$V$2:$V$506,Bets!$A$2:$A$506,"<>",Bets!$B$2:$B$506,"Trent",Bets!$H$2:$H$506,"N") | M6: =IF(K6=0,"",L6/K6) | N6: =SUMIFS(Bets!$AD$2:$AD$506,Bets!$A$2:$A$506,"<>",Bets!$B$2:$B$506,"Trent",Bets!$H$2:$H$506,"N") | O6: =SUMIFS(Bets!$W$2:$W$506,Bets!$A$2:$A$506,"<>",Bets!$B$2:$B$506,"Trent",Bets!$H$2:$H$506,"N") | P6: =IF(N6=0,"",O6/N6)
A7: Trent (@BookitWithTrent) | B7: Unknown | C7: =COUNTIFS(Bets!$A$2:$A$506,"<>",Bets!$B$2:$B$506,"Trent",Bets!$H$2:$H$506,"Unknown") | D7: =COUNTIFS(Bets!$A$2:$A$506,"<>",Bets!$B$2:$B$506,"Trent",Bets!$H$2:$H$506,"Unknown",Bets!$U$2:$U$506,"W") | E7: =COUNTIFS(Bets!$A$2:$A$506,"<>",Bets!$B$2:$B$506,"Trent",Bets!$H$2:$H$506,"Unknown",Bets!$U$2:$U$506,"L") | F7: =COUNTIFS(Bets!$A$2:$A$506,"<>",Bets!$B$2:$B$506,"Trent",Bets!$H$2:$H$506,"Unknown",Bets!$U$2:$U$506,"Push") | G7: =COUNTIFS(Bets!$A$2:$A$506,"<>",Bets!$B$2:$B$506,"Trent",Bets!$H$2:$H$506,"Unknown",Bets!$U$2:$U$506,"Pending") | H7: =COUNTIFS(Bets!$A$2:$A$506,"<>",Bets!$B$2:$B$506,"Trent",Bets!$H$2:$H$506,"Unknown",Bets!$U$2:$U$506,"Unknown") | I7: =IF(D7+E7=0,"",D7/(D7+E7)) | J7: =SUMIFS(Bets!$Q$2:$Q$506,Bets!$A$2:$A$506,"<>",Bets!$B$2:$B$506,"Trent",Bets!$H$2:$H$506,"Unknown") | K7: =SUMIFS(Bets!$AC$2:$AC$506,Bets!$A$2:$A$506,"<>",Bets!$B$2:$B$506,"Trent",Bets!$H$2:$H$506,"Unknown") | L7: =SUMIFS(Bets!$V$2:$V$506,Bets!$A$2:$A$506,"<>",Bets!$B$2:$B$506,"Trent",Bets!$H$2:$H$506,"Unknown") | M7: =IF(K7=0,"",L7/K7) | N7: =SUMIFS(Bets!$AD$2:$AD$506,Bets!$A$2:$A$506,"<>",Bets!$B$2:$B$506,"Trent",Bets!$H$2:$H$506,"Unknown") | O7: =SUMIFS(Bets!$W$2:$W$506,Bets!$A$2:$A$506,"<>",Bets!$B$2:$B$506,"Trent",Bets!$H$2:$H$506,"Unknown") | P7: =IF(N7=0,"",O7/N7)
A8: Steve (@stevewilldoit) | B8: Y | C8: =COUNTIFS(Bets!$A$2:$A$506,"<>",Bets!$B$2:$B$506,"Steve",Bets!$H$2:$H$506,"Y") | D8: =COUNTIFS(Bets!$A$2:$A$506,"<>",Bets!$B$2:$B$506,"Steve",Bets!$H$2:$H$506,"Y",Bets!$U$2:$U$506,"W") | E8: =COUNTIFS(Bets!$A$2:$A$506,"<>",Bets!$B$2:$B$506,"Steve",Bets!$H$2:$H$506,"Y",Bets!$U$2:$U$506,"L") | F8: =COUNTIFS(Bets!$A$2:$A$506,"<>",Bets!$B$2:$B$506,"Steve",Bets!$H$2:$H$506,"Y",Bets!$U$2:$U$506,"Push") | G8: =COUNTIFS(Bets!$A$2:$A$506,"<>",Bets!$B$2:$B$506,"Steve",Bets!$H$2:$H$506,"Y",Bets!$U$2:$U$506,"Pending") | H8: =COUNTIFS(Bets!$A$2:$A$506,"<>",Bets!$B$2:$B$506,"Steve",Bets!$H$2:$H$506,"Y",Bets!$U$2:$U$506,"Unknown") | I8: =IF(D8+E8=0,"",D8/(D8+E8)) | J8: =SUMIFS(Bets!$Q$2:$Q$506,Bets!$A$2:$A$506,"<>",Bets!$B$2:$B$506,"Steve",Bets!$H$2:$H$506,"Y") | K8: =SUMIFS(Bets!$AC$2:$AC$506,Bets!$A$2:$A$506,"<>",Bets!$B$2:$B$506,"Steve",Bets!$H$2:$H$506,"Y") | L8: =SUMIFS(Bets!$V$2:$V$506,Bets!$A$2:$A$506,"<>",Bets!$B$2:$B$506,"Steve",Bets!$H$2:$H$506,"Y") | M8: =IF(K8=0,"",L8/K8) | N8: =SUMIFS(Bets!$AD$2:$AD$506,Bets!$A$2:$A$506,"<>",Bets!$B$2:$B$506,"Steve",Bets!$H$2:$H$506,"Y") | O8: =SUMIFS(Bets!$W$2:$W$506,Bets!$A$2:$A$506,"<>",Bets!$B$2:$B$506,"Steve",Bets!$H$2:$H$506,"Y") | P8: =IF(N8=0,"",O8/N8)
A9: Steve (@stevewilldoit) | B9: N | C9: =COUNTIFS(Bets!$A$2:$A$506,"<>",Bets!$B$2:$B$506,"Steve",Bets!$H$2:$H$506,"N") | D9: =COUNTIFS(Bets!$A$2:$A$506,"<>",Bets!$B$2:$B$506,"Steve",Bets!$H$2:$H$506,"N",Bets!$U$2:$U$506,"W") | E9: =COUNTIFS(Bets!$A$2:$A$506,"<>",Bets!$B$2:$B$506,"Steve",Bets!$H$2:$H$506,"N",Bets!$U$2:$U$506,"L") | F9: =COUNTIFS(Bets!$A$2:$A$506,"<>",Bets!$B$2:$B$506,"Steve",Bets!$H$2:$H$506,"N",Bets!$U$2:$U$506,"Push") | G9: =COUNTIFS(Bets!$A$2:$A$506,"<>",Bets!$B$2:$B$506,"Steve",Bets!$H$2:$H$506,"N",Bets!$U$2:$U$506,"Pending") | H9: =COUNTIFS(Bets!$A$2:$A$506,"<>",Bets!$B$2:$B$506,"Steve",Bets!$H$2:$H$506,"N",Bets!$U$2:$U$506,"Unknown") | I9: =IF(D9+E9=0,"",D9/(D9+E9)) | J9: =SUMIFS(Bets!$Q$2:$Q$506,Bets!$A$2:$A$506,"<>",Bets!$B$2:$B$506,"Steve",Bets!$H$2:$H$506,"N") | K9: =SUMIFS(Bets!$AC$2:$AC$506,Bets!$A$2:$A$506,"<>",Bets!$B$2:$B$506,"Steve",Bets!$H$2:$H$506,"N") | L9: =SUMIFS(Bets!$V$2:$V$506,Bets!$A$2:$A$506,"<>",Bets!$B$2:$B$506,"Steve",Bets!$H$2:$H$506,"N") | M9: =IF(K9=0,"",L9/K9) | N9: =SUMIFS(Bets!$AD$2:$AD$506,Bets!$A$2:$A$506,"<>",Bets!$B$2:$B$506,"Steve",Bets!$H$2:$H$506,"N") | O9: =SUMIFS(Bets!$W$2:$W$506,Bets!$A$2:$A$506,"<>",Bets!$B$2:$B$506,"Steve",Bets!$H$2:$H$506,"N") | P9: =IF(N9=0,"",O9/N9)
A10: Steve (@stevewilldoit) | B10: Unknown | C10: =COUNTIFS(Bets!$A$2:$A$506,"<>",Bets!$B$2:$B$506,"Steve",Bets!$H$2:$H$506,"Unknown") | D10: =COUNTIFS(Bets!$A$2:$A$506,"<>",Bets!$B$2:$B$506,"Steve",Bets!$H$2:$H$506,"Unknown",Bets!$U$2:$U$506,"W") | E10: =COUNTIFS(Bets!$A$2:$A$506,"<>",Bets!$B$2:$B$506,"Steve",Bets!$H$2:$H$506,"Unknown",Bets!$U$2:$U$506,"L") | F10: =COUNTIFS(Bets!$A$2:$A$506,"<>",Bets!$B$2:$B$506,"Steve",Bets!$H$2:$H$506,"Unknown",Bets!$U$2:$U$506,"Push") | G10: =COUNTIFS(Bets!$A$2:$A$506,"<>",Bets!$B$2:$B$506,"Steve",Bets!$H$2:$H$506,"Unknown",Bets!$U$2:$U$506,"Pending") | H10: =COUNTIFS(Bets!$A$2:$A$506,"<>",Bets!$B$2:$B$506,"Steve",Bets!$H$2:$H$506,"Unknown",Bets!$U$2:$U$506,"Unknown") | I10: =IF(D10+E10=0,"",D10/(D10+E10)) | J10: =SUMIFS(Bets!$Q$2:$Q$506,Bets!$A$2:$A$506,"<>",Bets!$B$2:$B$506,"Steve",Bets!$H$2:$H$506,"Unknown") | K10: =SUMIFS(Bets!$AC$2:$AC$506,Bets!$A$2:$A$506,"<>",Bets!$B$2:$B$506,"Steve",Bets!$H$2:$H$506,"Unknown") | L10: =SUMIFS(Bets!$V$2:$V$506,Bets!$A$2:$A$506,"<>",Bets!$B$2:$B$506,"Steve",Bets!$H$2:$H$506,"Unknown") | M10: =IF(K10=0,"",L10/K10) | N10: =SUMIFS(Bets!$AD$2:$AD$506,Bets!$A$2:$A$506,"<>",Bets!$B$2:$B$506,"Steve",Bets!$H$2:$H$506,"Unknown") | O10: =SUMIFS(Bets!$W$2:$W$506,Bets!$A$2:$A$506,"<>",Bets!$B$2:$B$506,"Steve",Bets!$H$2:$H$506,"Unknown") | P10: =IF(N10=0,"",O10/N10)
A11: Combined | B11: Y | C11: =COUNTIFS(Bets!$A$2:$A$506,"<>",Bets!$B$2:$B$506,"*",Bets!$H$2:$H$506,"Y") | D11: =COUNTIFS(Bets!$A$2:$A$506,"<>",Bets!$B$2:$B$506,"*",Bets!$H$2:$H$506,"Y",Bets!$U$2:$U$506,"W") | E11: =COUNTIFS(Bets!$A$2:$A$506,"<>",Bets!$B$2:$B$506,"*",Bets!$H$2:$H$506,"Y",Bets!$U$2:$U$506,"L") | F11: =COUNTIFS(Bets!$A$2:$A$506,"<>",Bets!$B$2:$B$506,"*",Bets!$H$2:$H$506,"Y",Bets!$U$2:$U$506,"Push") | G11: =COUNTIFS(Bets!$A$2:$A$506,"<>",Bets!$B$2:$B$506,"*",Bets!$H$2:$H$506,"Y",Bets!$U$2:$U$506,"Pending") | H11: =COUNTIFS(Bets!$A$2:$A$506,"<>",Bets!$B$2:$B$506,"*",Bets!$H$2:$H$506,"Y",Bets!$U$2:$U$506,"Unknown") | I11: =IF(D11+E11=0,"",D11/(D11+E11)) | J11: =SUMIFS(Bets!$Q$2:$Q$506,Bets!$A$2:$A$506,"<>",Bets!$B$2:$B$506,"*",Bets!$H$2:$H$506,"Y") | K11: =SUMIFS(Bets!$AC$2:$AC$506,Bets!$A$2:$A$506,"<>",Bets!$B$2:$B$506,"*",Bets!$H$2:$H$506,"Y") | L11: =SUMIFS(Bets!$V$2:$V$506,Bets!$A$2:$A$506,"<>",Bets!$B$2:$B$506,"*",Bets!$H$2:$H$506,"Y") | M11: =IF(K11=0,"",L11/K11) | N11: =SUMIFS(Bets!$AD$2:$AD$506,Bets!$A$2:$A$506,"<>",Bets!$B$2:$B$506,"*",Bets!$H$2:$H$506,"Y") | O11: =SUMIFS(Bets!$W$2:$W$506,Bets!$A$2:$A$506,"<>",Bets!$B$2:$B$506,"*",Bets!$H$2:$H$506,"Y") | P11: =IF(N11=0,"",O11/N11)
A12: Combined | B12: N | C12: =COUNTIFS(Bets!$A$2:$A$506,"<>",Bets!$B$2:$B$506,"*",Bets!$H$2:$H$506,"N") | D12: =COUNTIFS(Bets!$A$2:$A$506,"<>",Bets!$B$2:$B$506,"*",Bets!$H$2:$H$506,"N",Bets!$U$2:$U$506,"W") | E12: =COUNTIFS(Bets!$A$2:$A$506,"<>",Bets!$B$2:$B$506,"*",Bets!$H$2:$H$506,"N",Bets!$U$2:$U$506,"L") | F12: =COUNTIFS(Bets!$A$2:$A$506,"<>",Bets!$B$2:$B$506,"*",Bets!$H$2:$H$506,"N",Bets!$U$2:$U$506,"Push") | G12: =COUNTIFS(Bets!$A$2:$A$506,"<>",Bets!$B$2:$B$506,"*",Bets!$H$2:$H$506,"N",Bets!$U$2:$U$506,"Pending") | H12: =COUNTIFS(Bets!$A$2:$A$506,"<>",Bets!$B$2:$B$506,"*",Bets!$H$2:$H$506,"N",Bets!$U$2:$U$506,"Unknown") | I12: =IF(D12+E12=0,"",D12/(D12+E12)) | J12: =SUMIFS(Bets!$Q$2:$Q$506,Bets!$A$2:$A$506,"<>",Bets!$B$2:$B$506,"*",Bets!$H$2:$H$506,"N") | K12: =SUMIFS(Bets!$AC$2:$AC$506,Bets!$A$2:$A$506,"<>",Bets!$B$2:$B$506,"*",Bets!$H$2:$H$506,"N") | L12: =SUMIFS(Bets!$V$2:$V$506,Bets!$A$2:$A$506,"<>",Bets!$B$2:$B$506,"*",Bets!$H$2:$H$506,"N") | M12: =IF(K12=0,"",L12/K12) | N12: =SUMIFS(Bets!$AD$2:$AD$506,Bets!$A$2:$A$506,"<>",Bets!$B$2:$B$506,"*",Bets!$H$2:$H$506,"N") | O12: =SUMIFS(Bets!$W$2:$W$506,Bets!$A$2:$A$506,"<>",Bets!$B$2:$B$506,"*",Bets!$H$2:$H$506,"N") | P12: =IF(N12=0,"",O12/N12)
A13: Combined | B13: Unknown | C13: =COUNTIFS(Bets!$A$2:$A$506,"<>",Bets!$B$2:$B$506,"*",Bets!$H$2:$H$506,"Unknown") | D13: =COUNTIFS(Bets!$A$2:$A$506,"<>",Bets!$B$2:$B$506,"*",Bets!$H$2:$H$506,"Unknown",Bets!$U$2:$U$506,"W") | E13: =COUNTIFS(Bets!$A$2:$A$506,"<>",Bets!$B$2:$B$506,"*",Bets!$H$2:$H$506,"Unknown",Bets!$U$2:$U$506,"L") | F13: =COUNTIFS(Bets!$A$2:$A$506,"<>",Bets!$B$2:$B$506,"*",Bets!$H$2:$H$506,"Unknown",Bets!$U$2:$U$506,"Push") | G13: =COUNTIFS(Bets!$A$2:$A$506,"<>",Bets!$B$2:$B$506,"*",Bets!$H$2:$H$506,"Unknown",Bets!$U$2:$U$506,"Pending") | H13: =COUNTIFS(Bets!$A$2:$A$506,"<>",Bets!$B$2:$B$506,"*",Bets!$H$2:$H$506,"Unknown",Bets!$U$2:$U$506,"Unknown") | I13: =IF(D13+E13=0,"",D13/(D13+E13)) | J13: =SUMIFS(Bets!$Q$2:$Q$506,Bets!$A$2:$A$506,"<>",Bets!$B$2:$B$506,"*",Bets!$H$2:$H$506,"Unknown") | K13: =SUMIFS(Bets!$AC$2:$AC$506,Bets!$A$2:$A$506,"<>",Bets!$B$2:$B$506,"*",Bets!$H$2:$H$506,"Unknown") | L13: =SUMIFS(Bets!$V$2:$V$506,Bets!$A$2:$A$506,"<>",Bets!$B$2:$B$506,"*",Bets!$H$2:$H$506,"Unknown") | M13: =IF(K13=0,"",L13/K13) | N13: =SUMIFS(Bets!$AD$2:$AD$506,Bets!$A$2:$A$506,"<>",Bets!$B$2:$B$506,"*",Bets!$H$2:$H$506,"Unknown") | O13: =SUMIFS(Bets!$W$2:$W$506,Bets!$A$2:$A$506,"<>",Bets!$B$2:$B$506,"*",Bets!$H$2:$H$506,"Unknown") | P13: =IF(N13=0,"",O13/N13)
A15: By prime-time slot
A16: Bettor | B16: Slot | C16: Bets | D16: W | E16: L | F16: Push | G16: Pending | H16: Unknown | I16: Win % (W/(W+L)) | J16: Total staked $ (all $ bets) | K16: Settled staked $ | L16: Net P/L $ | M16: ROI (net / settled $) | N16: Units staked (settled) | O16: Net units | P16: ROI (units)
A17: Trent (@BookitWithTrent) | B17: TNF | C17: =COUNTIFS(Bets!$A$2:$A$506,"<>",Bets!$B$2:$B$506,"Trent",Bets!$I$2:$I$506,"TNF") | D17: =COUNTIFS(Bets!$A$2:$A$506,"<>",Bets!$B$2:$B$506,"Trent",Bets!$I$2:$I$506,"TNF",Bets!$U$2:$U$506,"W") | E17: =COUNTIFS(Bets!$A$2:$A$506,"<>",Bets!$B$2:$B$506,"Trent",Bets!$I$2:$I$506,"TNF",Bets!$U$2:$U$506,"L") | F17: =COUNTIFS(Bets!$A$2:$A$506,"<>",Bets!$B$2:$B$506,"Trent",Bets!$I$2:$I$506,"TNF",Bets!$U$2:$U$506,"Push") | G17: =COUNTIFS(Bets!$A$2:$A$506,"<>",Bets!$B$2:$B$506,"Trent",Bets!$I$2:$I$506,"TNF",Bets!$U$2:$U$506,"Pending") | H17: =COUNTIFS(Bets!$A$2:$A$506,"<>",Bets!$B$2:$B$506,"Trent",Bets!$I$2:$I$506,"TNF",Bets!$U$2:$U$506,"Unknown") | I17: =IF(D17+E17=0,"",D17/(D17+E17)) | J17: =SUMIFS(Bets!$Q$2:$Q$506,Bets!$A$2:$A$506,"<>",Bets!$B$2:$B$506,"Trent",Bets!$I$2:$I$506,"TNF") | K17: =SUMIFS(Bets!$AC$2:$AC$506,Bets!$A$2:$A$506,"<>",Bets!$B$2:$B$506,"Trent",Bets!$I$2:$I$506,"TNF") | L17: =SUMIFS(Bets!$V$2:$V$506,Bets!$A$2:$A$506,"<>",Bets!$B$2:$B$506,"Trent",Bets!$I$2:$I$506,"TNF") | M17: =IF(K17=0,"",L17/K17) | N17: =SUMIFS(Bets!$AD$2:$AD$506,Bets!$A$2:$A$506,"<>",Bets!$B$2:$B$506,"Trent",Bets!$I$2:$I$506,"TNF") | O17: =SUMIFS(Bets!$W$2:$W$506,Bets!$A$2:$A$506,"<>",Bets!$B$2:$B$506,"Trent",Bets!$I$2:$I$506,"TNF") | P17: =IF(N17=0,"",O17/N17)
A18: Trent (@BookitWithTrent) | B18: SNF | C18: =COUNTIFS(Bets!$A$2:$A$506,"<>",Bets!$B$2:$B$506,"Trent",Bets!$I$2:$I$506,"SNF") | D18: =COUNTIFS(Bets!$A$2:$A$506,"<>",Bets!$B$2:$B$506,"Trent",Bets!$I$2:$I$506,"SNF",Bets!$U$2:$U$506,"W") | E18: =COUNTIFS(Bets!$A$2:$A$506,"<>",Bets!$B$2:$B$506,"Trent",Bets!$I$2:$I$506,"SNF",Bets!$U$2:$U$506,"L") | F18: =COUNTIFS(Bets!$A$2:$A$506,"<>",Bets!$B$2:$B$506,"Trent",Bets!$I$2:$I$506,"SNF",Bets!$U$2:$U$506,"Push") | G18: =COUNTIFS(Bets!$A$2:$A$506,"<>",Bets!$B$2:$B$506,"Trent",Bets!$I$2:$I$506,"SNF",Bets!$U$2:$U$506,"Pending") | H18: =COUNTIFS(Bets!$A$2:$A$506,"<>",Bets!$B$2:$B$506,"Trent",Bets!$I$2:$I$506,"SNF",Bets!$U$2:$U$506,"Unknown") | I18: =IF(D18+E18=0,"",D18/(D18+E18)) | J18: =SUMIFS(Bets!$Q$2:$Q$506,Bets!$A$2:$A$506,"<>",Bets!$B$2:$B$506,"Trent",Bets!$I$2:$I$506,"SNF") | K18: =SUMIFS(Bets!$AC$2:$AC$506,Bets!$A$2:$A$506,"<>",Bets!$B$2:$B$506,"Trent",Bets!$I$2:$I$506,"SNF") | L18: =SUMIFS(Bets!$V$2:$V$506,Bets!$A$2:$A$506,"<>",Bets!$B$2:$B$506,"Trent",Bets!$I$2:$I$506,"SNF") | M18: =IF(K18=0,"",L18/K18) | N18: =SUMIFS(Bets!$AD$2:$AD$506,Bets!$A$2:$A$506,"<>",Bets!$B$2:$B$506,"Trent",Bets!$I$2:$I$506,"SNF") | O18: =SUMIFS(Bets!$W$2:$W$506,Bets!$A$2:$A$506,"<>",Bets!$B$2:$B$506,"Trent",Bets!$I$2:$I$506,"SNF") | P18: =IF(N18=0,"",O18/N18)
A19: Trent (@BookitWithTrent) | B19: MNF | C19: =COUNTIFS(Bets!$A$2:$A$506,"<>",Bets!$B$2:$B$506,"Trent",Bets!$I$2:$I$506,"MNF") | D19: =COUNTIFS(Bets!$A$2:$A$506,"<>",Bets!$B$2:$B$506,"Trent",Bets!$I$2:$I$506,"MNF",Bets!$U$2:$U$506,"W") | E19: =COUNTIFS(Bets!$A$2:$A$506,"<>",Bets!$B$2:$B$506,"Trent",Bets!$I$2:$I$506,"MNF",Bets!$U$2:$U$506,"L") | F19: =COUNTIFS(Bets!$A$2:$A$506,"<>",Bets!$B$2:$B$506,"Trent",Bets!$I$2:$I$506,"MNF",Bets!$U$2:$U$506,"Push") | G19: =COUNTIFS(Bets!$A$2:$A$506,"<>",Bets!$B$2:$B$506,"Trent",Bets!$I$2:$I$506,"MNF",Bets!$U$2:$U$506,"Pending") | H19: =COUNTIFS(Bets!$A$2:$A$506,"<>",Bets!$B$2:$B$506,"Trent",Bets!$I$2:$I$506,"MNF",Bets!$U$2:$U$506,"Unknown") | I19: =IF(D19+E19=0,"",D19/(D19+E19)) | J19: =SUMIFS(Bets!$Q$2:$Q$506,Bets!$A$2:$A$506,"<>",Bets!$B$2:$B$506,"Trent",Bets!$I$2:$I$506,"MNF") | K19: =SUMIFS(Bets!$AC$2:$AC$506,Bets!$A$2:$A$506,"<>",Bets!$B$2:$B$506,"Trent",Bets!$I$2:$I$506,"MNF") | L19: =SUMIFS(Bets!$V$2:$V$506,Bets!$A$2:$A$506,"<>",Bets!$B$2:$B$506,"Trent",Bets!$I$2:$I$506,"MNF") | M19: =IF(K19=0,"",L19/K19) | N19: =SUMIFS(Bets!$AD$2:$AD$506,Bets!$A$2:$A$506,"<>",Bets!$B$2:$B$506,"Trent",Bets!$I$2:$I$506,"MNF") | O19: =SUMIFS(Bets!$W$2:$W$506,Bets!$A$2:$A$506,"<>",Bets!$B$2:$B$506,"Trent",Bets!$I$2:$I$506,"MNF") | P19: =IF(N19=0,"",O19/N19)
A20: Trent (@BookitWithTrent) | B20: NFL primetime (other day) | C20: =COUNTIFS(Bets!$A$2:$A$506,"<>",Bets!$B$2:$B$506,"Trent",Bets!$I$2:$I$506,"NFL primetime (other day)") | D20: =COUNTIFS(Bets!$A$2:$A$506,"<>",Bets!$B$2:$B$506,"Trent",Bets!$I$2:$I$506,"NFL primetime (other day)",Bets!$U$2:$U$506,"W") | E20: =COUNTIFS(Bets!$A$2:$A$506,"<>",Bets!$B$2:$B$506,"Trent",Bets!$I$2:$I$506,"NFL primetime (other day)",Bets!$U$2:$U$506,"L") | F20: =COUNTIFS(Bets!$A$2:$A$506,"<>",Bets!$B$2:$B$506,"Trent",Bets!$I$2:$I$506,"NFL primetime (other day)",Bets!$U$2:$U$506,"Push") | G20: =COUNTIFS(Bets!$A$2:$A$506,"<>",Bets!$B$2:$B$506,"Trent",Bets!$I$2:$I$506,"NFL primetime (other day)",Bets!$U$2:$U$506,"Pending") | H20: =COUNTIFS(Bets!$A$2:$A$506,"<>",Bets!$B$2:$B$506,"Trent",Bets!$I$2:$I$506,"NFL primetime (other day)",Bets!$U$2:$U$506,"Unknown") | I20: =IF(D20+E20=0,"",D20/(D20+E20)) | J20: =SUMIFS(Bets!$Q$2:$Q$506,Bets!$A$2:$A$506,"<>",Bets!$B$2:$B$506,"Trent",Bets!$I$2:$I$506,"NFL primetime (other day)") | K20: =SUMIFS(Bets!$AC$2:$AC$506,Bets!$A$2:$A$506,"<>",Bets!$B$2:$B$506,"Trent",Bets!$I$2:$I$506,"NFL primetime (other day)") | L20: =SUMIFS(Bets!$V$2:$V$506,Bets!$A$2:$A$506,"<>",Bets!$B$2:$B$506,"Trent",Bets!$I$2:$I$506,"NFL primetime (other day)") | M20: =IF(K20=0,"",L20/K20) | N20: =SUMIFS(Bets!$AD$2:$AD$506,Bets!$A$2:$A$506,"<>",Bets!$B$2:$B$506,"Trent",Bets!$I$2:$I$506,"NFL primetime (other day)") | O20: =SUMIFS(Bets!$W$2:$W$506,Bets!$A$2:$A$506,"<>",Bets!$B$2:$B$506,"Trent",Bets!$I$2:$I$506,"NFL primetime (other day)") | P20: =IF(N20=0,"",O20/N20)
A21: Trent (@BookitWithTrent) | B21: CFB Saturday night | C21: =COUNTIFS(Bets!$A$2:$A$506,"<>",Bets!$B$2:$B$506,"Trent",Bets!$I$2:$I$506,"CFB Saturday night") | D21: =COUNTIFS(Bets!$A$2:$A$506,"<>",Bets!$B$2:$B$506,"Trent",Bets!$I$2:$I$506,"CFB Saturday night",Bets!$U$2:$U$506,"W") | E21: =COUNTIFS(Bets!$A$2:$A$506,"<>",Bets!$B$2:$B$506,"Trent",Bets!$I$2:$I$506,"CFB Saturday night",Bets!$U$2:$U$506,"L") | F21: =COUNTIFS(Bets!$A$2:$A$506,"<>",Bets!$B$2:$B$506,"Trent",Bets!$I$2:$I$506,"CFB Saturday night",Bets!$U$2:$U$506,"Push") | G21: =COUNTIFS(Bets!$A$2:$A$506,"<>",Bets!$B$2:$B$506,"Trent",Bets!$I$2:$I$506,"CFB Saturday night",Bets!$U$2:$U$506,"Pending") | H21: =COUNTIFS(Bets!$A$2:$A$506,"<>",Bets!$B$2:$B$506,"Trent",Bets!$I$2:$I$506,"CFB Saturday night",Bets!$U$2:$U$506,"Unknown") | I21: =IF(D21+E21=0,"",D21/(D21+E21)) | J21: =SUMIFS(Bets!$Q$2:$Q$506,Bets!$A$2:$A$506,"<>",Bets!$B$2:$B$506,"Trent",Bets!$I$2:$I$506,"CFB Saturday night") | K21: =SUMIFS(Bets!$AC$2:$AC$506,Bets!$A$2:$A$506,"<>",Bets!$B$2:$B$506,"Trent",Bets!$I$2:$I$506,"CFB Saturday night") | L21: =SUMIFS(Bets!$V$2:$V$506,Bets!$A$2:$A$506,"<>",Bets!$B$2:$B$506,"Trent",Bets!$I$2:$I$506,"CFB Saturday night") | M21: =IF(K21=0,"",L21/K21) | N21: =SUMIFS(Bets!$AD$2:$AD$506,Bets!$A$2:$A$506,"<>",Bets!$B$2:$B$506,"Trent",Bets!$I$2:$I$506,"CFB Saturday night") | O21: =SUMIFS(Bets!$W$2:$W$506,Bets!$A$2:$A$506,"<>",Bets!$B$2:$B$506,"Trent",Bets!$I$2:$I$506,"CFB Saturday night") | P21: =IF(N21=0,"",O21/N21)
A22: Trent (@BookitWithTrent) | B22: CFB weeknight (Tue-Fri) | C22: =COUNTIFS(Bets!$A$2:$A$506,"<>",Bets!$B$2:$B$506,"Trent",Bets!$I$2:$I$506,"CFB weeknight (Tue-Fri)") | D22: =COUNTIFS(Bets!$A$2:$A$506,"<>",Bets!$B$2:$B$506,"Trent",Bets!$I$2:$I$506,"CFB weeknight (Tue-Fri)",Bets!$U$2:$U$506,"W") | E22: =COUNTIFS(Bets!$A$2:$A$506,"<>",Bets!$B$2:$B$506,"Trent",Bets!$I$2:$I$506,"CFB weeknight (Tue-Fri)",Bets!$U$2:$U$506,"L") | F22: =COUNTIFS(Bets!$A$2:$A$506,"<>",Bets!$B$2:$B$506,"Trent",Bets!$I$2:$I$506,"CFB weeknight (Tue-Fri)",Bets!$U$2:$U$506,"Push") | G22: =COUNTIFS(Bets!$A$2:$A$506,"<>",Bets!$B$2:$B$506,"Trent",Bets!$I$2:$I$506,"CFB weeknight (Tue-Fri)",Bets!$U$2:$U$506,"Pending") | H22: =COUNTIFS(Bets!$A$2:$A$506,"<>",Bets!$B$2:$B$506,"Trent",Bets!$I$2:$I$506,"CFB weeknight (Tue-Fri)",Bets!$U$2:$U$506,"Unknown") | I22: =IF(D22+E22=0,"",D22/(D22+E22)) | J22: =SUMIFS(Bets!$Q$2:$Q$506,Bets!$A$2:$A$506,"<>",Bets!$B$2:$B$506,"Trent",Bets!$I$2:$I$506,"CFB weeknight (Tue-Fri)") | K22: =SUMIFS(Bets!$AC$2:$AC$506,Bets!$A$2:$A$506,"<>",Bets!$B$2:$B$506,"Trent",Bets!$I$2:$I$506,"CFB weeknight (Tue-Fri)") | L22: =SUMIFS(Bets!$V$2:$V$506,Bets!$A$2:$A$506,"<>",Bets!$B$2:$B$506,"Trent",Bets!$I$2:$I$506,"CFB weeknight (Tue-Fri)") | M22: =IF(K22=0,"",L22/K22) | N22: =SUMIFS(Bets!$AD$2:$AD$506,Bets!$A$2:$A$506,"<>",Bets!$B$2:$B$506,"Trent",Bets!$I$2:$I$506,"CFB weeknight (Tue-Fri)") | O22: =SUMIFS(Bets!$W$2:$W$506,Bets!$A$2:$A$506,"<>",Bets!$B$2:$B$506,"Trent",Bets!$I$2:$I$506,"CFB weeknight (Tue-Fri)") | P22: =IF(N22=0,"",O22/N22)
A23: Trent (@BookitWithTrent) | B23: kickoff not matched | C23: =COUNTIFS(Bets!$A$2:$A$506,"<>",Bets!$B$2:$B$506,"Trent",Bets!$I$2:$I$506,"kickoff not matched") | D23: =COUNTIFS(Bets!$A$2:$A$506,"<>",Bets!$B$2:$B$506,"Trent",Bets!$I$2:$I$506,"kickoff not matched",Bets!$U$2:$U$506,"W") | E23: =COUNTIFS(Bets!$A$2:$A$506,"<>",Bets!$B$2:$B$506,"Trent",Bets!$I$2:$I$506,"kickoff not matched",Bets!$U$2:$U$506,"L") | F23: =COUNTIFS(Bets!$A$2:$A$506,"<>",Bets!$B$2:$B$506,"Trent",Bets!$I$2:$I$506,"kickoff not matched",Bets!$U$2:$U$506,"Push") | G23: =COUNTIFS(Bets!$A$2:$A$506,"<>",Bets!$B$2:$B$506,"Trent",Bets!$I$2:$I$506,"kickoff not matched",Bets!$U$2:$U$506,"Pending") | H23: =COUNTIFS(Bets!$A$2:$A$506,"<>",Bets!$B$2:$B$506,"Trent",Bets!$I$2:$I$506,"kickoff not matched",Bets!$U$2:$U$506,"Unknown") | I23: =IF(D23+E23=0,"",D23/(D23+E23)) | J23: =SUMIFS(Bets!$Q$2:$Q$506,Bets!$A$2:$A$506,"<>",Bets!$B$2:$B$506,"Trent",Bets!$I$2:$I$506,"kickoff not matched") | K23: =SUMIFS(Bets!$AC$2:$AC$506,Bets!$A$2:$A$506,"<>",Bets!$B$2:$B$506,"Trent",Bets!$I$2:$I$506,"kickoff not matched") | L23: =SUMIFS(Bets!$V$2:$V$506,Bets!$A$2:$A$506,"<>",Bets!$B$2:$B$506,"Trent",Bets!$I$2:$I$506,"kickoff not matched") | M23: =IF(K23=0,"",L23/K23) | N23: =SUMIFS(Bets!$AD$2:$AD$506,Bets!$A$2:$A$506,"<>",Bets!$B$2:$B$506,"Trent",Bets!$I$2:$I$506,"kickoff not matched") | O23: =SUMIFS(Bets!$W$2:$W$506,Bets!$A$2:$A$506,"<>",Bets!$B$2:$B$506,"Trent",Bets!$I$2:$I$506,"kickoff not matched") | P23: =IF(N23=0,"",O23/N23)
A24: Steve (@stevewilldoit) | B24: TNF | C24: =COUNTIFS(Bets!$A$2:$A$506,"<>",Bets!$B$2:$B$506,"Steve",Bets!$I$2:$I$506,"TNF") | D24: =COUNTIFS(Bets!$A$2:$A$506,"<>",Bets!$B$2:$B$506,"Steve",Bets!$I$2:$I$506,"TNF",Bets!$U$2:$U$506,"W") | E24: =COUNTIFS(Bets!$A$2:$A$506,"<>",Bets!$B$2:$B$506,"Steve",Bets!$I$2:$I$506,"TNF",Bets!$U$2:$U$506,"L") | F24: =COUNTIFS(Bets!$A$2:$A$506,"<>",Bets!$B$2:$B$506,"Steve",Bets!$I$2:$I$506,"TNF",Bets!$U$2:$U$506,"Push") | G24: =COUNTIFS(Bets!$A$2:$A$506,"<>",Bets!$B$2:$B$506,"Steve",Bets!$I$2:$I$506,"TNF",Bets!$U$2:$U$506,"Pending") | H24: =COUNTIFS(Bets!$A$2:$A$506,"<>",Bets!$B$2:$B$506,"Steve",Bets!$I$2:$I$506,"TNF",Bets!$U$2:$U$506,"Unknown") | I24: =IF(D24+E24=0,"",D24/(D24+E24)) | J24: =SUMIFS(Bets!$Q$2:$Q$506,Bets!$A$2:$A$506,"<>",Bets!$B$2:$B$506,"Steve",Bets!$I$2:$I$506,"TNF") | K24: =SUMIFS(Bets!$AC$2:$AC$506,Bets!$A$2:$A$506,"<>",Bets!$B$2:$B$506,"Steve",Bets!$I$2:$I$506,"TNF") | L24: =SUMIFS(Bets!$V$2:$V$506,Bets!$A$2:$A$506,"<>",Bets!$B$2:$B$506,"Steve",Bets!$I$2:$I$506,"TNF") | M24: =IF(K24=0,"",L24/K24) | N24: =SUMIFS(Bets!$AD$2:$AD$506,Bets!$A$2:$A$506,"<>",Bets!$B$2:$B$506,"Steve",Bets!$I$2:$I$506,"TNF") | O24: =SUMIFS(Bets!$W$2:$W$506,Bets!$A$2:$A$506,"<>",Bets!$B$2:$B$506,"Steve",Bets!$I$2:$I$506,"TNF") | P24: =IF(N24=0,"",O24/N24)
A25: Steve (@stevewilldoit) | B25: SNF | C25: =COUNTIFS(Bets!$A$2:$A$506,"<>",Bets!$B$2:$B$506,"Steve",Bets!$I$2:$I$506,"SNF") | D25: =COUNTIFS(Bets!$A$2:$A$506,"<>",Bets!$B$2:$B$506,"Steve",Bets!$I$2:$I$506,"SNF",Bets!$U$2:$U$506,"W") | E25: =COUNTIFS(Bets!$A$2:$A$506,"<>",Bets!$B$2:$B$506,"Steve",Bets!$I$2:$I$506,"SNF",Bets!$U$2:$U$506,"L") | F25: =COUNTIFS(Bets!$A$2:$A$506,"<>",Bets!$B$2:$B$506,"Steve",Bets!$I$2:$I$506,"SNF",Bets!$U$2:$U$506,"Push") | G25: =COUNTIFS(Bets!$A$2:$A$506,"<>",Bets!$B$2:$B$506,"Steve",Bets!$I$2:$I$506,"SNF",Bets!$U$2:$U$506,"Pending") | H25: =COUNTIFS(Bets!$A$2:$A$506,"<>",Bets!$B$2:$B$506,"Steve",Bets!$I$2:$I$506,"SNF",Bets!$U$2:$U$506,"Unknown") | I25: =IF(D25+E25=0,"",D25/(D25+E25)) | J25: =SUMIFS(Bets!$Q$2:$Q$506,Bets!$A$2:$A$506,"<>",Bets!$B$2:$B$506,"Steve",Bets!$I$2:$I$506,"SNF") | K25: =SUMIFS(Bets!$AC$2:$AC$506,Bets!$A$2:$A$506,"<>",Bets!$B$2:$B$506,"Steve",Bets!$I$2:$I$506,"SNF") | L25: =SUMIFS(Bets!$V$2:$V$506,Bets!$A$2:$A$506,"<>",Bets!$B$2:$B$506,"Steve",Bets!$I$2:$I$506,"SNF") | M25: =IF(K25=0,"",L25/K25) | N25: =SUMIFS(Bets!$AD$2:$AD$506,Bets!$A$2:$A$506,"<>",Bets!$B$2:$B$506,"Steve",Bets!$I$2:$I$506,"SNF") | O25: =SUMIFS(Bets!$W$2:$W$506,Bets!$A$2:$A$506,"<>",Bets!$B$2:$B$506,"Steve",Bets!$I$2:$I$506,"SNF") | P25: =IF(N25=0,"",O25/N25)
A26: Steve (@stevewilldoit) | B26: MNF | C26: =COUNTIFS(Bets!$A$2:$A$506,"<>",Bets!$B$2:$B$506,"Steve",Bets!$I$2:$I$506,"MNF") | D26: =COUNTIFS(Bets!$A$2:$A$506,"<>",Bets!$B$2:$B$506,"Steve",Bets!$I$2:$I$506,"MNF",Bets!$U$2:$U$506,"W") | E26: =COUNTIFS(Bets!$A$2:$A$506,"<>",Bets!$B$2:$B$506,"Steve",Bets!$I$2:$I$506,"MNF",Bets!$U$2:$U$506,"L") | F26: =COUNTIFS(Bets!$A$2:$A$506,"<>",Bets!$B$2:$B$506,"Steve",Bets!$I$2:$I$506,"MNF",Bets!$U$2:$U$506,"Push") | G26: =COUNTIFS(Bets!$A$2:$A$506,"<>",Bets!$B$2:$B$506,"Steve",Bets!$I$2:$I$506,"MNF",Bets!$U$2:$U$506,"Pending") | H26: =COUNTIFS(Bets!$A$2:$A$506,"<>",Bets!$B$2:$B$506,"Steve",Bets!$I$2:$I$506,"MNF",Bets!$U$2:$U$506,"Unknown") | I26: =IF(D26+E26=0,"",D26/(D26+E26)) | J26: =SUMIFS(Bets!$Q$2:$Q$506,Bets!$A$2:$A$506,"<>",Bets!$B$2:$B$506,"Steve",Bets!$I$2:$I$506,"MNF") | K26: =SUMIFS(Bets!$AC$2:$AC$506,Bets!$A$2:$A$506,"<>",Bets!$B$2:$B$506,"Steve",Bets!$I$2:$I$506,"MNF") | L26: =SUMIFS(Bets!$V$2:$V$506,Bets!$A$2:$A$506,"<>",Bets!$B$2:$B$506,"Steve",Bets!$I$2:$I$506,"MNF") | M26: =IF(K26=0,"",L26/K26) | N26: =SUMIFS(Bets!$AD$2:$AD$506,Bets!$A$2:$A$506,"<>",Bets!$B$2:$B$506,"Steve",Bets!$I$2:$I$506,"MNF") | O26: =SUMIFS(Bets!$W$2:$W$506,Bets!$A$2:$A$506,"<>",Bets!$B$2:$B$506,"Steve",Bets!$I$2:$I$506,"MNF") | P26: =IF(N26=0,"",O26/N26)
A27: Steve (@stevewilldoit) | B27: NFL primetime (other day) | C27: =COUNTIFS(Bets!$A$2:$A$506,"<>",Bets!$B$2:$B$506,"Steve",Bets!$I$2:$I$506,"NFL primetime (other day)") | D27: =COUNTIFS(Bets!$A$2:$A$506,"<>",Bets!$B$2:$B$506,"Steve",Bets!$I$2:$I$506,"NFL primetime (other day)",Bets!$U$2:$U$506,"W") | E27: =COUNTIFS(Bets!$A$2:$A$506,"<>",Bets!$B$2:$B$506,"Steve",Bets!$I$2:$I$506,"NFL primetime (other day)",Bets!$U$2:$U$506,"L") | F27: =COUNTIFS(Bets!$A$2:$A$506,"<>",Bets!$B$2:$B$506,"Steve",Bets!$I$2:$I$506,"NFL primetime (other day)",Bets!$U$2:$U$506,"Push") | G27: =COUNTIFS(Bets!$A$2:$A$506,"<>",Bets!$B$2:$B$506,"Steve",Bets!$I$2:$I$506,"NFL primetime (other day)",Bets!$U$2:$U$506,"Pending") | H27: =COUNTIFS(Bets!$A$2:$A$506,"<>",Bets!$B$2:$B$506,"Steve",Bets!$I$2:$I$506,"NFL primetime (other day)",Bets!$U$2:$U$506,"Unknown") | I27: =IF(D27+E27=0,"",D27/(D27+E27)) | J27: =SUMIFS(Bets!$Q$2:$Q$506,Bets!$A$2:$A$506,"<>",Bets!$B$2:$B$506,"Steve",Bets!$I$2:$I$506,"NFL primetime (other day)") | K27: =SUMIFS(Bets!$AC$2:$AC$506,Bets!$A$2:$A$506,"<>",Bets!$B$2:$B$506,"Steve",Bets!$I$2:$I$506,"NFL primetime (other day)") | L27: =SUMIFS(Bets!$V$2:$V$506,Bets!$A$2:$A$506,"<>",Bets!$B$2:$B$506,"Steve",Bets!$I$2:$I$506,"NFL primetime (other day)") | M27: =IF(K27=0,"",L27/K27) | N27: =SUMIFS(Bets!$AD$2:$AD$506,Bets!$A$2:$A$506,"<>",Bets!$B$2:$B$506,"Steve",Bets!$I$2:$I$506,"NFL primetime (other day)") | O27: =SUMIFS(Bets!$W$2:$W$506,Bets!$A$2:$A$506,"<>",Bets!$B$2:$B$506,"Steve",Bets!$I$2:$I$506,"NFL primetime (other day)") | P27: =IF(N27=0,"",O27/N27)
A28: Steve (@stevewilldoit) | B28: CFB Saturday night | C28: =COUNTIFS(Bets!$A$2:$A$506,"<>",Bets!$B$2:$B$506,"Steve",Bets!$I$2:$I$506,"CFB Saturday night") | D28: =COUNTIFS(Bets!$A$2:$A$506,"<>",Bets!$B$2:$B$506,"Steve",Bets!$I$2:$I$506,"CFB Saturday night",Bets!$U$2:$U$506,"W") | E28: =COUNTIFS(Bets!$A$2:$A$506,"<>",Bets!$B$2:$B$506,"Steve",Bets!$I$2:$I$506,"CFB Saturday night",Bets!$U$2:$U$506,"L") | F28: =COUNTIFS(Bets!$A$2:$A$506,"<>",Bets!$B$2:$B$506,"Steve",Bets!$I$2:$I$506,"CFB Saturday night",Bets!$U$2:$U$506,"Push") | G28: =COUNTIFS(Bets!$A$2:$A$506,"<>",Bets!$B$2:$B$506,"Steve",Bets!$I$2:$I$506,"CFB Saturday night",Bets!$U$2:$U$506,"Pending") | H28: =COUNTIFS(Bets!$A$2:$A$506,"<>",Bets!$B$2:$B$506,"Steve",Bets!$I$2:$I$506,"CFB Saturday night",Bets!$U$2:$U$506,"Unknown") | I28: =IF(D28+E28=0,"",D28/(D28+E28)) | J28: =SUMIFS(Bets!$Q$2:$Q$506,Bets!$A$2:$A$506,"<>",Bets!$B$2:$B$506,"Steve",Bets!$I$2:$I$506,"CFB Saturday night") | K28: =SUMIFS(Bets!$AC$2:$AC$506,Bets!$A$2:$A$506,"<>",Bets!$B$2:$B$506,"Steve",Bets!$I$2:$I$506,"CFB Saturday night") | L28: =SUMIFS(Bets!$V$2:$V$506,Bets!$A$2:$A$506,"<>",Bets!$B$2:$B$506,"Steve",Bets!$I$2:$I$506,"CFB Saturday night") | M28: =IF(K28=0,"",L28/K28) | N28: =SUMIFS(Bets!$AD$2:$AD$506,Bets!$A$2:$A$506,"<>",Bets!$B$2:$B$506,"Steve",Bets!$I$2:$I$506,"CFB Saturday night") | O28: =SUMIFS(Bets!$W$2:$W$506,Bets!$A$2:$A$506,"<>",Bets!$B$2:$B$506,"Steve",Bets!$I$2:$I$506,"CFB Saturday night") | P28: =IF(N28=0,"",O28/N28)
A29: Steve (@stevewilldoit) | B29: CFB weeknight (Tue-Fri) | C29: =COUNTIFS(Bets!$A$2:$A$506,"<>",Bets!$B$2:$B$506,"Steve",Bets!$I$2:$I$506,"CFB weeknight (Tue-Fri)") | D29: =COUNTIFS(Bets!$A$2:$A$506,"<>",Bets!$B$2:$B$506,"Steve",Bets!$I$2:$I$506,"CFB weeknight (Tue-Fri)",Bets!$U$2:$U$506,"W") | E29: =COUNTIFS(Bets!$A$2:$A$506,"<>",Bets!$B$2:$B$506,"Steve",Bets!$I$2:$I$506,"CFB weeknight (Tue-Fri)",Bets!$U$2:$U$506,"L") | F29: =COUNTIFS(Bets!$A$2:$A$506,"<>",Bets!$B$2:$B$506,"Steve",Bets!$I$2:$I$506,"CFB weeknight (Tue-Fri)",Bets!$U$2:$U$506,"Push") | G29: =COUNTIFS(Bets!$A$2:$A$506,"<>",Bets!$B$2:$B$506,"Steve",Bets!$I$2:$I$506,"CFB weeknight (Tue-Fri)",Bets!$U$2:$U$506,"Pending") | H29: =COUNTIFS(Bets!$A$2:$A$506,"<>",Bets!$B$2:$B$506,"Steve",Bets!$I$2:$I$506,"CFB weeknight (Tue-Fri)",Bets!$U$2:$U$506,"Unknown") | I29: =IF(D29+E29=0,"",D29/(D29+E29)) | J29: =SUMIFS(Bets!$Q$2:$Q$506,Bets!$A$2:$A$506,"<>",Bets!$B$2:$B$506,"Steve",Bets!$I$2:$I$506,"CFB weeknight (Tue-Fri)") | K29: =SUMIFS(Bets!$AC$2:$AC$506,Bets!$A$2:$A$506,"<>",Bets!$B$2:$B$506,"Steve",Bets!$I$2:$I$506,"CFB weeknight (Tue-Fri)") | L29: =SUMIFS(Bets!$V$2:$V$506,Bets!$A$2:$A$506,"<>",Bets!$B$2:$B$506,"Steve",Bets!$I$2:$I$506,"CFB weeknight (Tue-Fri)") | M29: =IF(K29=0,"",L29/K29) | N29: =SUMIFS(Bets!$AD$2:$AD$506,Bets!$A$2:$A$506,"<>",Bets!$B$2:$B$506,"Steve",Bets!$I$2:$I$506,"CFB weeknight (Tue-Fri)") | O29: =SUMIFS(Bets!$W$2:$W$506,Bets!$A$2:$A$506,"<>",Bets!$B$2:$B$506,"Steve",Bets!$I$2:$I$506,"CFB weeknight (Tue-Fri)") | P29: =IF(N29=0,"",O29/N29)
A30: Steve (@stevewilldoit) | B30: kickoff not matched | C30: =COUNTIFS(Bets!$A$2:$A$506,"<>",Bets!$B$2:$B$506,"Steve",Bets!$I$2:$I$506,"kickoff not matched") | D30: =COUNTIFS(Bets!$A$2:$A$506,"<>",Bets!$B$2:$B$506,"Steve",Bets!$I$2:$I$506,"kickoff not matched",Bets!$U$2:$U$506,"W") | E30: =COUNTIFS(Bets!$A$2:$A$506,"<>",Bets!$B$2:$B$506,"Steve",Bets!$I$2:$I$506,"kickoff not matched",Bets!$U$2:$U$506,"L") | F30: =COUNTIFS(Bets!$A$2:$A$506,"<>",Bets!$B$2:$B$506,"Steve",Bets!$I$2:$I$506,"kickoff not matched",Bets!$U$2:$U$506,"Push") | G30: =COUNTIFS(Bets!$A$2:$A$506,"<>",Bets!$B$2:$B$506,"Steve",Bets!$I$2:$I$506,"kickoff not matched",Bets!$U$2:$U$506,"Pending") | H30: =COUNTIFS(Bets!$A$2:$A$506,"<>",Bets!$B$2:$B$506,"Steve",Bets!$I$2:$I$506,"kickoff not matched",Bets!$U$2:$U$506,"Unknown") | I30: =IF(D30+E30=0,"",D30/(D30+E30)) | J30: =SUMIFS(Bets!$Q$2:$Q$506,Bets!$A$2:$A$506,"<>",Bets!$B$2:$B$506,"Steve",Bets!$I$2:$I$506,"kickoff not matched") | K30: =SUMIFS(Bets!$AC$2:$AC$506,Bets!$A$2:$A$506,"<>",Bets!$B$2:$B$506,"Steve",Bets!$I$2:$I$506,"kickoff not matched") | L30: =SUMIFS(Bets!$V$2:$V$506,Bets!$A$2:$A$506,"<>",Bets!$B$2:$B$506,"Steve",Bets!$I$2:$I$506,"kickoff not matched") | M30: =IF(K30=0,"",L30/K30) | N30: =SUMIFS(Bets!$AD$2:$AD$506,Bets!$A$2:$A$506,"<>",Bets!$B$2:$B$506,"Steve",Bets!$I$2:$I$506,"kickoff not matched") | O30: =SUMIFS(Bets!$W$2:$W$506,Bets!$A$2:$A$506,"<>",Bets!$B$2:$B$506,"Steve",Bets!$I$2:$I$506,"kickoff not matched") | P30: =IF(N30=0,"",O30/N30)
A31: Combined | B31: TNF | C31: =COUNTIFS(Bets!$A$2:$A$506,"<>",Bets!$B$2:$B$506,"*",Bets!$I$2:$I$506,"TNF") | D31: =COUNTIFS(Bets!$A$2:$A$506,"<>",Bets!$B$2:$B$506,"*",Bets!$I$2:$I$506,"TNF",Bets!$U$2:$U$506,"W") | E31: =COUNTIFS(Bets!$A$2:$A$506,"<>",Bets!$B$2:$B$506,"*",Bets!$I$2:$I$506,"TNF",Bets!$U$2:$U$506,"L") | F31: =COUNTIFS(Bets!$A$2:$A$506,"<>",Bets!$B$2:$B$506,"*",Bets!$I$2:$I$506,"TNF",Bets!$U$2:$U$506,"Push") | G31: =COUNTIFS(Bets!$A$2:$A$506,"<>",Bets!$B$2:$B$506,"*",Bets!$I$2:$I$506,"TNF",Bets!$U$2:$U$506,"Pending") | H31: =COUNTIFS(Bets!$A$2:$A$506,"<>",Bets!$B$2:$B$506,"*",Bets!$I$2:$I$506,"TNF",Bets!$U$2:$U$506,"Unknown") | I31: =IF(D31+E31=0,"",D31/(D31+E31)) | J31: =SUMIFS(Bets!$Q$2:$Q$506,Bets!$A$2:$A$506,"<>",Bets!$B$2:$B$506,"*",Bets!$I$2:$I$506,"TNF") | K31: =SUMIFS(Bets!$AC$2:$AC$506,Bets!$A$2:$A$506,"<>",Bets!$B$2:$B$506,"*",Bets!$I$2:$I$506,"TNF") | L31: =SUMIFS(Bets!$V$2:$V$506,Bets!$A$2:$A$506,"<>",Bets!$B$2:$B$506,"*",Bets!$I$2:$I$506,"TNF") | M31: =IF(K31=0,"",L31/K31) | N31: =SUMIFS(Bets!$AD$2:$AD$506,Bets!$A$2:$A$506,"<>",Bets!$B$2:$B$506,"*",Bets!$I$2:$I$506,"TNF") | O31: =SUMIFS(Bets!$W$2:$W$506,Bets!$A$2:$A$506,"<>",Bets!$B$2:$B$506,"*",Bets!$I$2:$I$506,"TNF") | P31: =IF(N31=0,"",O31/N31)
A32: Combined | B32: SNF | C32: =COUNTIFS(Bets!$A$2:$A$506,"<>",Bets!$B$2:$B$506,"*",Bets!$I$2:$I$506,"SNF") | D32: =COUNTIFS(Bets!$A$2:$A$506,"<>",Bets!$B$2:$B$506,"*",Bets!$I$2:$I$506,"SNF",Bets!$U$2:$U$506,"W") | E32: =COUNTIFS(Bets!$A$2:$A$506,"<>",Bets!$B$2:$B$506,"*",Bets!$I$2:$I$506,"SNF",Bets!$U$2:$U$506,"L") | F32: =COUNTIFS(Bets!$A$2:$A$506,"<>",Bets!$B$2:$B$506,"*",Bets!$I$2:$I$506,"SNF",Bets!$U$2:$U$506,"Push") | G32: =COUNTIFS(Bets!$A$2:$A$506,"<>",Bets!$B$2:$B$506,"*",Bets!$I$2:$I$506,"SNF",Bets!$U$2:$U$506,"Pending") | H32: =COUNTIFS(Bets!$A$2:$A$506,"<>",Bets!$B$2:$B$506,"*",Bets!$I$2:$I$506,"SNF",Bets!$U$2:$U$506,"Unknown") | I32: =IF(D32+E32=0,"",D32/(D32+E32)) | J32: =SUMIFS(Bets!$Q$2:$Q$506,Bets!$A$2:$A$506,"<>",Bets!$B$2:$B$506,"*",Bets!$I$2:$I$506,"SNF") | K32: =SUMIFS(Bets!$AC$2:$AC$506,Bets!$A$2:$A$506,"<>",Bets!$B$2:$B$506,"*",Bets!$I$2:$I$506,"SNF") | L32: =SUMIFS(Bets!$V$2:$V$506,Bets!$A$2:$A$506,"<>",Bets!$B$2:$B$506,"*",Bets!$I$2:$I$506,"SNF") | M32: =IF(K32=0,"",L32/K32) | N32: =SUMIFS(Bets!$AD$2:$AD$506,Bets!$A$2:$A$506,"<>",Bets!$B$2:$B$506,"*",Bets!$I$2:$I$506,"SNF") | O32: =SUMIFS(Bets!$W$2:$W$506,Bets!$A$2:$A$506,"<>",Bets!$B$2:$B$506,"*",Bets!$I$2:$I$506,"SNF") | P32: =IF(N32=0,"",O32/N32)
A33: Combined | B33: MNF | C33: =COUNTIFS(Bets!$A$2:$A$506,"<>",Bets!$B$2:$B$506,"*",Bets!$I$2:$I$506,"MNF") | D33: =COUNTIFS(Bets!$A$2:$A$506,"<>",Bets!$B$2:$B$506,"*",Bets!$I$2:$I$506,"MNF",Bets!$U$2:$U$506,"W") | E33: =COUNTIFS(Bets!$A$2:$A$506,"<>",Bets!$B$2:$B$506,"*",Bets!$I$2:$I$506,"MNF",Bets!$U$2:$U$506,"L") | F33: =COUNTIFS(Bets!$A$2:$A$506,"<>",Bets!$B$2:$B$506,"*",Bets!$I$2:$I$506,"MNF",Bets!$U$2:$U$506,"Push") | G33: =COUNTIFS(Bets!$A$2:$A$506,"<>",Bets!$B$2:$B$506,"*",Bets!$I$2:$I$506,"MNF",Bets!$U$2:$U$506,"Pending") | H33: =COUNTIFS(Bets!$A$2:$A$506,"<>",Bets!$B$2:$B$506,"*",Bets!$I$2:$I$506,"MNF",Bets!$U$2:$U$506,"Unknown") | I33: =IF(D33+E33=0,"",D33/(D33+E33)) | J33: =SUMIFS(Bets!$Q$2:$Q$506,Bets!$A$2:$A$506,"<>",Bets!$B$2:$B$506,"*",Bets!$I$2:$I$506,"MNF") | K33: =SUMIFS(Bets!$AC$2:$AC$506,Bets!$A$2:$A$506,"<>",Bets!$B$2:$B$506,"*",Bets!$I$2:$I$506,"MNF") | L33: =SUMIFS(Bets!$V$2:$V$506,Bets!$A$2:$A$506,"<>",Bets!$B$2:$B$506,"*",Bets!$I$2:$I$506,"MNF") | M33: =IF(K33=0,"",L33/K33) | N33: =SUMIFS(Bets!$AD$2:$AD$506,Bets!$A$2:$A$506,"<>",Bets!$B$2:$B$506,"*",Bets!$I$2:$I$506,"MNF") | O33: =SUMIFS(Bets!$W$2:$W$506,Bets!$A$2:$A$506,"<>",Bets!$B$2:$B$506,"*",Bets!$I$2:$I$506,"MNF") | P33: =IF(N33=0,"",O33/N33)
A34: Combined | B34: NFL primetime (other day) | C34: =COUNTIFS(Bets!$A$2:$A$506,"<>",Bets!$B$2:$B$506,"*",Bets!$I$2:$I$506,"NFL primetime (other day)") | D34: =COUNTIFS(Bets!$A$2:$A$506,"<>",Bets!$B$2:$B$506,"*",Bets!$I$2:$I$506,"NFL primetime (other day)",Bets!$U$2:$U$506,"W") | E34: =COUNTIFS(Bets!$A$2:$A$506,"<>",Bets!$B$2:$B$506,"*",Bets!$I$2:$I$506,"NFL primetime (other day)",Bets!$U$2:$U$506,"L") | F34: =COUNTIFS(Bets!$A$2:$A$506,"<>",Bets!$B$2:$B$506,"*",Bets!$I$2:$I$506,"NFL primetime (other day)",Bets!$U$2:$U$506,"Push") | G34: =COUNTIFS(Bets!$A$2:$A$506,"<>",Bets!$B$2:$B$506,"*",Bets!$I$2:$I$506,"NFL primetime (other day)",Bets!$U$2:$U$506,"Pending") | H34: =COUNTIFS(Bets!$A$2:$A$506,"<>",Bets!$B$2:$B$506,"*",Bets!$I$2:$I$506,"NFL primetime (other day)",Bets!$U$2:$U$506,"Unknown") | I34: =IF(D34+E34=0,"",D34/(D34+E34)) | J34: =SUMIFS(Bets!$Q$2:$Q$506,Bets!$A$2:$A$506,"<>",Bets!$B$2:$B$506,"*",Bets!$I$2:$I$506,"NFL primetime (other day)") | K34: =SUMIFS(Bets!$AC$2:$AC$506,Bets!$A$2:$A$506,"<>",Bets!$B$2:$B$506,"*",Bets!$I$2:$I$506,"NFL primetime (other day)") | L34: =SUMIFS(Bets!$V$2:$V$506,Bets!$A$2:$A$506,"<>",Bets!$B$2:$B$506,"*",Bets!$I$2:$I$506,"NFL primetime (other day)") | M34: =IF(K34=0,"",L34/K34) | N34: =SUMIFS(Bets!$AD$2:$AD$506,Bets!$A$2:$A$506,"<>",Bets!$B$2:$B$506,"*",Bets!$I$2:$I$506,"NFL primetime (other day)") | O34: =SUMIFS(Bets!$W$2:$W$506,Bets!$A$2:$A$506,"<>",Bets!$B$2:$B$506,"*",Bets!$I$2:$I$506,"NFL primetime (other day)") | P34: =IF(N34=0,"",O34/N34)
A35: Combined | B35: CFB Saturday night | C35: =COUNTIFS(Bets!$A$2:$A$506,"<>",Bets!$B$2:$B$506,"*",Bets!$I$2:$I$506,"CFB Saturday night") | D35: =COUNTIFS(Bets!$A$2:$A$506,"<>",Bets!$B$2:$B$506,"*",Bets!$I$2:$I$506,"CFB Saturday night",Bets!$U$2:$U$506,"W") | E35: =COUNTIFS(Bets!$A$2:$A$506,"<>",Bets!$B$2:$B$506,"*",Bets!$I$2:$I$506,"CFB Saturday night",Bets!$U$2:$U$506,"L") | F35: =COUNTIFS(Bets!$A$2:$A$506,"<>",Bets!$B$2:$B$506,"*",Bets!$I$2:$I$506,"CFB Saturday night",Bets!$U$2:$U$506,"Push") | G35: =COUNTIFS(Bets!$A$2:$A$506,"<>",Bets!$B$2:$B$506,"*",Bets!$I$2:$I$506,"CFB Saturday night",Bets!$U$2:$U$506,"Pending") | H35: =COUNTIFS(Bets!$A$2:$A$506,"<>",Bets!$B$2:$B$506,"*",Bets!$I$2:$I$506,"CFB Saturday night",Bets!$U$2:$U$506,"Unknown") | I35: =IF(D35+E35=0,"",D35/(D35+E35)) | J35: =SUMIFS(Bets!$Q$2:$Q$506,Bets!$A$2:$A$506,"<>",Bets!$B$2:$B$506,"*",Bets!$I$2:$I$506,"CFB Saturday night") | K35: =SUMIFS(Bets!$AC$2:$AC$506,Bets!$A$2:$A$506,"<>",Bets!$B$2:$B$506,"*",Bets!$I$2:$I$506,"CFB Saturday night") | L35: =SUMIFS(Bets!$V$2:$V$506,Bets!$A$2:$A$506,"<>",Bets!$B$2:$B$506,"*",Bets!$I$2:$I$506,"CFB Saturday night") | M35: =IF(K35=0,"",L35/K35) | N35: =SUMIFS(Bets!$AD$2:$AD$506,Bets!$A$2:$A$506,"<>",Bets!$B$2:$B$506,"*",Bets!$I$2:$I$506,"CFB Saturday night") | O35: =SUMIFS(Bets!$W$2:$W$506,Bets!$A$2:$A$506,"<>",Bets!$B$2:$B$506,"*",Bets!$I$2:$I$506,"CFB Saturday night") | P35: =IF(N35=0,"",O35/N35)
A36: Combined | B36: CFB weeknight (Tue-Fri) | C36: =COUNTIFS(Bets!$A$2:$A$506,"<>",Bets!$B$2:$B$506,"*",Bets!$I$2:$I$506,"CFB weeknight (Tue-Fri)") | D36: =COUNTIFS(Bets!$A$2:$A$506,"<>",Bets!$B$2:$B$506,"*",Bets!$I$2:$I$506,"CFB weeknight (Tue-Fri)",Bets!$U$2:$U$506,"W") | E36: =COUNTIFS(Bets!$A$2:$A$506,"<>",Bets!$B$2:$B$506,"*",Bets!$I$2:$I$506,"CFB weeknight (Tue-Fri)",Bets!$U$2:$U$506,"L") | F36: =COUNTIFS(Bets!$A$2:$A$506,"<>",Bets!$B$2:$B$506,"*",Bets!$I$2:$I$506,"CFB weeknight (Tue-Fri)",Bets!$U$2:$U$506,"Push") | G36: =COUNTIFS(Bets!$A$2:$A$506,"<>",Bets!$B$2:$B$506,"*",Bets!$I$2:$I$506,"CFB weeknight (Tue-Fri)",Bets!$U$2:$U$506,"Pending") | H36: =COUNTIFS(Bets!$A$2:$A$506,"<>",Bets!$B$2:$B$506,"*",Bets!$I$2:$I$506,"CFB weeknight (Tue-Fri)",Bets!$U$2:$U$506,"Unknown") | I36: =IF(D36+E36=0,"",D36/(D36+E36)) | J36: =SUMIFS(Bets!$Q$2:$Q$506,Bets!$A$2:$A$506,"<>",Bets!$B$2:$B$506,"*",Bets!$I$2:$I$506,"CFB weeknight (Tue-Fri)") | K36: =SUMIFS(Bets!$AC$2:$AC$506,Bets!$A$2:$A$506,"<>",Bets!$B$2:$B$506,"*",Bets!$I$2:$I$506,"CFB weeknight (Tue-Fri)") | L36: =SUMIFS(Bets!$V$2:$V$506,Bets!$A$2:$A$506,"<>",Bets!$B$2:$B$506,"*",Bets!$I$2:$I$506,"CFB weeknight (Tue-Fri)") | M36: =IF(K36=0,"",L36/K36) | N36: =SUMIFS(Bets!$AD$2:$AD$506,Bets!$A$2:$A$506,"<>",Bets!$B$2:$B$506,"*",Bets!$I$2:$I$506,"CFB weeknight (Tue-Fri)") | O36: =SUMIFS(Bets!$W$2:$W$506,Bets!$A$2:$A$506,"<>",Bets!$B$2:$B$506,"*",Bets!$I$2:$I$506,"CFB weeknight (Tue-Fri)") | P36: =IF(N36=0,"",O36/N36)
A37: Combined | B37: kickoff not matched | C37: =COUNTIFS(Bets!$A$2:$A$506,"<>",Bets!$B$2:$B$506,"*",Bets!$I$2:$I$506,"kickoff not matched") | D37: =COUNTIFS(Bets!$A$2:$A$506,"<>",Bets!$B$2:$B$506,"*",Bets!$I$2:$I$506,"kickoff not matched",Bets!$U$2:$U$506,"W") | E37: =COUNTIFS(Bets!$A$2:$A$506,"<>",Bets!$B$2:$B$506,"*",Bets!$I$2:$I$506,"kickoff not matched",Bets!$U$2:$U$506,"L") | F37: =COUNTIFS(Bets!$A$2:$A$506,"<>",Bets!$B$2:$B$506,"*",Bets!$I$2:$I$506,"kickoff not matched",Bets!$U$2:$U$506,"Push") | G37: =COUNTIFS(Bets!$A$2:$A$506,"<>",Bets!$B$2:$B$506,"*",Bets!$I$2:$I$506,"kickoff not matched",Bets!$U$2:$U$506,"Pending") | H37: =COUNTIFS(Bets!$A$2:$A$506,"<>",Bets!$B$2:$B$506,"*",Bets!$I$2:$I$506,"kickoff not matched",Bets!$U$2:$U$506,"Unknown") | I37: =IF(D37+E37=0,"",D37/(D37+E37)) | J37: =SUMIFS(Bets!$Q$2:$Q$506,Bets!$A$2:$A$506,"<>",Bets!$B$2:$B$506,"*",Bets!$I$2:$I$506,"kickoff not matched") | K37: =SUMIFS(Bets!$AC$2:$AC$506,Bets!$A$2:$A$506,"<>",Bets!$B$2:$B$506,"*",Bets!$I$2:$I$506,"kickoff not matched") | L37: =SUMIFS(Bets!$V$2:$V$506,Bets!$A$2:$A$506,"<>",Bets!$B$2:$B$506,"*",Bets!$I$2:$I$506,"kickoff not matched") | M37: =IF(K37=0,"",L37/K37) | N37: =SUMIFS(Bets!$AD$2:$AD$506,Bets!$A$2:$A$506,"<>",Bets!$B$2:$B$506,"*",Bets!$I$2:$I$506,"kickoff not matched") | O37: =SUMIFS(Bets!$W$2:$W$506,Bets!$A$2:$A$506,"<>",Bets!$B$2:$B$506,"*",Bets!$I$2:$I$506,"kickoff not matched") | P37: =IF(N37=0,"",O37/N37)

Sheet By Day of Week
A1: By GAME day of week (formula helper uses WEEKDAY of Game date)
A3: Trent (@BookitWithTrent)
A4: Bettor | B4: Game day | C4: Bets | D4: W | E4: L | F4: Push | G4: Pending | H4: Unknown | I4: Win % (W/(W+L)) | J4: Total staked $ (all $ bets) | K4: Settled staked $ | L4: Net P/L $ | M4: ROI (net / settled $) | N4: Units staked (settled) | O4: Net units | P4: ROI (units)
A5: Trent (@BookitWithTrent) | B5: Monday | C5: =COUNTIFS(Bets!$A$2:$A$506,"<>",Bets!$B$2:$B$506,"Trent",Bets!$F$2:$F$506,"Monday") | D5: =COUNTIFS(Bets!$A$2:$A$506,"<>",Bets!$B$2:$B$506,"Trent",Bets!$F$2:$F$506,"Monday",Bets!$U$2:$U$506,"W") | E5: =COUNTIFS(Bets!$A$2:$A$506,"<>",Bets!$B$2:$B$506,"Trent",Bets!$F$2:$F$506,"Monday",Bets!$U$2:$U$506,"L") | F5: =COUNTIFS(Bets!$A$2:$A$506,"<>",Bets!$B$2:$B$506,"Trent",Bets!$F$2:$F$506,"Monday",Bets!$U$2:$U$506,"Push") | G5: =COUNTIFS(Bets!$A$2:$A$506,"<>",Bets!$B$2:$B$506,"Trent",Bets!$F$2:$F$506,"Monday",Bets!$U$2:$U$506,"Pending") | H5: =COUNTIFS(Bets!$A$2:$A$506,"<>",Bets!$B$2:$B$506,"Trent",Bets!$F$2:$F$506,"Monday",Bets!$U$2:$U$506,"Unknown") | I5: =IF(D5+E5=0,"",D5/(D5+E5)) | J5: =SUMIFS(Bets!$Q$2:$Q$506,Bets!$A$2:$A$506,"<>",Bets!$B$2:$B$506,"Trent",Bets!$F$2:$F$506,"Monday") | K5: =SUMIFS(Bets!$AC$2:$AC$506,Bets!$A$2:$A$506,"<>",Bets!$B$2:$B$506,"Trent",Bets!$F$2:$F$506,"Monday") | L5: =SUMIFS(Bets!$V$2:$V$506,Bets!$A$2:$A$506,"<>",Bets!$B$2:$B$506,"Trent",Bets!$F$2:$F$506,"Monday") | M5: =IF(K5=0,"",L5/K5) | N5: =SUMIFS(Bets!$AD$2:$AD$506,Bets!$A$2:$A$506,"<>",Bets!$B$2:$B$506,"Trent",Bets!$F$2:$F$506,"Monday") | O5: =SUMIFS(Bets!$W$2:$W$506,Bets!$A$2:$A$506,"<>",Bets!$B$2:$B$506,"Trent",Bets!$F$2:$F$506,"Monday") | P5: =IF(N5=0,"",O5/N5)
A6: Trent (@BookitWithTrent) | B6: Tuesday | C6: =COUNTIFS(Bets!$A$2:$A$506,"<>",Bets!$B$2:$B$506,"Trent",Bets!$F$2:$F$506,"Tuesday") | D6: =COUNTIFS(Bets!$A$2:$A$506,"<>",Bets!$B$2:$B$506,"Trent",Bets!$F$2:$F$506,"Tuesday",Bets!$U$2:$U$506,"W") | E6: =COUNTIFS(Bets!$A$2:$A$506,"<>",Bets!$B$2:$B$506,"Trent",Bets!$F$2:$F$506,"Tuesday",Bets!$U$2:$U$506,"L") | F6: =COUNTIFS(Bets!$A$2:$A$506,"<>",Bets!$B$2:$B$506,"Trent",Bets!$F$2:$F$506,"Tuesday",Bets!$U$2:$U$506,"Push") | G6: =COUNTIFS(Bets!$A$2:$A$506,"<>",Bets!$B$2:$B$506,"Trent",Bets!$F$2:$F$506,"Tuesday",Bets!$U$2:$U$506,"Pending") | H6: =COUNTIFS(Bets!$A$2:$A$506,"<>",Bets!$B$2:$B$506,"Trent",Bets!$F$2:$F$506,"Tuesday",Bets!$U$2:$U$506,"Unknown") | I6: =IF(D6+E6=0,"",D6/(D6+E6)) | J6: =SUMIFS(Bets!$Q$2:$Q$506,Bets!$A$2:$A$506,"<>",Bets!$B$2:$B$506,"Trent",Bets!$F$2:$F$506,"Tuesday") | K6: =SUMIFS(Bets!$AC$2:$AC$506,Bets!$A$2:$A$506,"<>",Bets!$B$2:$B$506,"Trent",Bets!$F$2:$F$506,"Tuesday") | L6: =SUMIFS(Bets!$V$2:$V$506,Bets!$A$2:$A$506,"<>",Bets!$B$2:$B$506,"Trent",Bets!$F$2:$F$506,"Tuesday") | M6: =IF(K6=0,"",L6/K6) | N6: =SUMIFS(Bets!$AD$2:$AD$506,Bets!$A$2:$A$506,"<>",Bets!$B$2:$B$506,"Trent",Bets!$F$2:$F$506,"Tuesday") | O6: =SUMIFS(Bets!$W$2:$W$506,Bets!$A$2:$A$506,"<>",Bets!$B$2:$B$506,"Trent",Bets!$F$2:$F$506,"Tuesday") | P6: =IF(N6=0,"",O6/N6)
A7: Trent (@BookitWithTrent) | B7: Wednesday | C7: =COUNTIFS(Bets!$A$2:$A$506,"<>",Bets!$B$2:$B$506,"Trent",Bets!$F$2:$F$506,"Wednesday") | D7: =COUNTIFS(Bets!$A$2:$A$506,"<>",Bets!$B$2:$B$506,"Trent",Bets!$F$2:$F$506,"Wednesday",Bets!$U$2:$U$506,"W") | E7: =COUNTIFS(Bets!$A$2:$A$506,"<>",Bets!$B$2:$B$506,"Trent",Bets!$F$2:$F$506,"Wednesday",Bets!$U$2:$U$506,"L") | F7: =COUNTIFS(Bets!$A$2:$A$506,"<>",Bets!$B$2:$B$506,"Trent",Bets!$F$2:$F$506,"Wednesday",Bets!$U$2:$U$506,"Push") | G7: =COUNTIFS(Bets!$A$2:$A$506,"<>",Bets!$B$2:$B$506,"Trent",Bets!$F$2:$F$506,"Wednesday",Bets!$U$2:$U$506,"Pending") | H7: =COUNTIFS(Bets!$A$2:$A$506,"<>",Bets!$B$2:$B$506,"Trent",Bets!$F$2:$F$506,"Wednesday",Bets!$U$2:$U$506,"Unknown") | I7: =IF(D7+E7=0,"",D7/(D7+E7)) | J7: =SUMIFS(Bets!$Q$2:$Q$506,Bets!$A$2:$A$506,"<>",Bets!$B$2:$B$506,"Trent",Bets!$F$2:$F$506,"Wednesday") | K7: =SUMIFS(Bets!$AC$2:$AC$506,Bets!$A$2:$A$506,"<>",Bets!$B$2:$B$506,"Trent",Bets!$F$2:$F$506,"Wednesday") | L7: =SUMIFS(Bets!$V$2:$V$506,Bets!$A$2:$A$506,"<>",Bets!$B$2:$B$506,"Trent",Bets!$F$2:$F$506,"Wednesday") | M7: =IF(K7=0,"",L7/K7) | N7: =SUMIFS(Bets!$AD$2:$AD$506,Bets!$A$2:$A$506,"<>",Bets!$B$2:$B$506,"Trent",Bets!$F$2:$F$506,"Wednesday") | O7: =SUMIFS(Bets!$W$2:$W$506,Bets!$A$2:$A$506,"<>",Bets!$B$2:$B$506,"Trent",Bets!$F$2:$F$506,"Wednesday") | P7: =IF(N7=0,"",O7/N7)
A8: Trent (@BookitWithTrent) | B8: Thursday | C8: =COUNTIFS(Bets!$A$2:$A$506,"<>",Bets!$B$2:$B$506,"Trent",Bets!$F$2:$F$506,"Thursday") | D8: =COUNTIFS(Bets!$A$2:$A$506,"<>",Bets!$B$2:$B$506,"Trent",Bets!$F$2:$F$506,"Thursday",Bets!$U$2:$U$506,"W") | E8: =COUNTIFS(Bets!$A$2:$A$506,"<>",Bets!$B$2:$B$506,"Trent",Bets!$F$2:$F$506,"Thursday",Bets!$U$2:$U$506,"L") | F8: =COUNTIFS(Bets!$A$2:$A$506,"<>",Bets!$B$2:$B$506,"Trent",Bets!$F$2:$F$506,"Thursday",Bets!$U$2:$U$506,"Push") | G8: =COUNTIFS(Bets!$A$2:$A$506,"<>",Bets!$B$2:$B$506,"Trent",Bets!$F$2:$F$506,"Thursday",Bets!$U$2:$U$506,"Pending") | H8: =COUNTIFS(Bets!$A$2:$A$506,"<>",Bets!$B$2:$B$506,"Trent",Bets!$F$2:$F$506,"Thursday",Bets!$U$2:$U$506,"Unknown") | I8: =IF(D8+E8=0,"",D8/(D8+E8)) | J8: =SUMIFS(Bets!$Q$2:$Q$506,Bets!$A$2:$A$506,"<>",Bets!$B$2:$B$506,"Trent",Bets!$F$2:$F$506,"Thursday") | K8: =SUMIFS(Bets!$AC$2:$AC$506,Bets!$A$2:$A$506,"<>",Bets!$B$2:$B$506,"Trent",Bets!$F$2:$F$506,"Thursday") | L8: =SUMIFS(Bets!$V$2:$V$506,Bets!$A$2:$A$506,"<>",Bets!$B$2:$B$506,"Trent",Bets!$F$2:$F$506,"Thursday") | M8: =IF(K8=0,"",L8/K8) | N8: =SUMIFS(Bets!$AD$2:$AD$506,Bets!$A$2:$A$506,"<>",Bets!$B$2:$B$506,"Trent",Bets!$F$2:$F$506,"Thursday") | O8: =SUMIFS(Bets!$W$2:$W$506,Bets!$A$2:$A$506,"<>",Bets!$B$2:$B$506,"Trent",Bets!$F$2:$F$506,"Thursday") | P8: =IF(N8=0,"",O8/N8)
A9: Trent (@BookitWithTrent) | B9: Friday | C9: =COUNTIFS(Bets!$A$2:$A$506,"<>",Bets!$B$2:$B$506,"Trent",Bets!$F$2:$F$506,"Friday") | D9: =COUNTIFS(Bets!$A$2:$A$506,"<>",Bets!$B$2:$B$506,"Trent",Bets!$F$2:$F$506,"Friday",Bets!$U$2:$U$506,"W") | E9: =COUNTIFS(Bets!$A$2:$A$506,"<>",Bets!$B$2:$B$506,"Trent",Bets!$F$2:$F$506,"Friday",Bets!$U$2:$U$506,"L") | F9: =COUNTIFS(Bets!$A$2:$A$506,"<>",Bets!$B$2:$B$506,"Trent",Bets!$F$2:$F$506,"Friday",Bets!$U$2:$U$506,"Push") | G9: =COUNTIFS(Bets!$A$2:$A$506,"<>",Bets!$B$2:$B$506,"Trent",Bets!$F$2:$F$506,"Friday",Bets!$U$2:$U$506,"Pending") | H9: =COUNTIFS(Bets!$A$2:$A$506,"<>",Bets!$B$2:$B$506,"Trent",Bets!$F$2:$F$506,"Friday",Bets!$U$2:$U$506,"Unknown") | I9: =IF(D9+E9=0,"",D9/(D9+E9)) | J9: =SUMIFS(Bets!$Q$2:$Q$506,Bets!$A$2:$A$506,"<>",Bets!$B$2:$B$506,"Trent",Bets!$F$2:$F$506,"Friday") | K9: =SUMIFS(Bets!$AC$2:$AC$506,Bets!$A$2:$A$506,"<>",Bets!$B$2:$B$506,"Trent",Bets!$F$2:$F$506,"Friday") | L9: =SUMIFS(Bets!$V$2:$V$506,Bets!$A$2:$A$506,"<>",Bets!$B$2:$B$506,"Trent",Bets!$F$2:$F$506,"Friday") | M9: =IF(K9=0,"",L9/K9) | N9: =SUMIFS(Bets!$AD$2:$AD$506,Bets!$A$2:$A$506,"<>",Bets!$B$2:$B$506,"Trent",Bets!$F$2:$F$506,"Friday") | O9: =SUMIFS(Bets!$W$2:$W$506,Bets!$A$2:$A$506,"<>",Bets!$B$2:$B$506,"Trent",Bets!$F$2:$F$506,"Friday") | P9: =IF(N9=0,"",O9/N9)
A10: Trent (@BookitWithTrent) | B10: Saturday | C10: =COUNTIFS(Bets!$A$2:$A$506,"<>",Bets!$B$2:$B$506,"Trent",Bets!$F$2:$F$506,"Saturday") | D10: =COUNTIFS(Bets!$A$2:$A$506,"<>",Bets!$B$2:$B$506,"Trent",Bets!$F$2:$F$506,"Saturday",Bets!$U$2:$U$506,"W") | E10: =COUNTIFS(Bets!$A$2:$A$506,"<>",Bets!$B$2:$B$506,"Trent",Bets!$F$2:$F$506,"Saturday",Bets!$U$2:$U$506,"L") | F10: =COUNTIFS(Bets!$A$2:$A$506,"<>",Bets!$B$2:$B$506,"Trent",Bets!$F$2:$F$506,"Saturday",Bets!$U$2:$U$506,"Push") | G10: =COUNTIFS(Bets!$A$2:$A$506,"<>",Bets!$B$2:$B$506,"Trent",Bets!$F$2:$F$506,"Saturday",Bets!$U$2:$U$506,"Pending") | H10: =COUNTIFS(Bets!$A$2:$A$506,"<>",Bets!$B$2:$B$506,"Trent",Bets!$F$2:$F$506,"Saturday",Bets!$U$2:$U$506,"Unknown") | I10: =IF(D10+E10=0,"",D10/(D10+E10)) | J10: =SUMIFS(Bets!$Q$2:$Q$506,Bets!$A$2:$A$506,"<>",Bets!$B$2:$B$506,"Trent",Bets!$F$2:$F$506,"Saturday") | K10: =SUMIFS(Bets!$AC$2:$AC$506,Bets!$A$2:$A$506,"<>",Bets!$B$2:$B$506,"Trent",Bets!$F$2:$F$506,"Saturday") | L10: =SUMIFS(Bets!$V$2:$V$506,Bets!$A$2:$A$506,"<>",Bets!$B$2:$B$506,"Trent",Bets!$F$2:$F$506,"Saturday") | M10: =IF(K10=0,"",L10/K10) | N10: =SUMIFS(Bets!$AD$2:$AD$506,Bets!$A$2:$A$506,"<>",Bets!$B$2:$B$506,"Trent",Bets!$F$2:$F$506,"Saturday") | O10: =SUMIFS(Bets!$W$2:$W$506,Bets!$A$2:$A$506,"<>",Bets!$B$2:$B$506,"Trent",Bets!$F$2:$F$506,"Saturday") | P10: =IF(N10=0,"",O10/N10)
A11: Trent (@BookitWithTrent) | B11: Sunday | C11: =COUNTIFS(Bets!$A$2:$A$506,"<>",Bets!$B$2:$B$506,"Trent",Bets!$F$2:$F$506,"Sunday") | D11: =COUNTIFS(Bets!$A$2:$A$506,"<>",Bets!$B$2:$B$506,"Trent",Bets!$F$2:$F$506,"Sunday",Bets!$U$2:$U$506,"W") | E11: =COUNTIFS(Bets!$A$2:$A$506,"<>",Bets!$B$2:$B$506,"Trent",Bets!$F$2:$F$506,"Sunday",Bets!$U$2:$U$506,"L") | F11: =COUNTIFS(Bets!$A$2:$A$506,"<>",Bets!$B$2:$B$506,"Trent",Bets!$F$2:$F$506,"Sunday",Bets!$U$2:$U$506,"Push") | G11: =COUNTIFS(Bets!$A$2:$A$506,"<>",Bets!$B$2:$B$506,"Trent",Bets!$F$2:$F$506,"Sunday",Bets!$U$2:$U$506,"Pending") | H11: =COUNTIFS(Bets!$A$2:$A$506,"<>",Bets!$B$2:$B$506,"Trent",Bets!$F$2:$F$506,"Sunday",Bets!$U$2:$U$506,"Unknown") | I11: =IF(D11+E11=0,"",D11/(D11+E11)) | J11: =SUMIFS(Bets!$Q$2:$Q$506,Bets!$A$2:$A$506,"<>",Bets!$B$2:$B$506,"Trent",Bets!$F$2:$F$506,"Sunday") | K11: =SUMIFS(Bets!$AC$2:$AC$506,Bets!$A$2:$A$506,"<>",Bets!$B$2:$B$506,"Trent",Bets!$F$2:$F$506,"Sunday") | L11: =SUMIFS(Bets!$V$2:$V$506,Bets!$A$2:$A$506,"<>",Bets!$B$2:$B$506,"Trent",Bets!$F$2:$F$506,"Sunday") | M11: =IF(K11=0,"",L11/K11) | N11: =SUMIFS(Bets!$AD$2:$AD$506,Bets!$A$2:$A$506,"<>",Bets!$B$2:$B$506,"Trent",Bets!$F$2:$F$506,"Sunday") | O11: =SUMIFS(Bets!$W$2:$W$506,Bets!$A$2:$A$506,"<>",Bets!$B$2:$B$506,"Trent",Bets!$F$2:$F$506,"Sunday") | P11: =IF(N11=0,"",O11/N11)
A13: Steve (@stevewilldoit)
A14: Bettor | B14: Game day | C14: Bets | D14: W | E14: L | F14: Push | G14: Pending | H14: Unknown | I14: Win % (W/(W+L)) | J14: Total staked $ (all $ bets) | K14: Settled staked $ | L14: Net P/L $ | M14: ROI (net / settled $) | N14: Units staked (settled) | O14: Net units | P14: ROI (units)
A15: Steve (@stevewilldoit) | B15: Monday | C15: =COUNTIFS(Bets!$A$2:$A$506,"<>",Bets!$B$2:$B$506,"Steve",Bets!$F$2:$F$506,"Monday") | D15: =COUNTIFS(Bets!$A$2:$A$506,"<>",Bets!$B$2:$B$506,"Steve",Bets!$F$2:$F$506,"Monday",Bets!$U$2:$U$506,"W") | E15: =COUNTIFS(Bets!$A$2:$A$506,"<>",Bets!$B$2:$B$506,"Steve",Bets!$F$2:$F$506,"Monday",Bets!$U$2:$U$506,"L") | F15: =COUNTIFS(Bets!$A$2:$A$506,"<>",Bets!$B$2:$B$506,"Steve",Bets!$F$2:$F$506,"Monday",Bets!$U$2:$U$506,"Push") | G15: =COUNTIFS(Bets!$A$2:$A$506,"<>",Bets!$B$2:$B$506,"Steve",Bets!$F$2:$F$506,"Monday",Bets!$U$2:$U$506,"Pending") | H15: =COUNTIFS(Bets!$A$2:$A$506,"<>",Bets!$B$2:$B$506,"Steve",Bets!$F$2:$F$506,"Monday",Bets!$U$2:$U$506,"Unknown") | I15: =IF(D15+E15=0,"",D15/(D15+E15)) | J15: =SUMIFS(Bets!$Q$2:$Q$506,Bets!$A$2:$A$506,"<>",Bets!$B$2:$B$506,"Steve",Bets!$F$2:$F$506,"Monday") | K15: =SUMIFS(Bets!$AC$2:$AC$506,Bets!$A$2:$A$506,"<>",Bets!$B$2:$B$506,"Steve",Bets!$F$2:$F$506,"Monday") | L15: =SUMIFS(Bets!$V$2:$V$506,Bets!$A$2:$A$506,"<>",Bets!$B$2:$B$506,"Steve",Bets!$F$2:$F$506,"Monday") | M15: =IF(K15=0,"",L15/K15) | N15: =SUMIFS(Bets!$AD$2:$AD$506,Bets!$A$2:$A$506,"<>",Bets!$B$2:$B$506,"Steve",Bets!$F$2:$F$506,"Monday") | O15: =SUMIFS(Bets!$W$2:$W$506,Bets!$A$2:$A$506,"<>",Bets!$B$2:$B$506,"Steve",Bets!$F$2:$F$506,"Monday") | P15: =IF(N15=0,"",O15/N15)
A16: Steve (@stevewilldoit) | B16: Tuesday | C16: =COUNTIFS(Bets!$A$2:$A$506,"<>",Bets!$B$2:$B$506,"Steve",Bets!$F$2:$F$506,"Tuesday") | D16: =COUNTIFS(Bets!$A$2:$A$506,"<>",Bets!$B$2:$B$506,"Steve",Bets!$F$2:$F$506,"Tuesday",Bets!$U$2:$U$506,"W") | E16: =COUNTIFS(Bets!$A$2:$A$506,"<>",Bets!$B$2:$B$506,"Steve",Bets!$F$2:$F$506,"Tuesday",Bets!$U$2:$U$506,"L") | F16: =COUNTIFS(Bets!$A$2:$A$506,"<>",Bets!$B$2:$B$506,"Steve",Bets!$F$2:$F$506,"Tuesday",Bets!$U$2:$U$506,"Push") | G16: =COUNTIFS(Bets!$A$2:$A$506,"<>",Bets!$B$2:$B$506,"Steve",Bets!$F$2:$F$506,"Tuesday",Bets!$U$2:$U$506,"Pending") | H16: =COUNTIFS(Bets!$A$2:$A$506,"<>",Bets!$B$2:$B$506,"Steve",Bets!$F$2:$F$506,"Tuesday",Bets!$U$2:$U$506,"Unknown") | I16: =IF(D16+E16=0,"",D16/(D16+E16)) | J16: =SUMIFS(Bets!$Q$2:$Q$506,Bets!$A$2:$A$506,"<>",Bets!$B$2:$B$506,"Steve",Bets!$F$2:$F$506,"Tuesday") | K16: =SUMIFS(Bets!$AC$2:$AC$506,Bets!$A$2:$A$506,"<>",Bets!$B$2:$B$506,"Steve",Bets!$F$2:$F$506,"Tuesday") | L16: =SUMIFS(Bets!$V$2:$V$506,Bets!$A$2:$A$506,"<>",Bets!$B$2:$B$506,"Steve",Bets!$F$2:$F$506,"Tuesday") | M16: =IF(K16=0,"",L16/K16) | N16: =SUMIFS(Bets!$AD$2:$AD$506,Bets!$A$2:$A$506,"<>",Bets!$B$2:$B$506,"Steve",Bets!$F$2:$F$506,"Tuesday") | O16: =SUMIFS(Bets!$W$2:$W$506,Bets!$A$2:$A$506,"<>",Bets!$B$2:$B$506,"Steve",Bets!$F$2:$F$506,"Tuesday") | P16: =IF(N16=0,"",O16/N16)
A17: Steve (@stevewilldoit) | B17: Wednesday | C17: =COUNTIFS(Bets!$A$2:$A$506,"<>",Bets!$B$2:$B$506,"Steve",Bets!$F$2:$F$506,"Wednesday") | D17: =COUNTIFS(Bets!$A$2:$A$506,"<>",Bets!$B$2:$B$506,"Steve",Bets!$F$2:$F$506,"Wednesday",Bets!$U$2:$U$506,"W") | E17: =COUNTIFS(Bets!$A$2:$A$506,"<>",Bets!$B$2:$B$506,"Steve",Bets!$F$2:$F$506,"Wednesday",Bets!$U$2:$U$506,"L") | F17: =COUNTIFS(Bets!$A$2:$A$506,"<>",Bets!$B$2:$B$506,"Steve",Bets!$F$2:$F$506,"Wednesday",Bets!$U$2:$U$506,"Push") | G17: =COUNTIFS(Bets!$A$2:$A$506,"<>",Bets!$B$2:$B$506,"Steve",Bets!$F$2:$F$506,"Wednesday",Bets!$U$2:$U$506,"Pending") | H17: =COUNTIFS(Bets!$A$2:$A$506,"<>",Bets!$B$2:$B$506,"Steve",Bets!$F$2:$F$506,"Wednesday",Bets!$U$2:$U$506,"Unknown") | I17: =IF(D17+E17=0,"",D17/(D17+E17)) | J17: =SUMIFS(Bets!$Q$2:$Q$506,Bets!$A$2:$A$506,"<>",Bets!$B$2:$B$506,"Steve",Bets!$F$2:$F$506,"Wednesday") | K17: =SUMIFS(Bets!$AC$2:$AC$506,Bets!$A$2:$A$506,"<>",Bets!$B$2:$B$506,"Steve",Bets!$F$2:$F$506,"Wednesday") | L17: =SUMIFS(Bets!$V$2:$V$506,Bets!$A$2:$A$506,"<>",Bets!$B$2:$B$506,"Steve",Bets!$F$2:$F$506,"Wednesday") | M17: =IF(K17=0,"",L17/K17) | N17: =SUMIFS(Bets!$AD$2:$AD$506,Bets!$A$2:$A$506,"<>",Bets!$B$2:$B$506,"Steve",Bets!$F$2:$F$506,"Wednesday") | O17: =SUMIFS(Bets!$W$2:$W$506,Bets!$A$2:$A$506,"<>",Bets!$B$2:$B$506,"Steve",Bets!$F$2:$F$506,"Wednesday") | P17: =IF(N17=0,"",O17/N17)
A18: Steve (@stevewilldoit) | B18: Thursday | C18: =COUNTIFS(Bets!$A$2:$A$506,"<>",Bets!$B$2:$B$506,"Steve",Bets!$F$2:$F$506,"Thursday") | D18: =COUNTIFS(Bets!$A$2:$A$506,"<>",Bets!$B$2:$B$506,"Steve",Bets!$F$2:$F$506,"Thursday",Bets!$U$2:$U$506,"W") | E18: =COUNTIFS(Bets!$A$2:$A$506,"<>",Bets!$B$2:$B$506,"Steve",Bets!$F$2:$F$506,"Thursday",Bets!$U$2:$U$506,"L") | F18: =COUNTIFS(Bets!$A$2:$A$506,"<>",Bets!$B$2:$B$506,"Steve",Bets!$F$2:$F$506,"Thursday",Bets!$U$2:$U$506,"Push") | G18: =COUNTIFS(Bets!$A$2:$A$506,"<>",Bets!$B$2:$B$506,"Steve",Bets!$F$2:$F$506,"Thursday",Bets!$U$2:$U$506,"Pending") | H18: =COUNTIFS(Bets!$A$2:$A$506,"<>",Bets!$B$2:$B$506,"Steve",Bets!$F$2:$F$506,"Thursday",Bets!$U$2:$U$506,"Unknown") | I18: =IF(D18+E18=0,"",D18/(D18+E18)) | J18: =SUMIFS(Bets!$Q$2:$Q$506,Bets!$A$2:$A$506,"<>",Bets!$B$2:$B$506,"Steve",Bets!$F$2:$F$506,"Thursday") | K18: =SUMIFS(Bets!$AC$2:$AC$506,Bets!$A$2:$A$506,"<>",Bets!$B$2:$B$506,"Steve",Bets!$F$2:$F$506,"Thursday") | L18: =SUMIFS(Bets!$V$2:$V$506,Bets!$A$2:$A$506,"<>",Bets!$B$2:$B$506,"Steve",Bets!$F$2:$F$506,"Thursday") | M18: =IF(K18=0,"",L18/K18) | N18: =SUMIFS(Bets!$AD$2:$AD$506,Bets!$A$2:$A$506,"<>",Bets!$B$2:$B$506,"Steve",Bets!$F$2:$F$506,"Thursday") | O18: =SUMIFS(Bets!$W$2:$W$506,Bets!$A$2:$A$506,"<>",Bets!$B$2:$B$506,"Steve",Bets!$F$2:$F$506,"Thursday") | P18: =IF(N18=0,"",O18/N18)
A19: Steve (@stevewilldoit) | B19: Friday | C19: =COUNTIFS(Bets!$A$2:$A$506,"<>",Bets!$B$2:$B$506,"Steve",Bets!$F$2:$F$506,"Friday") | D19: =COUNTIFS(Bets!$A$2:$A$506,"<>",Bets!$B$2:$B$506,"Steve",Bets!$F$2:$F$506,"Friday",Bets!$U$2:$U$506,"W") | E19: =COUNTIFS(Bets!$A$2:$A$506,"<>",Bets!$B$2:$B$506,"Steve",Bets!$F$2:$F$506,"Friday",Bets!$U$2:$U$506,"L") | F19: =COUNTIFS(Bets!$A$2:$A$506,"<>",Bets!$B$2:$B$506,"Steve",Bets!$F$2:$F$506,"Friday",Bets!$U$2:$U$506,"Push") | G19: =COUNTIFS(Bets!$A$2:$A$506,"<>",Bets!$B$2:$B$506,"Steve",Bets!$F$2:$F$506,"Friday",Bets!$U$2:$U$506,"Pending") | H19: =COUNTIFS(Bets!$A$2:$A$506,"<>",Bets!$B$2:$B$506,"Steve",Bets!$F$2:$F$506,"Friday",Bets!$U$2:$U$506,"Unknown") | I19: =IF(D19+E19=0,"",D19/(D19+E19)) | J19: =SUMIFS(Bets!$Q$2:$Q$506,Bets!$A$2:$A$506,"<>",Bets!$B$2:$B$506,"Steve",Bets!$F$2:$F$506,"Friday") | K19: =SUMIFS(Bets!$AC$2:$AC$506,Bets!$A$2:$A$506,"<>",Bets!$B$2:$B$506,"Steve",Bets!$F$2:$F$506,"Friday") | L19: =SUMIFS(Bets!$V$2:$V$506,Bets!$A$2:$A$506,"<>",Bets!$B$2:$B$506,"Steve",Bets!$F$2:$F$506,"Friday") | M19: =IF(K19=0,"",L19/K19) | N19: =SUMIFS(Bets!$AD$2:$AD$506,Bets!$A$2:$A$506,"<>",Bets!$B$2:$B$506,"Steve",Bets!$F$2:$F$506,"Friday") | O19: =SUMIFS(Bets!$W$2:$W$506,Bets!$A$2:$A$506,"<>",Bets!$B$2:$B$506,"Steve",Bets!$F$2:$F$506,"Friday") | P19: =IF(N19=0,"",O19/N19)
A20: Steve (@stevewilldoit) | B20: Saturday | C20: =COUNTIFS(Bets!$A$2:$A$506,"<>",Bets!$B$2:$B$506,"Steve",Bets!$F$2:$F$506,"Saturday") | D20: =COUNTIFS(Bets!$A$2:$A$506,"<>",Bets!$B$2:$B$506,"Steve",Bets!$F$2:$F$506,"Saturday",Bets!$U$2:$U$506,"W") | E20: =COUNTIFS(Bets!$A$2:$A$506,"<>",Bets!$B$2:$B$506,"Steve",Bets!$F$2:$F$506,"Saturday",Bets!$U$2:$U$506,"L") | F20: =COUNTIFS(Bets!$A$2:$A$506,"<>",Bets!$B$2:$B$506,"Steve",Bets!$F$2:$F$506,"Saturday",Bets!$U$2:$U$506,"Push") | G20: =COUNTIFS(Bets!$A$2:$A$506,"<>",Bets!$B$2:$B$506,"Steve",Bets!$F$2:$F$506,"Saturday",Bets!$U$2:$U$506,"Pending") | H20: =COUNTIFS(Bets!$A$2:$A$506,"<>",Bets!$B$2:$B$506,"Steve",Bets!$F$2:$F$506,"Saturday",Bets!$U$2:$U$506,"Unknown") | I20: =IF(D20+E20=0,"",D20/(D20+E20)) | J20: =SUMIFS(Bets!$Q$2:$Q$506,Bets!$A$2:$A$506,"<>",Bets!$B$2:$B$506,"Steve",Bets!$F$2:$F$506,"Saturday") | K20: =SUMIFS(Bets!$AC$2:$AC$506,Bets!$A$2:$A$506,"<>",Bets!$B$2:$B$506,"Steve",Bets!$F$2:$F$506,"Saturday") | L20: =SUMIFS(Bets!$V$2:$V$506,Bets!$A$2:$A$506,"<>",Bets!$B$2:$B$506,"Steve",Bets!$F$2:$F$506,"Saturday") | M20: =IF(K20=0,"",L20/K20) | N20: =SUMIFS(Bets!$AD$2:$AD$506,Bets!$A$2:$A$506,"<>",Bets!$B$2:$B$506,"Steve",Bets!$F$2:$F$506,"Saturday") | O20: =SUMIFS(Bets!$W$2:$W$506,Bets!$A$2:$A$506,"<>",Bets!$B$2:$B$506,"Steve",Bets!$F$2:$F$506,"Saturday") | P20: =IF(N20=0,"",O20/N20)
A21: Steve (@stevewilldoit) | B21: Sunday | C21: =COUNTIFS(Bets!$A$2:$A$506,"<>",Bets!$B$2:$B$506,"Steve",Bets!$F$2:$F$506,"Sunday") | D21: =COUNTIFS(Bets!$A$2:$A$506,"<>",Bets!$B$2:$B$506,"Steve",Bets!$F$2:$F$506,"Sunday",Bets!$U$2:$U$506,"W") | E21: =COUNTIFS(Bets!$A$2:$A$506,"<>",Bets!$B$2:$B$506,"Steve",Bets!$F$2:$F$506,"Sunday",Bets!$U$2:$U$506,"L") | F21: =COUNTIFS(Bets!$A$2:$A$506,"<>",Bets!$B$2:$B$506,"Steve",Bets!$F$2:$F$506,"Sunday",Bets!$U$2:$U$506,"Push") | G21: =COUNTIFS(Bets!$A$2:$A$506,"<>",Bets!$B$2:$B$506,"Steve",Bets!$F$2:$F$506,"Sunday",Bets!$U$2:$U$506,"Pending") | H21: =COUNTIFS(Bets!$A$2:$A$506,"<>",Bets!$B$2:$B$506,"Steve",Bets!$F$2:$F$506,"Sunday",Bets!$U$2:$U$506,"Unknown") | I21: =IF(D21+E21=0,"",D21/(D21+E21)) | J21: =SUMIFS(Bets!$Q$2:$Q$506,Bets!$A$2:$A$506,"<>",Bets!$B$2:$B$506,"Steve",Bets!$F$2:$F$506,"Sunday") | K21: =SUMIFS(Bets!$AC$2:$AC$506,Bets!$A$2:$A$506,"<>",Bets!$B$2:$B$506,"Steve",Bets!$F$2:$F$506,"Sunday") | L21: =SUMIFS(Bets!$V$2:$V$506,Bets!$A$2:$A$506,"<>",Bets!$B$2:$B$506,"Steve",Bets!$F$2:$F$506,"Sunday") | M21: =IF(K21=0,"",L21/K21) | N21: =SUMIFS(Bets!$AD$2:$AD$506,Bets!$A$2:$A$506,"<>",Bets!$B$2:$B$506,"Steve",Bets!$F$2:$F$506,"Sunday") | O21: =SUMIFS(Bets!$W$2:$W$506,Bets!$A$2:$A$506,"<>",Bets!$B$2:$B$506,"Steve",Bets!$F$2:$F$506,"Sunday") | P21: =IF(N21=0,"",O21/N21)
A23: Combined
A24: Bettor | B24: Game day | C24: Bets | D24: W | E24: L | F24: Push | G24: Pending | H24: Unknown | I24: Win % (W/(W+L)) | J24: Total staked $ (all $ bets) | K24: Settled staked $ | L24: Net P/L $ | M24: ROI (net / settled $) | N24: Units staked (settled) | O24: Net units | P24: ROI (units)
A25: Combined | B25: Monday | C25: =COUNTIFS(Bets!$A$2:$A$506,"<>",Bets!$B$2:$B$506,"*",Bets!$F$2:$F$506,"Monday") | D25: =COUNTIFS(Bets!$A$2:$A$506,"<>",Bets!$B$2:$B$506,"*",Bets!$F$2:$F$506,"Monday",Bets!$U$2:$U$506,"W") | E25: =COUNTIFS(Bets!$A$2:$A$506,"<>",Bets!$B$2:$B$506,"*",Bets!$F$2:$F$506,"Monday",Bets!$U$2:$U$506,"L") | F25: =COUNTIFS(Bets!$A$2:$A$506,"<>",Bets!$B$2:$B$506,"*",Bets!$F$2:$F$506,"Monday",Bets!$U$2:$U$506,"Push") | G25: =COUNTIFS(Bets!$A$2:$A$506,"<>",Bets!$B$2:$B$506,"*",Bets!$F$2:$F$506,"Monday",Bets!$U$2:$U$506,"Pending") | H25: =COUNTIFS(Bets!$A$2:$A$506,"<>",Bets!$B$2:$B$506,"*",Bets!$F$2:$F$506,"Monday",Bets!$U$2:$U$506,"Unknown") | I25: =IF(D25+E25=0,"",D25/(D25+E25)) | J25: =SUMIFS(Bets!$Q$2:$Q$506,Bets!$A$2:$A$506,"<>",Bets!$B$2:$B$506,"*",Bets!$F$2:$F$506,"Monday") | K25: =SUMIFS(Bets!$AC$2:$AC$506,Bets!$A$2:$A$506,"<>",Bets!$B$2:$B$506,"*",Bets!$F$2:$F$506,"Monday") | L25: =SUMIFS(Bets!$V$2:$V$506,Bets!$A$2:$A$506,"<>",Bets!$B$2:$B$506,"*",Bets!$F$2:$F$506,"Monday") | M25: =IF(K25=0,"",L25/K25) | N25: =SUMIFS(Bets!$AD$2:$AD$506,Bets!$A$2:$A$506,"<>",Bets!$B$2:$B$506,"*",Bets!$F$2:$F$506,"Monday") | O25: =SUMIFS(Bets!$W$2:$W$506,Bets!$A$2:$A$506,"<>",Bets!$B$2:$B$506,"*",Bets!$F$2:$F$506,"Monday") | P25: =IF(N25=0,"",O25/N25)
A26: Combined | B26: Tuesday | C26: =COUNTIFS(Bets!$A$2:$A$506,"<>",Bets!$B$2:$B$506,"*",Bets!$F$2:$F$506,"Tuesday") | D26: =COUNTIFS(Bets!$A$2:$A$506,"<>",Bets!$B$2:$B$506,"*",Bets!$F$2:$F$506,"Tuesday",Bets!$U$2:$U$506,"W") | E26: =COUNTIFS(Bets!$A$2:$A$506,"<>",Bets!$B$2:$B$506,"*",Bets!$F$2:$F$506,"Tuesday",Bets!$U$2:$U$506,"L") | F26: =COUNTIFS(Bets!$A$2:$A$506,"<>",Bets!$B$2:$B$506,"*",Bets!$F$2:$F$506,"Tuesday",Bets!$U$2:$U$506,"Push") | G26: =COUNTIFS(Bets!$A$2:$A$506,"<>",Bets!$B$2:$B$506,"*",Bets!$F$2:$F$506,"Tuesday",Bets!$U$2:$U$506,"Pending") | H26: =COUNTIFS(Bets!$A$2:$A$506,"<>",Bets!$B$2:$B$506,"*",Bets!$F$2:$F$506,"Tuesday",Bets!$U$2:$U$506,"Unknown") | I26: =IF(D26+E26=0,"",D26/(D26+E26)) | J26: =SUMIFS(Bets!$Q$2:$Q$506,Bets!$A$2:$A$506,"<>",Bets!$B$2:$B$506,"*",Bets!$F$2:$F$506,"Tuesday") | K26: =SUMIFS(Bets!$AC$2:$AC$506,Bets!$A$2:$A$506,"<>",Bets!$B$2:$B$506,"*",Bets!$F$2:$F$506,"Tuesday") | L26: =SUMIFS(Bets!$V$2:$V$506,Bets!$A$2:$A$506,"<>",Bets!$B$2:$B$506,"*",Bets!$F$2:$F$506,"Tuesday") | M26: =IF(K26=0,"",L26/K26) | N26: =SUMIFS(Bets!$AD$2:$AD$506,Bets!$A$2:$A$506,"<>",Bets!$B$2:$B$506,"*",Bets!$F$2:$F$506,"Tuesday") | O26: =SUMIFS(Bets!$W$2:$W$506,Bets!$A$2:$A$506,"<>",Bets!$B$2:$B$506,"*",Bets!$F$2:$F$506,"Tuesday") | P26: =IF(N26=0,"",O26/N26)
A27: Combined | B27: Wednesday | C27: =COUNTIFS(Bets!$A$2:$A$506,"<>",Bets!$B$2:$B$506,"*",Bets!$F$2:$F$506,"Wednesday") | D27: =COUNTIFS(Bets!$A$2:$A$506,"<>",Bets!$B$2:$B$506,"*",Bets!$F$2:$F$506,"Wednesday",Bets!$U$2:$U$506,"W") | E27: =COUNTIFS(Bets!$A$2:$A$506,"<>",Bets!$B$2:$B$506,"*",Bets!$F$2:$F$506,"Wednesday",Bets!$U$2:$U$506,"L") | F27: =COUNTIFS(Bets!$A$2:$A$506,"<>",Bets!$B$2:$B$506,"*",Bets!$F$2:$F$506,"Wednesday",Bets!$U$2:$U$506,"Push") | G27: =COUNTIFS(Bets!$A$2:$A$506,"<>",Bets!$B$2:$B$506,"*",Bets!$F$2:$F$506,"Wednesday",Bets!$U$2:$U$506,"Pending") | H27: =COUNTIFS(Bets!$A$2:$A$506,"<>",Bets!$B$2:$B$506,"*",Bets!$F$2:$F$506,"Wednesday",Bets!$U$2:$U$506,"Unknown") | I27: =IF(D27+E27=0,"",D27/(D27+E27)) | J27: =SUMIFS(Bets!$Q$2:$Q$506,Bets!$A$2:$A$506,"<>",Bets!$B$2:$B$506,"*",Bets!$F$2:$F$506,"Wednesday") | K27: =SUMIFS(Bets!$AC$2:$AC$506,Bets!$A$2:$A$506,"<>",Bets!$B$2:$B$506,"*",Bets!$F$2:$F$506,"Wednesday") | L27: =SUMIFS(Bets!$V$2:$V$506,Bets!$A$2:$A$506,"<>",Bets!$B$2:$B$506,"*",Bets!$F$2:$F$506,"Wednesday") | M27: =IF(K27=0,"",L27/K27) | N27: =SUMIFS(Bets!$AD$2:$AD$506,Bets!$A$2:$A$506,"<>",Bets!$B$2:$B$506,"*",Bets!$F$2:$F$506,"Wednesday") | O27: =SUMIFS(Bets!$W$2:$W$506,Bets!$A$2:$A$506,"<>",Bets!$B$2:$B$506,"*",Bets!$F$2:$F$506,"Wednesday") | P27: =IF(N27=0,"",O27/N27)
A28: Combined | B28: Thursday | C28: =COUNTIFS(Bets!$A$2:$A$506,"<>",Bets!$B$2:$B$506,"*",Bets!$F$2:$F$506,"Thursday") | D28: =COUNTIFS(Bets!$A$2:$A$506,"<>",Bets!$B$2:$B$506,"*",Bets!$F$2:$F$506,"Thursday",Bets!$U$2:$U$506,"W") | E28: =COUNTIFS(Bets!$A$2:$A$506,"<>",Bets!$B$2:$B$506,"*",Bets!$F$2:$F$506,"Thursday",Bets!$U$2:$U$506,"L") | F28: =COUNTIFS(Bets!$A$2:$A$506,"<>",Bets!$B$2:$B$506,"*",Bets!$F$2:$F$506,"Thursday",Bets!$U$2:$U$506,"Push") | G28: =COUNTIFS(Bets!$A$2:$A$506,"<>",Bets!$B$2:$B$506,"*",Bets!$F$2:$F$506,"Thursday",Bets!$U$2:$U$506,"Pending") | H28: =COUNTIFS(Bets!$A$2:$A$506,"<>",Bets!$B$2:$B$506,"*",Bets!$F$2:$F$506,"Thursday",Bets!$U$2:$U$506,"Unknown") | I28: =IF(D28+E28=0,"",D28/(D28+E28)) | J28: =SUMIFS(Bets!$Q$2:$Q$506,Bets!$A$2:$A$506,"<>",Bets!$B$2:$B$506,"*",Bets!$F$2:$F$506,"Thursday") | K28: =SUMIFS(Bets!$AC$2:$AC$506,Bets!$A$2:$A$506,"<>",Bets!$B$2:$B$506,"*",Bets!$F$2:$F$506,"Thursday") | L28: =SUMIFS(Bets!$V$2:$V$506,Bets!$A$2:$A$506,"<>",Bets!$B$2:$B$506,"*",Bets!$F$2:$F$506,"Thursday") | M28: =IF(K28=0,"",L28/K28) | N28: =SUMIFS(Bets!$AD$2:$AD$506,Bets!$A$2:$A$506,"<>",Bets!$B$2:$B$506,"*",Bets!$F$2:$F$506,"Thursday") | O28: =SUMIFS(Bets!$W$2:$W$506,Bets!$A$2:$A$506,"<>",Bets!$B$2:$B$506,"*",Bets!$F$2:$F$506,"Thursday") | P28: =IF(N28=0,"",O28/N28)
A29: Combined | B29: Friday | C29: =COUNTIFS(Bets!$A$2:$A$506,"<>",Bets!$B$2:$B$506,"*",Bets!$F$2:$F$506,"Friday") | D29: =COUNTIFS(Bets!$A$2:$A$506,"<>",Bets!$B$2:$B$506,"*",Bets!$F$2:$F$506,"Friday",Bets!$U$2:$U$506,"W") | E29: =COUNTIFS(Bets!$A$2:$A$506,"<>",Bets!$B$2:$B$506,"*",Bets!$F$2:$F$506,"Friday",Bets!$U$2:$U$506,"L") | F29: =COUNTIFS(Bets!$A$2:$A$506,"<>",Bets!$B$2:$B$506,"*",Bets!$F$2:$F$506,"Friday",Bets!$U$2:$U$506,"Push") | G29: =COUNTIFS(Bets!$A$2:$A$506,"<>",Bets!$B$2:$B$506,"*",Bets!$F$2:$F$506,"Friday",Bets!$U$2:$U$506,"Pending") | H29: =COUNTIFS(Bets!$A$2:$A$506,"<>",Bets!$B$2:$B$506,"*",Bets!$F$2:$F$506,"Friday",Bets!$U$2:$U$506,"Unknown") | I29: =IF(D29+E29=0,"",D29/(D29+E29)) | J29: =SUMIFS(Bets!$Q$2:$Q$506,Bets!$A$2:$A$506,"<>",Bets!$B$2:$B$506,"*",Bets!$F$2:$F$506,"Friday") | K29: =SUMIFS(Bets!$AC$2:$AC$506,Bets!$A$2:$A$506,"<>",Bets!$B$2:$B$506,"*",Bets!$F$2:$F$506,"Friday") | L29: =SUMIFS(Bets!$V$2:$V$506,Bets!$A$2:$A$506,"<>",Bets!$B$2:$B$506,"*",Bets!$F$2:$F$506,"Friday") | M29: =IF(K29=0,"",L29/K29) | N29: =SUMIFS(Bets!$AD$2:$AD$506,Bets!$A$2:$A$506,"<>",Bets!$B$2:$B$506,"*",Bets!$F$2:$F$506,"Friday") | O29: =SUMIFS(Bets!$W$2:$W$506,Bets!$A$2:$A$506,"<>",Bets!$B$2:$B$506,"*",Bets!$F$2:$F$506,"Friday") | P29: =IF(N29=0,"",O29/N29)
A30: Combined | B30: Saturday | C30: =COUNTIFS(Bets!$A$2:$A$506,"<>",Bets!$B$2:$B$506,"*",Bets!$F$2:$F$506,"Saturday") | D30: =COUNTIFS(Bets!$A$2:$A$506,"<>",Bets!$B$2:$B$506,"*",Bets!$F$2:$F$506,"Saturday",Bets!$U$2:$U$506,"W") | E30: =COUNTIFS(Bets!$A$2:$A$506,"<>",Bets!$B$2:$B$506,"*",Bets!$F$2:$F$506,"Saturday",Bets!$U$2:$U$506,"L") | F30: =COUNTIFS(Bets!$A$2:$A$506,"<>",Bets!$B$2:$B$506,"*",Bets!$F$2:$F$506,"Saturday",Bets!$U$2:$U$506,"Push") | G30: =COUNTIFS(Bets!$A$2:$A$506,"<>",Bets!$B$2:$B$506,"*",Bets!$F$2:$F$506,"Saturday",Bets!$U$2:$U$506,"Pending") | H30: =COUNTIFS(Bets!$A$2:$A$506,"<>",Bets!$B$2:$B$506,"*",Bets!$F$2:$F$506,"Saturday",Bets!$U$2:$U$506,"Unknown") | I30: =IF(D30+E30=0,"",D30/(D30+E30)) | J30: =SUMIFS(Bets!$Q$2:$Q$506,Bets!$A$2:$A$506,"<>",Bets!$B$2:$B$506,"*",Bets!$F$2:$F$506,"Saturday") | K30: =SUMIFS(Bets!$AC$2:$AC$506,Bets!$A$2:$A$506,"<>",Bets!$B$2:$B$506,"*",Bets!$F$2:$F$506,"Saturday") | L30: =SUMIFS(Bets!$V$2:$V$506,Bets!$A$2:$A$506,"<>",Bets!$B$2:$B$506,"*",Bets!$F$2:$F$506,"Saturday") | M30: =IF(K30=0,"",L30/K30) | N30: =SUMIFS(Bets!$AD$2:$AD$506,Bets!$A$2:$A$506,"<>",Bets!$B$2:$B$506,"*",Bets!$F$2:$F$506,"Saturday") | O30: =SUMIFS(Bets!$W$2:$W$506,Bets!$A$2:$A$506,"<>",Bets!$B$2:$B$506,"*",Bets!$F$2:$F$506,"Saturday") | P30: =IF(N30=0,"",O30/N30)
